Workbook

Sheet Seed Methodology
B2: Seed methodology — how a pre-event strength value is derived
B3: Every method resolves to the same two fields the simulator consumes: a STRENGTH RANK within the field, and a CONFIDENCE grade. Confidence is separate from title volatility and does a different job — volatility says how much the title scrambles outcomes, confidence says how much we trust the seed. A weak seed widens the simulated spread even in a low-volatility title. Record also the snapshot date and whether the roster changed after it: a rating attaches to five players, not a logo.
B7: Method | C7: Conf. | D7: What it is | E7: When to use it | F7: Worked example | G7: Watch out for
B8: A · Actual seed / world rank | C8: A | D8: Published numeric ranking the ecosystem itself uses to invite or seed. | E8: First choice wherever it exists — gives ratings as well as ranks, so gaps are measurable. | F8: CS2 — Valve Regional Standings. Chess — FIDE / Chess.com rapid. | G8: Snapshot must predate the event; ratings attach to a roster.
B9: B · Most recent event / league form | C9: B | D9: Finishing order from a recent competition the same teams contested. | E9: Franchised or closed circuits where the field has just played each other. | F9: Black Ops 7 — CDL season standings. | G9: One event is a small sample; prefer a season table.
B10: C · Power ranking | C10: C | D10: Community or media composite ranking. | E10: Cross-region titles with no official ladder. | F10: PUBG, Dota 2 analyst tiering. | G10: Poor update cadence, opaque method. Record source and date.
B11: D · Cohort seeding (High/Med/Low) | C11: C | D11: Banded strength by region and international pedigree. | E11: Titles where regions rarely meet and ordinals would be false precision. | F11: LoL — LCK/LPL High; top LEC/AMER/PAC Med; rest Low. | G11: Sample WITHIN the band each run — never collapse a band to one rank.
B12: E · No credible seed | C12: D | D12: No usable pre-event signal exists. | E12: Declare it rather than forcing a proxy; simulator treats the field as flat. | F12: Warzone, Free Fire, Fortnite. | G12: Being explicit beats a fabricated seed that looks authoritative.
B14: PROPOSED METHOD PER TITLE — editable, for your approval
B15: Title | C15: TVI | D15: Method | E15: Proposed source | F15: Notes
B16: Counter-Strike 2 | C16: 52 | D16: A | E16: Valve Regional Standings (global snapshot) | F16: Ratings available — best-in-class source
B17: Chess | C17: 8 | D17: A | E17: FIDE / Chess.com rapid rating | F17: Elo is ideal simulator input
B18: Trackmania | C18: 22 | D18: A | E18: Elite Cup standings / TM world ranking
B19: Rocket League | C19: 26 | D19: B | E19: RLCS season standings
B20: Black Ops 7 | C20: 28 | D20: B | E20: CDL season standings | F20: Franchised — field has just played
B21: Rainbow Six Siege | C21: 30 | D21: B | E21: SI points / season standings
B22: Honor of Kings | C22: 32 | D22: B | E22: KPL season standings
B23: MLBB Women's | C23: 34 | D23: D | E23: Cohort: prior MWI final / ID-PH circuit High, knockout-pedigree regions Medium, expansion Low | F23: Proposed, needs approval — no cross-regional ranking exists
B24: Tekken 8 | C24: 36 | D24: C | E24: FGC / EWC ranking points
B25: CrossFire | C25: 38 | D25: B | E25: CFPL season standings
B26: League of Legends | C26: 40 | D26: D | E26: Cohort: LCK+LPL High / top LEC+AMER+PAC Med / rest Low | F26: Regions rarely meet
B27: Overwatch 2 | C27: 45 | D27: D | E27: Cohort: Korea S2 top 2 + NA/EMEA/China S2 winners High, Pacific + FACEIT Low, rest Medium | F27: Agreed rule
B28: Fatal Fury: CotW | C28: 45 | D28: C | E28: FGC circuit points | F28: Young title
B29: Valorant | C29: 50 | D29: D | E29: Cohort by region + VCT placement
B30: Dota 2 | C30: 55 | D30: C | E30: EPT standings
B31: Street Fighter 6 | C31: 58 | D31: C | E31: Capcom Pro Tour points
B32: MLBB (MSC) | C32: 60 | D32: B | E32: MPL regional standings
B33: PUBG | C33: 62 | D33: D | E33: Cohort: PGS Points seeds + title defender High, regional series seeds Medium | F33: PGS Points are global and comparable; regional PGC Points are not
B34: EA Sports FC 26 | C34: 65 | D34: C | E34: FC Pro rankings | F34: Weak predictor historically
B35: Teamfight Tactics | C35: 65 | D35: C | E35: TFT circuit points
B36: Free Fire | C36: 75 | D36: E | E36: — | F36: Regional fragmentation
B37: Warzone | C37: 75 | D37: E | E37: — | F37: Open qualification
B38: PUBG Mobile | C38: 78 | D38: C | E38: PMGC points
B39: Fortnite | C39: 80 | D39: E | E39: — | F39: Format changes yearly
B40: Apex Legends | C40: 82 | D40: C | E40: ALGS championship points | F40: Circuit points exist but weak predictor

Sheet Clubs
B2: Club registry — all Club Championship participants
B3: All 133 Club Championship-eligible clubs — i.e. every club that fielded more than one title at EWC26. Single-title clubs are excluded because they cannot score CC points. Every title tab joins on club_id.
B5: club_id | C5: Display name | D5: Aliases (semicolon separated) | E5: Titles fielded | F5: Qualified | G5: EWC26 CC points | H5: CC top 24
B6: team_falcons | C6: Team Falcons | D6: Riyadh Falcons; Falcons Vega; Falcons Vega MENA; Falcons Vega PH; Team Falcons PH | E6: 22 | F6: 22/25 | G6: 4600 | H6: Yes
B7: team_vitality | C7: Team Vitality | D7: Bigetron by Vitality; HavoK by Vitality; Bigetron MY by VIT | E7: 20 | F7: 17/25 | G7: 3300 | H7: Yes
B8: virtuspro | C8: Virtus.pro | D8: Virtus.pro Fe; Virtus.pro MENA | E8: 20 | F8: 13/25 | G8: 2200 | H8: Yes
B9: agal_international | C9: AG.AL International | D9: All Gamers; Anyone's Legend; AG Super Play; All Gamers Global | E9: 19 | F9: 18/25 | G9: 5300 | H9: Yes
B10: s8ul_esports | C10: S8UL Esports | D10: — | E10: 16 | F10: 6/25 | G10: 0
B11: twisted_minds | C11: Twisted Minds | D11: Twisted Minds ID; Twisted Minds VN; Twisted Minds PH; Twisted Minds Orchid | E11: 16 | F11: 9/25 | G11: 1900 | H11: Yes
B12: godlike | C12: GodLike | D12: — | E12: 15 | F12: 8/25 | G12: 0
B13: team_liquid | C13: Team Liquid | D13: Team Liquid ID; Team Liquid PH; Team Liquid Aqua | E13: 15 | F13: 10/25 | G13: 2700 | H13: Yes
B14: team_nemesis | C14: Team Nemesis | D14: — | E14: 15 | F14: 10/25 | G14: 0
B15: titan_esports_club | C15: Titan Esports Club | D15: — | E15: 15 | F15: 4/25 | G15: 0
B16: weibo_gaming | C16: Weibo Gaming | D16: — | E16: 15 | F16: 6/25 | G16: 1100 | H16: Yes
B17: ninjas_in_pyjamas | C17: Ninjas in Pyjamas | D17: — | E17: 14 | F17: 8/25 | G17: 0
B18: 9z_team | C18: 9z Team | D18: — | E18: 13 | F18: 2/25 | G18: 0
B19: aurora_gaming | C19: Aurora Gaming | D19: Aurora Avalanche; Aurora Storm; Aurora Gaming PH; Aurora Gaming (Serbia) | E19: 13 | F19: 11/25 | G19: 2150 | H19: Yes
B20: geng_esports | C20: Gen.G Esports | D20: — | E20: 13 | F20: 9/25 | G20: 0
B21: geekay_esports | C21: Geekay Esports | D21: — | E21: 12 | F21: 11/25 | G21: 0
B22: natus_vincere | C22: Natus Vincere | D22: Natus Vincere PH; Natus Vincere MY | E22: 12 | F22: 7/25 | G22: 2950 | H22: Yes
B23: the_vicious | C23: The Vicious | D23: — | E23: 12 | F23: 4/25 | G23: 0
B24: fnatic | C24: Fnatic | D24: — | E24: 11 | F24: 6/25 | G24: 0
B25: t1 | C25: T1 | D25: — | E25: 11 | F25: 7/25 | G25: 1800 | H25: Yes
B26: team_spirit | C26: Team Spirit | D26: — | E26: 11 | F26: 3/25 | G26: 2200 | H26: Yes
B27: team_vision | C27: Team Vision | D27: Vision Esports | E27: 11 | F27: 2/25 | G27: 1750 | H27: Yes
B28: furia | C28: FURIA | D28: FURIA Esports | E28: 10 | F28: 6/25 | G28: 1050 | H28: Yes
B29: fut_esports | C29: FUT Esports | D29: — | E29: 10 | F29: 5/25 | G29: 0
B30: rex_regum_qeon | C30: Rex Regum Qeon | D30: — | E30: 10 | F30: 5/25 | G30: 0
B31: team_spirit | C31: Team Spirit | D31: — | E31: 10 | F31: 4/25 | G31: 2200 | H31: Yes
B32: jd_gaming | C32: JD Gaming | D32: — | E32: 9 | F32: 6/25 | G32: 0
B33: leviatán | C33: Leviatán | D33: — | E33: 9 | F33: 4/25 | G33: 0
B34: onic | C34: ONIC | D34: — | E34: 9 | F34: 5/25 | G34: 0
B35: reject | C35: REJECT | D35: — | E35: 9 | F35: 5/25 | G35: 1000 | H35: Yes
B36: team_heretics | C36: Team Heretics | D36: Miami Heretics | E36: 9 | F36: 6/25 | G36: 950 | H36: Yes
B37: edward_gaming | C37: EDward Gaming | D37: — | E37: 8 | F37: 2/25 | G37: 0
B38: mibrlos | C38: MIBR.LOS | D38: — | E38: 8 | F38: 8/25 | G38: 0
B39: roc_esports | C39: ROC Esports | D39: — | E39: 8 | F39: 4/25 | G39: 0
B40: wolves_esports | C40: Wolves Esports | D40: — | E40: 8 | F40: 2/25 | G40: 0
B41: zeta_division | C41: ZETA DIVISION | D41: — | E41: 8 | F41: 5/25 | G41: 1500 | H41: Yes
B42: drx | C42: DRX | D42: — | E42: 7 | F42: 3/25 | G42: 950 | H42: Yes
B43: fluxo_w7m | C43: Fluxo W7M | D43: — | E43: 7 | F43: 1/25 | G43: 0
B44: g2_esports | C44: G2 Esports | D44: G2 Minnesota | E44: 7 | F44: 5/25 | G44: 1200 | H44: Yes
B45: gentle_mates | C45: Gentle Mates | D45: — | E45: 7 | F45: 4/25 | G45: 0
B46: team_falcons | C46: Team Falcons | D46: Riyadh Falcons; Falcons Vega; Falcons Vega MENA; Falcons Vega PH; Team Falcons PH | E46: 7 | F46: 3/25 | G46: 4600 | H46: Yes
B47: full_sense | C47: FULL SENSE | D47: — | E47: 6 | F47: 1/25 | G47: 0
B48: lgd_gaming | C48: LGD Gaming | D48: — | E48: 6 | F48: 1/25 | G48: 0
B49: mouz | C49: MOUZ | D49: — | E49: 6 | F49: 3/25 | G49: 0
B50: r8_esports | C50: R8 Esports | D50: — | E50: 6 | F50: 2/25 | G50: 0
B51: shopify_rebellion | C51: Shopify Rebellion | D51: — | E51: 6 | F51: 3/25 | G51: 0
B52: 100_thieves | C52: 100 Thieves | D52: Los Angeles Thieves; Crazy Thieves | E52: 5 | F52: 2/25 | G52: 1500 | H52: Yes
B53: al_ula_club | C53: Al-Ula Club | D53: — | E53: 5 | F53: 2/25 | G53: 0
B54: alpha7_esports | C54: Alpha7 Esports | D54: — | E54: 5 | F54: 2/25 | G54: 0
B55: crazy_raccoon | C55: Crazy Raccoon | D55: — | E55: 5 | F55: 2/25 | G55: 0
B56: detonation_focusme | C56: DetonatioN FocusMe | D56: — | E56: 5 | F56: 2/25 | G56: 0
B57: dplus | C57: Dplus | D57: — | E57: 5 | F57: 1/25 | G57: 0
B58: eko_esports | C58: EKO Esports | D58: — | E58: 5 | F58: 1/25 | G58: 0
B59: flyquest | C59: FlyQuest | D59: — | E59: 5 | F59: 1/25 | G59: 0
B60: gam_esports | C60: GAM Esports | D60: — | E60: 5 | F60: 2/25 | G60: 0
B61: kinotrope_gaming | C61: KINOTROPE gaming | D61: — | E61: 5 | F61: 1/25 | G61: 0
B62: loud | C62: LOUD | D62: — | E62: 5 | F62: 1/25 | G62: 0
B63: novo_esports | C63: NOVO Esports | D63: — | E63: 5 | F63: 2/25 | G63: 0
B64: nongshim_redforce | C64: Nongshim RedForce | D64: — | E64: 5 | F64: 4/25 | G64: 1250 | H64: Yes
B65: revenant_xspark | C65: Revenant XSpark | D65: — | E65: 5 | F65: 1/25 | G65: 0
B66: s2g_esports | C66: S2G Esports | D66: — | E66: 5 | F66: 1/25 | G66: 0
B67: soopers | C67: SOOPers | D67: — | E67: 5 | F67: 2/25 | G67: 0
B68: sentinels | C68: Sentinels | D68: — | E68: 5 | F68: 3/25 | G68: 0
B69: varrel | C69: VARREL | D69: — | E69: 5 | F69: 4/25 | G69: 0
B70: zedi_esports | C70: ZEDI ESPORTS | D70: — | E70: 5 | F70: 2/25 | G70: 0
B71: al_ahli_esports | C71: Al Ahli Esports | D71: — | E71: 4 | F71: 2/25 | G71: 0
B72: al_qadsiah | C72: Al Qadsiah | D72: — | E72: 4 | F72: 2/25 | G72: 0
B73: big | C73: BIG | D73: — | E73: 4 | F73: 2/25 | G73: 1200 | H73: Yes
B74: buriram_united_esports | C74: Buriram United Esports | D74: — | E74: 4 | F74: 2/25 | G74: 0
B75: cloud9 | C75: Cloud9 | D75: — | E75: 4 | F75: 1/25 | G75: 0
B76: enter_force36 | C76: ENTER FORCE.36 | D76: — | E76: 4 | F76: 1/25 | G76: 0
B77: faze_clan | C77: FaZe Clan | D77: FaZe Vegas | E77: 4 | F77: 3/25 | G77: 1200 | H77: Yes
B78: flash_wolves | C78: Flash Wolves | D78: — | E78: 4 | F78: 1/25 | G78: 0
B79: four_angry_men | C79: Four Angry Men | D79: — | E79: 4 | F79: 1/25 | G79: 0
B80: influence_rage | C80: INFLUENCE RAGE | D80: — | E80: 4 | F80: 1/25 | G80: 0
B81: lyon | C81: LYON | D81: — | E81: 4 | F81: 2/25 | G81: 0
B82: m80 | C82: M80 | D82: — | E82: 4 | F82: 2/25 | G82: 0
B83: movistar_koi | C83: Movistar KOI | D83: — | E83: 4 | F83: 3/25 | G83: 0
B84: nrg | C84: NRG | D84: — | E84: 4 | F84: 2/25 | G84: 0
B85: ravens_esports | C85: Ravens Esports | D85: — | E85: 4 | F85: 1/25 | G85: 0
B86: tyloo | C86: TYLOO | D86: — | E86: 4 | F86: 3/25 | G86: 0
B87: team_orchid | C87: Team Orchid | D87: — | E87: 4 | F87: 1/25 | G87: 0
B88: team_spirit | C88: Team Spirit | D88: — | E88: 4 | F88: 4/25 | G88: 2200 | H88: Yes
B89: yangon_galacticos | C89: Yangon Galacticos | D89: — | E89: 4 | F89: 2/25 | G89: 0
B90: earena | C90: eArena | D90: — | E90: 4 | F90: 1/25 | G90: 0
B91: boom_esports | C91: BOOM Esports | D91: — | E91: 3 | F91: 1/25 | G91: 0
B92: deep_cross_gaming | C92: Deep Cross Gaming | D92: — | E92: 3 | F92: 2/25 | G92: 0
B93: dignitas | C93: Dignitas | D93: — | E93: 3 | F93: 1/25 | G93: 0
B94: evos_esports | C94: EVOS Esports | D94: — | E94: 3 | F94: 1/25 | G94: 0
B95: elite_esports | C95: Elite Esports | D95: — | E95: 3 | F95: 3/25 | G95: 0
B96: for_fun_esports | C96: For Fun Esports | D96: — | E96: 3 | F96: 2/25 | G96: 0
B97: gaimin_gladiators | C97: Gaimin Gladiators | D97: — | E97: 3 | F97: 1/25 | G97: 0
B98: gamax_esports | C98: Gamax Esports | D98: — | E98: 3 | F98: 1/25 | G98: 0
B99: good_8_squad | C99: Good 8 Squad | D99: — | E99: 3 | F99: 2/25 | G99: 0
B100: karmine_corp | C100: Karmine Corp | D100: — | E100: 3 | F100: 3/25 | G100: 1050 | H100: Yes
B101: og | C101: OG | D101: — | E101: 3 | F101: 2/25 | G101: 0
B102: sharper_esports | C102: Sharper Esports | D102: — | E102: 3 | F102: 1/25 | G102: 0
...

Sheet CS2
B2: Counter-Strike 2 — EWC 2026
B3: TEMPLATE TAB — copy this sheet for every new title. Three stacked blocks: 1) field & results, 2) point system, 3) seed reference. All CS2 data below is VERIFIED against liquipedia.net/counterstrike/Esports_World_Cup/2026.
B5: FORMAT | D5: FIELD SIZE | F5: TVI | H5: SEED METHOD | J5: SEED SOURCE | L5: PLACEMENT GRANULARITY
B6: 4× GSL groups → 16-team single-elim | D6: 32 (confirmed) | F6: 52 · Medium | H6: A — world rank | J6: Valve VRS global, 3 Aug 2026 (latest pre-event) | L6: Bands (5-8, 9-16, 17-32 share points)
B8: 1 · FIELD & RESULTS
B9: Complete 32-team field, sorted by finishing position. Placements and point table taken from the Liquipedia event page; seeds from Valve's latest pre-event VRS (3 Aug 2026), which reflects form better than the June invite snapshot. June ranks retained in block 3 for reference. Points auto-calculate from block 2 and are checked against official CC points.
B10: Club | C10: Seed (VRS Aug) | D10: Group | E10: Placement | F10: Points (auto) | G10: Official CC pts | H10: Δ check | I10: Prize (USD) | J10: Notes | L10: Club (canonical)
B11: Team Spirit | C11: 1 | D11: A | E11: 1 | F11: =IF($E11="","",IFERROR(LOOKUP(VALUE(LEFT($E11&"",FIND("-",$E11&"-")-1)),$C$54:$C$59,$D$54:$D$59),"")) -> 1000 | G11: 1000 | H11: =IF($G11="","n/a",IF($F11=$G11,"ok","MISMATCH")) -> ok | I11: 600000 | L11: Team Spirit
B12: FUT Esports | C12: 14 | D12: C | E12: 2 | F12: =IF($E12="","",IFERROR(LOOKUP(VALUE(LEFT($E12&"",FIND("-",$E12&"-")-1)),$C$54:$C$59,$D$54:$D$59),"")) -> 750 | G12: 750 | H12: =IF($G12="","n/a",IF($F12=$G12,"ok","MISMATCH")) -> ok | I12: 340000 | L12: FUT Esports
B13: Legacy | C13: 7 | D13: B | E13: 3 | F13: =IF($E13="","",IFERROR(LOOKUP(VALUE(LEFT($E13&"",FIND("-",$E13&"-")-1)),$C$54:$C$59,$D$54:$D$59),"")) -> 500 | G13: 500 | H13: =IF($G13="","n/a",IF($F13=$G13,"ok","MISMATCH")) -> ok | I13: 190000 | L13: Legacy
B14: FURIA | C14: 8 | D14: D | E14: 4 | F14: =IF($E14="","",IFERROR(LOOKUP(VALUE(LEFT($E14&"",FIND("-",$E14&"-")-1)),$C$54:$C$59,$D$54:$D$59),"")) -> 300 | G14: 300 | H14: =IF($G14="","n/a",IF($F14=$G14,"ok","MISMATCH")) -> ok | I14: 110000 | L14: FURIA
B15: G2 Esports | C15: 11 | D15: A | E15: 5-8 | F15: =IF($E15="","",IFERROR(LOOKUP(VALUE(LEFT($E15&"",FIND("-",$E15&"-")-1)),$C$54:$C$59,$D$54:$D$59),"")) -> 200 | G15: 200 | H15: =IF($G15="","n/a",IF($F15=$G15,"ok","MISMATCH")) -> ok | I15: 60000 | L15: G2 Esports
B16: MOUZ | C16: 3 | D16: C | E16: 5-8 | F16: =IF($E16="","",IFERROR(LOOKUP(VALUE(LEFT($E16&"",FIND("-",$E16&"-")-1)),$C$54:$C$59,$D$54:$D$59),"")) -> 200 | G16: 200 | H16: =IF($G16="","n/a",IF($F16=$G16,"ok","MISMATCH")) -> ok | I16: 60000 | L16: MOUZ
B17: Team Falcons | C17: 2 | D17: B | E17: 5-8 | F17: =IF($E17="","",IFERROR(LOOKUP(VALUE(LEFT($E17&"",FIND("-",$E17&"-")-1)),$C$54:$C$59,$D$54:$D$59),"")) -> 200 | G17: 200 | H17: =IF($G17="","n/a",IF($F17=$G17,"ok","MISMATCH")) -> ok | I17: 60000 | L17: Team Falcons
B18: Team Vitality | C18: 5 | D18: C | E18: 5-8 | F18: =IF($E18="","",IFERROR(LOOKUP(VALUE(LEFT($E18&"",FIND("-",$E18&"-")-1)),$C$54:$C$59,$D$54:$D$59),"")) -> 200 | G18: 200 | H18: =IF($G18="","n/a",IF($F18=$G18,"ok","MISMATCH")) -> ok | I18: 60000 | L18: Team Vitality
B19: GamerLegion | C19: 22 | D19: A | E19: 9-16 | F19: =IF($E19="","",IFERROR(LOOKUP(VALUE(LEFT($E19&"",FIND("-",$E19&"-")-1)),$C$54:$C$59,$D$54:$D$59),"")) -> 0 | H19: =IF($G19="","n/a",IF($F19=$G19,"ok","MISMATCH")) -> n/a | J19: moved 9→22 between June invite list and event | L19: GamerLegion
B20: Aurora Gaming | C20: 10 | D20: A | E20: 9-16 | F20: =IF($E20="","",IFERROR(LOOKUP(VALUE(LEFT($E20&"",FIND("-",$E20&"-")-1)),$C$54:$C$59,$D$54:$D$59),"")) -> 0 | G20: 0 | H20: =IF($G20="","n/a",IF($F20=$G20,"ok","MISMATCH")) -> ok | L20: Aurora Gaming
B21: FaZe Clan | C21: 13 | D21: B | E21: 9-16 | F21: =IF($E21="","",IFERROR(LOOKUP(VALUE(LEFT($E21&"",FIND("-",$E21&"-")-1)),$C$54:$C$59,$D$54:$D$59),"")) -> 0 | G21: 0 | H21: =IF($G21="","n/a",IF($F21=$G21,"ok","MISMATCH")) -> ok | J21: moved 22→13 between June invite list and event | L21: FaZe Clan
B22: Astralis | C22: 19 | D22: B | E22: 9-16 | F22: =IF($E22="","",IFERROR(LOOKUP(VALUE(LEFT($E22&"",FIND("-",$E22&"-")-1)),$C$54:$C$59,$D$54:$D$59),"")) -> 0 | H22: =IF($G22="","n/a",IF($F22=$G22,"ok","MISMATCH")) -> n/a | J22: moved 10→19 between June invite list and event | L22: Astralis
B23: B8 | C23: 20 | D23: C | E23: 9-16 | F23: =IF($E23="","",IFERROR(LOOKUP(VALUE(LEFT($E23&"",FIND("-",$E23&"-")-1)),$C$54:$C$59,$D$54:$D$59),"")) -> 0 | H23: =IF($G23="","n/a",IF($F23=$G23,"ok","MISMATCH")) -> n/a | L23: B8
B24: Natus Vincere | C24: 6 | D24: D | E24: 9-16 | F24: =IF($E24="","",IFERROR(LOOKUP(VALUE(LEFT($E24&"",FIND("-",$E24&"-")-1)),$C$54:$C$59,$D$54:$D$59),"")) -> 0 | G24: 0 | H24: =IF($G24="","n/a",IF($F24=$G24,"ok","MISMATCH")) -> ok | L24: Natus Vincere
B25: magic | C25: 23 | D25: D | E25: 9-16 | F25: =IF($E25="","",IFERROR(LOOKUP(VALUE(LEFT($E25&"",FIND("-",$E25&"-")-1)),$C$54:$C$59,$D$54:$D$59),"")) -> 0 | H25: =IF($G25="","n/a",IF($F25=$G25,"ok","MISMATCH")) -> n/a | L25: magic
B26: The MongolZ | C26: 15 | D26: D | E26: 9-16 | F26: =IF($E26="","",IFERROR(LOOKUP(VALUE(LEFT($E26&"",FIND("-",$E26&"-")-1)),$C$54:$C$59,$D$54:$D$59),"")) -> 0 | H26: =IF($G26="","n/a",IF($F26=$G26,"ok","MISMATCH")) -> n/a | J26: moved 7→15 between June invite list and event | L26: The MongolZ
B27: JiJieHao | C27: 58 | D27: A | E27: 17-32 | F27: =IF($E27="","",IFERROR(LOOKUP(VALUE(LEFT($E27&"",FIND("-",$E27&"-")-1)),$C$54:$C$59,$D$54:$D$59),"")) -> 0 | H27: =IF($G27="","n/a",IF($F27=$G27,"ok","MISMATCH")) -> n/a | J27: moved 44→58 between June invite list and event | L27: JiJieHao
B28: Luminosity | C28: 24 | D28: A | E28: 17-32 | F28: =IF($E28="","",IFERROR(LOOKUP(VALUE(LEFT($E28&"",FIND("-",$E28&"-")-1)),$C$54:$C$59,$D$54:$D$59),"")) -> 0 | H28: =IF($G28="","n/a",IF($F28=$G28,"ok","MISMATCH")) -> n/a | J28: no June VRS entry — returned to CS2 in July 2026 | L28: Luminosity
B29: M80 | C29: 36 | D29: A | E29: 17-32 | F29: =IF($E29="","",IFERROR(LOOKUP(VALUE(LEFT($E29&"",FIND("-",$E29&"-")-1)),$C$54:$C$59,$D$54:$D$59),"")) -> 0 | H29: =IF($G29="","n/a",IF($F29=$G29,"ok","MISMATCH")) -> n/a | L29: M80
B30: BIG | C30: 21 | D30: A | E30: 17-32 | F30: =IF($E30="","",IFERROR(LOOKUP(VALUE(LEFT($E30&"",FIND("-",$E30&"-")-1)),$C$54:$C$59,$D$54:$D$59),"")) -> 0 | G30: 0 | H30: =IF($G30="","n/a",IF($F30=$G30,"ok","MISMATCH")) -> ok | J30: moved 28→21 between June invite list and event | L30: BIG
B31: K27 | C31: 39 | D31: B | E31: 17-32 | F31: =IF($E31="","",IFERROR(LOOKUP(VALUE(LEFT($E31&"",FIND("-",$E31&"-")-1)),$C$54:$C$59,$D$54:$D$59),"")) -> 0 | H31: =IF($G31="","n/a",IF($F31=$G31,"ok","MISMATCH")) -> n/a | L31: K27
B32: MIBR | C32: 16 | D32: B | E32: 17-32 | F32: =IF($E32="","",IFERROR(LOOKUP(VALUE(LEFT($E32&"",FIND("-",$E32&"-")-1)),$C$54:$C$59,$D$54:$D$59),"")) -> 0 | H32: =IF($G32="","n/a",IF($F32=$G32,"ok","MISMATCH")) -> n/a | L32: MIBR.LOS
B33: BetBoom | C33: 9 | D33: B | E33: 17-32 | F33: =IF($E33="","",IFERROR(LOOKUP(VALUE(LEFT($E33&"",FIND("-",$E33&"-")-1)),$C$54:$C$59,$D$54:$D$59),"")) -> 0 | H33: =IF($G33="","n/a",IF($F33=$G33,"ok","MISMATCH")) -> n/a | J33: moved 17→9 between June invite list and event | L33: BetBoom
B34: Ninjas in Pyjamas | C34: 27 | D34: B | E34: 17-32 | F34: =IF($E34="","",IFERROR(LOOKUP(VALUE(LEFT($E34&"",FIND("-",$E34&"-")-1)),$C$54:$C$59,$D$54:$D$59),"")) -> 0 | G34: 0 | H34: =IF($G34="","n/a",IF($F34=$G34,"ok","MISMATCH")) -> ok | L34: Ninjas in Pyjamas
B35: 100 Thieves | C35: 40 | D35: C | E35: 17-32 | F35: =IF($E35="","",IFERROR(LOOKUP(VALUE(LEFT($E35&"",FIND("-",$E35&"-")-1)),$C$54:$C$59,$D$54:$D$59),"")) -> 0 | G35: 0 | H35: =IF($G35="","n/a",IF($F35=$G35,"ok","MISMATCH")) -> ok | J35: moved 47→40 between June invite list and event | L35: 100 Thieves
B36: PARIVISION | C36: 12 | D36: C | E36: 17-32 | F36: =IF($E36="","",IFERROR(LOOKUP(VALUE(LEFT($E36&"",FIND("-",$E36&"-")-1)),$C$54:$C$59,$D$54:$D$59),"")) -> 0 | G36: 0 | H36: =IF($G36="","n/a",IF($F36=$G36,"ok","MISMATCH")) -> ok | L36: PARIVISION
B37: TYLOO | C37: 18 | D37: C | E37: 17-32 | F37: =IF($E37="","",IFERROR(LOOKUP(VALUE(LEFT($E37&"",FIND("-",$E37&"-")-1)),$C$54:$C$59,$D$54:$D$59),"")) -> 0 | H37: =IF($G37="","n/a",IF($F37=$G37,"ok","MISMATCH")) -> n/a | J37: moved 32→18 between June invite list and event | L37: TYLOO
B38: Lynn Vision | C38: 29 | D38: C | E38: 17-32 | F38: =IF($E38="","",IFERROR(LOOKUP(VALUE(LEFT($E38&"",FIND("-",$E38&"-")-1)),$C$54:$C$59,$D$54:$D$59),"")) -> 0 | H38: =IF($G38="","n/a",IF($F38=$G38,"ok","MISMATCH")) -> n/a | L38: Lynn Vision
B39: 3DMAX | C39: 31 | D39: D | E39: 17-32 | F39: =IF($E39="","",IFERROR(LOOKUP(VALUE(LEFT($E39&"",FIND("-",$E39&"-")-1)),$C$54:$C$59,$D$54:$D$59),"")) -> 0 | H39: =IF($G39="","n/a",IF($F39=$G39,"ok","MISMATCH")) -> n/a | L39: 3DMAX
B40: 9z | C40: 4 | D40: D | E40: 17-32 | F40: =IF($E40="","",IFERROR(LOOKUP(VALUE(LEFT($E40&"",FIND("-",$E40&"-")-1)),$C$54:$C$59,$D$54:$D$59),"")) -> 0 | H40: =IF($G40="","n/a",IF($F40=$G40,"ok","MISMATCH")) -> n/a | J40: moved 15→4 between June invite list and event | L40: 9z Team
B41: paiN | C41: 26 | D41: D | E41: 17-32 | F41: =IF($E41="","",IFERROR(LOOKUP(VALUE(LEFT($E41&"",FIND("-",$E41&"-")-1)),$C$54:$C$59,$D$54:$D$59),"")) -> 0 | H41: =IF($G41="","n/a",IF($F41=$G41,"ok","MISMATCH")) -> n/a | J41: moved 19→26 between June invite list and event | L41: paiN
B42: Wildcard | C42: 38 | D42: D | E42: 17-32 | F42: =IF($E42="","",IFERROR(LOOKUP(VALUE(LEFT($E42&"",FIND("-",$E42&"-")-1)),$C$54:$C$59,$D$54:$D$59),"")) -> 0 | G42: 0 | H42: =IF($G42="","n/a",IF($F42=$G42,"ok","MISMATCH")) -> ok | J42: moved 25→38 between June invite list and event | L42: Wildcard
B44: TOTAL POINTS AWARDED | F44: =SUM(F11:F42) -> 3350
B45: Confirmed total: 1000+750+500+300+(200×4) = 3,350.
B51: 2 · POINT SYSTEM
B52: CONFIRMED from the Liquipedia event page prize-pool table. Note for other titles: 150- and 50-pt awards appear ONLY in battle royales — playoff titles pay nothing below 8th.
B53: From place | C53: Club points | D53: Band
C54: 1 | D54: 1000 | E54: 1st
C55: 2 | D55: 750 | E55: 2nd
C56: 3 | D56: 500 | E56: 3rd
C57: 4 | D57: 300 | E57: 4th
C58: 5 | D58: 200 | E58: 5th–8th
C59: 9 | D59: 0 | E59: 9th–32nd — confirmed no award
B62: 3 · SEED REFERENCE — Valve Regional Standings (June = invite basis, August = pre-event form)
B63: Source: github.com/ValveSoftware/counter-strike_regional_standings — official, public, versioned. Liquipedia records the invite basis as the June 2026 VRS; August shown alongside to expose form movement between seeding and the event.
B64: Team | C64: Jun rank | D64: Jun rating | E64: Aug rank | F64: Aug rating | G64: Movement
B65: Team Spirit | C65: 2 | D65: 1990 | E65: 1 | F65: 2011 | G65: 1
B66: FUT Esports | C66: 12 | D66: 1694 | E66: 14 | F66: 1663 | G66: -2
B67: Legacy | C67: 6 | D67: 1856 | E67: 7 | F67: 1773 | G67: -1
B68: FURIA | C68: 11 | D68: 1716 | E68: 8 | F68: 1771 | G68: 3
B69: G2 Esports | C69: 13 | D69: 1683 | E69: 11 | F69: 1688 | G69: 2
B70: MOUZ | C70: 5 | D70: 1859 | E70: 3 | F70: 1873 | G70: 2
B71: Team Falcons | C71: 3 | D71: 1954 | E71: 2 | F71: 1950 | G71: 1
B72: Team Vitality | C72: 1 | D72: 2024 | E72: 5 | F72: 1836 | G72: -4
B73: GamerLegion | C73: 9 | D73: 1724 | E73: 22 | F73: 1504 | G73: -13
B74: Aurora Gaming | C74: 8 | D74: 1741 | E74: 10 | F74: 1690 | G74: -2
B75: FaZe Clan | C75: 22 | D75: 1492 | E75: 13 | F75: 1677 | G75: 9
B76: Astralis | C76: 10 | D76: 1721 | E76: 19 | F76: 1555 | G76: -9
... B81: JiJieHao | C81: 44 | D81: 1315 | E81: 58 | F81: 1159 | G81: -14
B82: Luminosity | E82: 24 | F82: 1468
B83: M80 | C83: 33 | D83: 1385 | E83: 36 | F83: 1361 | G83: -3
B84: BIG | C84: 28 | D84: 1416 | E84: 21 | F84: 1516 | G84: 7
B85: K27 | C85: 42 | D85: 1323 | E85: 39 | F85: 1319 | G85: 3
B86: MIBR | C86: 20 | D86: 1535 | E86: 16 | F86: 1611 | G86: 4
B87: BetBoom | C87: 17 | D87: 1562 | E87: 9 | F87: 1742 | G87: 8
B88: Ninjas in Pyjamas | C88: 23 | D88: 1460 | E88: 27 | F88: 1444 | G88: -4
B89: 100 Thieves | C89: 47 | D89: 1275 | E89: 40 | F89: 1310 | G89: 7
B90: PARIVISION | C90: 14 | D90: 1679 | E90: 12 | F90: 1685 | G90: 2
B91: TYLOO | C91: 32 | D91: 1395 | E91: 18 | F91: 1565 | G91: 14
B92: Lynn Vision | C92: 24 | D92: 1443 | E92: 29 | F92: 1431 | G92: -5
B93: 3DMAX | C93: 26 | D93: 1429 | E93: 31 | F93: 1410 | G93: -5
B94: 9z | C94: 15 | D94: 1633 | E94: 4 | F94: 1847 | G94: 11
... B96: Wildcard | C96: 25 | D96: 1431 | E96: 38 | F96: 1352 | G96: -13

Sheet Chess
B2: Chess — EWC 2026
B3: Built on the CS2 template. Verified against liquipedia.net/chess/Esports_World_Cup/2026. Individual title: rows are PLAYERS, points accrue to their club.
B5: FORMAT | D5: FIELD SIZE | F5: TVI | H5: SEED METHOD | J5: SEED SOURCE | L5: PLACEMENT GRANULARITY
B6: Play-ins(8) → 2× groups of 8 → 8-player single-elim | D6: 22 players | F6: 8 · Low | H6: A — world rank | J6: FIDE rapid rating, August 2026 list | L6: Bands (5-8, 9-22 share points)
B8: 1 · FIELD & RESULTS
B9: All 22 players with exact placements from the Liquipedia prize table and seeds derived from the FIDE rapid rating list for August 2026 — a genuine pre-event snapshot, since EWC chess ran 11-15 August.
B10: Club | C10: Player | D10: Seed (rapid rank) | E10: Placement | F10: Points (auto) | G10: Official CC pts | H10: Δ check | I10: Prize (USD) | J10: Qualification route | L10: Club (canonical)
B11: Team Liquid | C11: Magnus Carlsen | D11: 1 | E11: 1 | F11: =IF($E11="","",IFERROR(LOOKUP(VALUE(LEFT($E11&"",FIND("-",$E11&"-")-1)),$C$44:$C$49,$D$44:$D$49),"")) -> 1000 | G11: 1000 | H11: =IF($G11="","n/a",IF($F11=$G11,"ok","MISMATCH")) -> ok | I11: 250000 | J11: EWC 2025 Champion | L11: Team Liquid
B12: AG.AL International | C12: Denis Lazavik | D12: 17 | E12: 2 | F12: =IF($E12="","",IFERROR(LOOKUP(VALUE(LEFT($E12&"",FIND("-",$E12&"-")-1)),$C$44:$C$49,$D$44:$D$49),"")) -> 750 | G12: 750 | H12: =IF($G12="","n/a",IF($F12=$G12,"ok","MISMATCH")) -> ok | I12: 190000 | J12: SCC 2025 / CCT points | L12: AG.AL International
B13: Team Falcons | C13: Hikaru Nakamura | D13: 4 | E13: 3 | F13: =IF($E13="","",IFERROR(LOOKUP(VALUE(LEFT($E13&"",FIND("-",$E13&"-")-1)),$C$44:$C$49,$D$44:$D$49),"")) -> 500 | G13: 500 | H13: =IF($G13="","n/a",IF($F13=$G13,"ok","MISMATCH")) -> ok | I13: 145000 | J13: CCT 2025-26 Circuit Points | L13: Team Falcons
B14: Team Falcons | C14: Alireza Firouzja | D14: 2 | E14: 4 | F14: =IF($E14="","",IFERROR(LOOKUP(VALUE(LEFT($E14&"",FIND("-",$E14&"-")-1)),$C$44:$C$49,$D$44:$D$49),"")) -> 300 | H14: =IF($G14="","n/a",IF($F14=$G14,"ok","MISMATCH")) -> n/a | I14: 100000 | J14: SCC 2025 | L14: Team Falcons
B15: S8UL Esports | C15: Nihal Sarin | D15: 9 | E15: 5-8 | F15: =IF($E15="","",IFERROR(LOOKUP(VALUE(LEFT($E15&"",FIND("-",$E15&"-")-1)),$C$44:$C$49,$D$44:$D$49),"")) -> 200 | G15: 200 | H15: =IF($G15="","n/a",IF($F15=$G15,"ok","MISMATCH")) -> ok | I15: 72500 | J15: CCT 2025-26 Circuit Points | L15: S8UL Esports
B16: GodLike Esports | C16: Hans Moke Niemann | D16: 12 | E16: 5-8 | F16: =IF($E16="","",IFERROR(LOOKUP(VALUE(LEFT($E16&"",FIND("-",$E16&"-")-1)),$C$44:$C$49,$D$44:$D$49),"")) -> 200 | H16: =IF($G16="","n/a",IF($F16=$G16,"ok","MISMATCH")) -> n/a | I16: 72500 | J16: CCT 2025-26 Circuit Points | L16: GodLike
B17: Natus Vincere | C17: Nodirbek Abdusattorov | D17: 8 | E17: 5-8 | F17: =IF($E17="","",IFERROR(LOOKUP(VALUE(LEFT($E17&"",FIND("-",$E17&"-")-1)),$C$44:$C$49,$D$44:$D$49),"")) -> 200 | G17: 200 | H17: =IF($G17="","n/a",IF($F17=$G17,"ok","MISMATCH")) -> ok | I17: 72500 | J17: CCT 2025-26 Circuit Points | L17: Natus Vincere
B18: Gen.G Esports | C18: Arjun Erigaisi | D18: 3 | E18: 5-8 | F18: =IF($E18="","",IFERROR(LOOKUP(VALUE(LEFT($E18&"",FIND("-",$E18&"-")-1)),$C$44:$C$49,$D$44:$D$49),"")) -> 200 | G18: 200 | H18: =IF($G18="","n/a",IF($F18=$G18,"ok","MISMATCH")) -> ok | I18: 72500 | J18: CCT points (replacement for Caruana) | L18: Gen.G Esports
B19: Weibo Gaming | C19: Jan-Krzysztof Duda | D19: 11 | E19: 9-12 | F19: =IF($E19="","",IFERROR(LOOKUP(VALUE(LEFT($E19&"",FIND("-",$E19&"-")-1)),$C$44:$C$49,$D$44:$D$49),"")) -> 0 | G19: 0 | H19: =IF($G19="","n/a",IF($F19=$G19,"ok","MISMATCH")) -> ok | I19: 52500 | J19: Chess.com Open 2026 | L19: Weibo Gaming
B20: S8UL Esports | C20: Pranesh M | D20: 21 | E20: 9-12 | F20: =IF($E20="","",IFERROR(LOOKUP(VALUE(LEFT($E20&"",FIND("-",$E20&"-")-1)),$C$44:$C$49,$D$44:$D$49),"")) -> 0 | H20: =IF($G20="","n/a",IF($F20=$G20,"ok","MISMATCH")) -> n/a | I20: 52500 | J20: CCT points (replacement for MVL) | L20: S8UL Esports
B21: Aurora Gaming | C21: Ian Nepomniachtchi | D21: 5 | E21: 9-12 | F21: =IF($E21="","",IFERROR(LOOKUP(VALUE(LEFT($E21&"",FIND("-",$E21&"-")-1)),$C$44:$C$49,$D$44:$D$49),"")) -> 0 | G21: 0 | H21: =IF($G21="","n/a",IF($F21=$G21,"ok","MISMATCH")) -> ok | I21: 52500 | J21: CCT 2025-26 Circuit Points | L21: Aurora Gaming
B22: Team Stallions | C22: Sina Movahed | D22: 22 | E22: 9-12 | F22: =IF($E22="","",IFERROR(LOOKUP(VALUE(LEFT($E22&"",FIND("-",$E22&"-")-1)),$C$44:$C$49,$D$44:$D$49),"")) -> 0 | G22: 0 | H22: =IF($G22="","n/a",IF($F22=$G22,"ok","MISMATCH")) -> ok | I22: 52500 | J22: CCT 2025-26 Circuit Points | L22: Team Stallions
B23: Team Nemesis | C23: Wei Yi | D23: 6 | E23: 13-16 | F23: =IF($E23="","",IFERROR(LOOKUP(VALUE(LEFT($E23&"",FIND("-",$E23&"-")-1)),$C$44:$C$49,$D$44:$D$49),"")) -> 0 | G23: 0 | H23: =IF($G23="","n/a",IF($F23=$G23,"ok","MISMATCH")) -> ok | I23: 40000 | J23: Last Chance Qualifier | L23: Team Nemesis
B24: Team MGD1 | C24: Benjamin Bok | D24: 20 | E24: 13-16 | F24: =IF($E24="","",IFERROR(LOOKUP(VALUE(LEFT($E24&"",FIND("-",$E24&"-")-1)),$C$44:$C$49,$D$44:$D$49),"")) -> 0 | H24: =IF($G24="","n/a",IF($F24=$G24,"ok","MISMATCH")) -> n/a | I24: 40000 | J24: India Rising 2026 | L24: Team MGD1
B25: Virtus.pro | C25: Andrey Esipenko | D25: 14 | E25: 13-16 | F25: =IF($E25="","",IFERROR(LOOKUP(VALUE(LEFT($E25&"",FIND("-",$E25&"-")-1)),$C$44:$C$49,$D$44:$D$49),"")) -> 0 | G25: 0 | H25: =IF($G25="","n/a",IF($F25=$G25,"ok","MISMATCH")) -> ok | I25: 40000 | J25: DH Atlanta | L25: Virtus.pro
B26: Fnatic | C26: Alexey Sarana | D26: 15 | E26: 13-16 | F26: =IF($E26="","",IFERROR(LOOKUP(VALUE(LEFT($E26&"",FIND("-",$E26&"-")-1)),$C$44:$C$49,$D$44:$D$49),"")) -> 0 | G26: 0 | H26: =IF($G26="","n/a",IF($F26=$G26,"ok","MISMATCH")) -> ok | I26: 40000 | J26: DH Atlanta / higher seed via CCT | L26: Fnatic
B27: Team Spirit | C27: Vladislav Artemiev | D27: 7 | E27: 17 | F27: =IF($E27="","",IFERROR(LOOKUP(VALUE(LEFT($E27&"",FIND("-",$E27&"-")-1)),$C$44:$C$49,$D$44:$D$49),"")) -> 0 | G27: 0 | H27: =IF($G27="","n/a",IF($F27=$G27,"ok","MISMATCH")) -> ok | I27: 32000 | J27: Last Chance Qualifier | L27: Team Spirit
B28: (no club) | C28: Parham Maghsoodloo | D28: 10 | E28: 18 | F28: =IF($E28="","",IFERROR(LOOKUP(VALUE(LEFT($E28&"",FIND("-",$E28&"-")-1)),$C$44:$C$49,$D$44:$D$49),"")) -> 0 | H28: =IF($G28="","n/a",IF($F28=$G28,"ok","MISMATCH")) -> n/a | I28: 27000 | J28: Last Chance Qualifier | L28: (no club)
B29: (no club) | C29: Olexandr Bortnyk | D29: 18 | E29: 19-20 | F29: =IF($E29="","",IFERROR(LOOKUP(VALUE(LEFT($E29&"",FIND("-",$E29&"-")-1)),$C$44:$C$49,$D$44:$D$49),"")) -> 0 | H29: =IF($G29="","n/a",IF($F29=$G29,"ok","MISMATCH")) -> n/a | I29: 25000 | J29: Last Chance Qualifier | L29: (no club)
B30: (no club) | C30: Alexander Grischuk | D30: 13 | E30: 19-20 | F30: =IF($E30="","",IFERROR(LOOKUP(VALUE(LEFT($E30&"",FIND("-",$E30&"-")-1)),$C$44:$C$49,$D$44:$D$49),"")) -> 0 | H30: =IF($G30="","n/a",IF($F30=$G30,"ok","MISMATCH")) -> n/a | I30: 25000 | J30: Last Chance Qualifier | L30: (no club)
B31: S8UL Esports | C31: Aravindh Chithambaram | D31: 19 | E31: 21-22 | F31: =IF($E31="","",IFERROR(LOOKUP(VALUE(LEFT($E31&"",FIND("-",$E31&"-")-1)),$C$44:$C$49,$D$44:$D$49),"")) -> 0 | H31: =IF($G31="","n/a",IF($F31=$G31,"ok","MISMATCH")) -> n/a | I31: 23000 | J31: DH Atlanta | L31: S8UL Esports
B32: Team Flash | C32: Lê Quang Liêm | D32: 16 | E32: 21-22 | F32: =IF($E32="","",IFERROR(LOOKUP(VALUE(LEFT($E32&"",FIND("-",$E32&"-")-1)),$C$44:$C$49,$D$44:$D$49),"")) -> 0 | H32: =IF($G32="","n/a",IF($F32=$G32,"ok","MISMATCH")) -> n/a | I32: 23000 | J32: DH Atlanta | L32: Team Flash
B34: TOTAL POINTS AWARDED | F34: =SUM(F11:F32) -> 3350
B35: 1000+750+500+300+(200×4) = 3,350 awarded to players. Club totals differ: a club scores only its BEST placement per title — Falcons had both Nakamura (3rd) and Firouzja (4th) but scored 500, not 800.
B41: 2 · POINT SYSTEM
B42: Read directly from the Liquipedia prize-pool table, which lists club points and prize money for every placement band down to 21st–22nd. Club points stop after 8th; prize money continues to 22nd (all $1.5M accounted for).
B43: From place | C43: Club points | D43: Band
C44: 1 | D44: 1000 | E44: 1st
C45: 2 | D45: 750 | E45: 2nd
C46: 3 | D46: 500 | E46: 3rd
C47: 4 | D47: 300 | E47: 4th
C48: 5 | D48: 200 | E48: 5th-8th
C49: 9 | D49: 0 | E49: 9th-22nd (prize money only)
B52: 3 · SEED REFERENCE — FIDE rapid rating list, August 2026
B53: Source: ratings.fide.com, official rapid list for the August 2026 period (the last published before the event). Rapid is the format played at EWC — standard and blitz ratings are different scales and must not be mixed in. Four players sit outside the world top 100; their ratings come from their national rapid lists for the same period, so world rank is not available for them but the rating itself is directly comparable.
B54: Seed | C54: Player | D54: Rapid rating | E54: World rank | F54: Placement | G54: Seed − result
B55: 1 | C55: Magnus Carlsen | D55: 2803 | E55: 1 | F55: 1 | G55: 0
B56: 2 | C56: Alireza Firouzja | D56: 2749 | E56: 3 | F56: 4 | G56: -2
B57: 3 | C57: Arjun Erigaisi | D57: 2745 | E57: 4 | F57: 5-8 | G57: -2
B58: 4 | C58: Hikaru Nakamura | D58: 2738 | E58: 5 | F58: 3 | G58: 1
B59: 5 | C59: Ian Nepomniachtchi | D59: 2729 | E59: 7 | F59: 9-12 | G59: -4
B60: 6 | C60: Wei Yi | D60: 2726 | E60: 8 | F60: 13-16 | G60: -7
B61: 7 | C61: Vladislav Artemiev | D61: 2709 | E61: 10 | F61: 17 | G61: -10
B62: 8 | C62: Nodirbek Abdusattorov | D62: 2706 | E62: 11 | F62: 5-8 | G62: 3
B63: 9 | C63: Nihal Sarin | D63: 2698 | E63: 18 | F63: 5-8 | G63: 4
B64: 10 | C64: Parham Maghsoodloo | D64: 2689 | E64: 21 | F64: 18 | G64: -8
B65: 11 | C65: Jan-Krzysztof Duda | D65: 2685 | E65: 25 | F65: 9-12 | G65: 2
B66: 12 | C66: Hans Moke Niemann | D66: 2675 | E66: 28 | F66: 5-8 | G66: 7
... B72: 18 | C72: Olexandr Bortnyk | D72: 2607 | E72: 97 | F72: 19-20 | G72: -1
B73: 19 | C73: Aravindh Chithambaram | D73: 2604 | E73: — | F73: 21-22 | G73: -2
B74: 20 | C74: Benjamin Bok | D74: 2563 | E74: — | F74: 13-16 | G74: 7
B75: 21 | C75: Pranesh M | D75: 2534 | E75: — | F75: 9-12 | G75: 12
B76: 22 | C76: Sina Movahed | D76: 2446 | E76: — | F76: 9-12 | G76: 13
B78: Seed − result: positive = finished better than rating suggested (Lazavik seeded 17th, finished 2nd). Negative = underperformed. This column is the raw material for calibrating chess volatility once several editions exist.

Sheet LoL
B2: League of Legends — EWC 2026
B3: Cohort-seeded title. Regions and cohorts below are SUGGESTIONS — the Liquipedia page carries no participant/region table, so confirm both. Cohort is a dropdown; the model in block 4 turns it into simulator inputs.
B5: FORMAT | D5: FIELD SIZE | F5: TVI | H5: SEED METHOD | J5: SEED SOURCE | L5: PLACEMENT GRANULARITY
B6: 4 groups → playoffs | D6: 16 teams | F6: 40 · Low | H6: D — cohort seeding | J6: Manual: region + international pedigree | L6: Bands (5-8, 9-12, 13-16)
B8: 1 · FIELD & RESULTS
B9: All 16 teams with exact placement bands and prize money from the Liquipedia prize table. Cohort drives the simulator — edit it directly.
B10: Club | C10: Region | D10: Cohort | E10: Placement | F10: Points (auto) | G10: Official CC pts | H10: Δ check | I10: Prize (USD) | J10: Notes | L10: Club (canonical)
B11: Dplus | C11: LCK | D11: High | E11: 1 | F11: =IF($E11="","",IFERROR(LOOKUP(VALUE(LEFT($E11&"",FIND("-",$E11&"-")-1)),$C$34:$C$39,$D$34:$D$39),"")) -> 1000 | H11: =IF($G11="","n/a",IF($F11=$G11,"ok","MISMATCH")) -> n/a | I11: 600000 | L11: Dplus
B12: Karmine Corp | C12: LEC | D12: Medium | E12: 2 | F12: =IF($E12="","",IFERROR(LOOKUP(VALUE(LEFT($E12&"",FIND("-",$E12&"-")-1)),$C$34:$C$39,$D$34:$D$39),"")) -> 750 | G12: 750 | H12: =IF($G12="","n/a",IF($F12=$G12,"ok","MISMATCH")) -> ok | I12: 340000 | L12: Karmine Corp
B13: Gen.G Esports | C13: LCK | D13: High | E13: 3 | F13: =IF($E13="","",IFERROR(LOOKUP(VALUE(LEFT($E13&"",FIND("-",$E13&"-")-1)),$C$34:$C$39,$D$34:$D$39),"")) -> 500 | G13: 500 | H13: =IF($G13="","n/a",IF($F13=$G13,"ok","MISMATCH")) -> ok | I13: 220000 | L13: Gen.G Esports
B14: T1 | C14: LCK | D14: High | E14: 4 | F14: =IF($E14="","",IFERROR(LOOKUP(VALUE(LEFT($E14&"",FIND("-",$E14&"-")-1)),$C$34:$C$39,$D$34:$D$39),"")) -> 300 | G14: 300 | H14: =IF($G14="","n/a",IF($F14=$G14,"ok","MISMATCH")) -> ok | I14: 140000 | L14: T1
B15: Hanwha Life Esports | C15: LCK | D15: High | E15: 5-8 | F15: =IF($E15="","",IFERROR(LOOKUP(VALUE(LEFT($E15&"",FIND("-",$E15&"-")-1)),$C$34:$C$39,$D$34:$D$39),"")) -> 200 | G15: 200 | H15: =IF($G15="","n/a",IF($F15=$G15,"ok","MISMATCH")) -> ok | I15: 90000 | L15: Hanwha Life Esports
B16: AG.AL International | C16: LPL | D16: High | E16: 5-8 | F16: =IF($E16="","",IFERROR(LOOKUP(VALUE(LEFT($E16&"",FIND("-",$E16&"-")-1)),$C$34:$C$39,$D$34:$D$39),"")) -> 200 | G16: 200 | H16: =IF($G16="","n/a",IF($F16=$G16,"ok","MISMATCH")) -> ok | I16: 90000 | L16: AG.AL International
B17: JD Gaming | C17: LPL | D17: High | E17: 5-8 | F17: =IF($E17="","",IFERROR(LOOKUP(VALUE(LEFT($E17&"",FIND("-",$E17&"-")-1)),$C$34:$C$39,$D$34:$D$39),"")) -> 200 | G17: 200 | H17: =IF($G17="","n/a",IF($F17=$G17,"ok","MISMATCH")) -> ok | I17: 90000 | L17: JD Gaming
B18: Bilibili Gaming | C18: LPL | D18: High | E18: 5-8 | F18: =IF($E18="","",IFERROR(LOOKUP(VALUE(LEFT($E18&"",FIND("-",$E18&"-")-1)),$C$34:$C$39,$D$34:$D$39),"")) -> 200 | G18: 200 | H18: =IF($G18="","n/a",IF($F18=$G18,"ok","MISMATCH")) -> ok | I18: 90000 | L18: Bilibili Gaming
B19: G2 Esports | C19: LEC | D19: Medium | E19: 9-12 | F19: =IF($E19="","",IFERROR(LOOKUP(VALUE(LEFT($E19&"",FIND("-",$E19&"-")-1)),$C$34:$C$39,$D$34:$D$39),"")) -> 0 | G19: 0 | H19: =IF($G19="","n/a",IF($F19=$G19,"ok","MISMATCH")) -> ok | I19: 55000 | L19: G2 Esports
B20: Sentinels | C20: LTA North | D20: Medium | E20: 9-12 | F20: =IF($E20="","",IFERROR(LOOKUP(VALUE(LEFT($E20&"",FIND("-",$E20&"-")-1)),$C$34:$C$39,$D$34:$D$39),"")) -> 0 | G20: 0 | H20: =IF($G20="","n/a",IF($F20=$G20,"ok","MISMATCH")) -> ok | I20: 55000 | L20: Sentinels
B21: GAM Esports | C21: LCP | D21: Low | E21: 9-12 | F21: =IF($E21="","",IFERROR(LOOKUP(VALUE(LEFT($E21&"",FIND("-",$E21&"-")-1)),$C$34:$C$39,$D$34:$D$39),"")) -> 0 | G21: 0 | H21: =IF($G21="","n/a",IF($F21=$G21,"ok","MISMATCH")) -> ok | I21: 55000 | L21: GAM Esports
B22: MIBR.LOS | C22: LTA South | D22: Low | E22: 9-12 | F22: =IF($E22="","",IFERROR(LOOKUP(VALUE(LEFT($E22&"",FIND("-",$E22&"-")-1)),$C$34:$C$39,$D$34:$D$39),"")) -> 0 | G22: 0 | H22: =IF($G22="","n/a",IF($F22=$G22,"ok","MISMATCH")) -> ok | I22: 55000 | L22: MIBR.LOS
B23: FURIA | C23: LTA South | D23: Low | E23: 13-16 | F23: =IF($E23="","",IFERROR(LOOKUP(VALUE(LEFT($E23&"",FIND("-",$E23&"-")-1)),$C$34:$C$39,$D$34:$D$39),"")) -> 0 | G23: 0 | H23: =IF($G23="","n/a",IF($F23=$G23,"ok","MISMATCH")) -> ok | I23: 30000 | L23: FURIA
... B26: LYON | C26: LTA North | D26: Low | E26: 13-16 | F26: =IF($E26="","",IFERROR(LOOKUP(VALUE(LEFT($E26&"",FIND("-",$E26&"-")-1)),$C$34:$C$39,$D$34:$D$39),"")) -> 0 | G26: 0 | H26: =IF($G26="","n/a",IF($F26=$G26,"ok","MISMATCH")) -> ok | I26: 30000 | L26: LYON
B28: TOTAL POINTS AWARDED | F28: =SUM(F11:F26) -> 3350
B29: 3,350 club points awarded. Prize money sums to $2,000,000 of the $2,025,000 pool — the $25,000 balance is an MVP award, as in CS2.
B31: 2 · POINT SYSTEM
B32: From the Liquipedia prize table. Identical curve to CS2 and Chess: club points stop after 8th, prize money continues to 16th.
B33: From place | C33: Club points | D33: Band
C34: 1 | D34: 1000 | E34: 1st
C35: 2 | D35: 750 | E35: 2nd
C36: 3 | D36: 500 | E36: 3rd
C37: 4 | D37: 300 | E37: 4th
C38: 5 | D38: 200 | E38: 5th-8th
C39: 9 | D39: 0 | E39: 9th-16th (prize money only)
B41: 3 · COHORT MODEL — how a band becomes a number the simulator can use
B42: A cohort is not a seed, it is a RANGE. The simulator never collapses a band to a single rank — that would create artificial ties and understate variance. Instead each cohort maps to a latent strength distribution: a mean position (the midpoint of its band) and a spread (how uncertain we are within the band). On every run each team draws a strength value from its own distribution, the field is re-ranked by those draws, and the resulting order becomes that run's finishing order. Two independent noise sources are combined: SEED UNCERTAINTY (we do not know the order inside a cohort) and TITLE VOLATILITY (the title scrambles outcomes regardless of seed). They add in quadrature — sigma_total = SQRT(sigma_within^2 + sigma_title^2) — because they are independent. This is why the same machinery serves every seed method: a VRS rating gives a precise mean and a small sigma_within; a cohort gives a coarse mean and a large one. Change a team's cohort and its mean moves; change the TVI and every team's spread moves together.
B48: Cohort | C48: Teams (auto) | D48: Band from (auto) | E48: Band to (auto) | F48: Mean position (mu) | G48: Within-cohort sigma | H48: Title sigma | I48: Total sigma
B49: High | C49: =COUNTIF($D$11:$D$26,$B49) -> 7 | D49: =1 -> 1 | E49: =D49+C49-1 -> 7 | F49: =(D49+E49)/2 -> 4 | G49: =(E49-D49+1)/SQRT(12) -> 2.0207259 | H49: =$D$54/100*$D$55/2 -> 3.2 | I49: =SQRT(G49^2+H49^2) -> 3.784618
B50: Medium | C50: =COUNTIF($D$11:$D$26,$B50) -> 4 | D50: =E49+1 -> 8 | E50: =D50+C50-1 -> 11 | F50: =(D50+E50)/2 -> 9.5 | G50: =(E50-D50+1)/SQRT(12) -> 1.1547005 | H50: =$D$54/100*$D$55/2 -> 3.2 | I50: =SQRT(G50^2+H50^2) -> 3.4019602
B51: Low | C51: =COUNTIF($D$11:$D$26,$B51) -> 5 | D51: =E50+1 -> 12 | E51: =D51+C51-1 -> 16 | F51: =(D51+E51)/2 -> 14 | G51: =(E51-D51+1)/SQRT(12) -> 1.4433757 | H51: =$D$54/100*$D$55/2 -> 3.2 | I51: =SQRT(G51^2+H51^2) -> 3.5104606
B53: Bands derive automatically from the cohort dropdowns above — reassign a team and every band, mu and sigma updates. Only the two blue cells below are inputs.
B54: TVI (title volatility) | D54: 40
B55: Field size | D55: 16
B56: Simulator draw, per run and per team: strength = mu + NORM.INV(RAND(), 0, total sigma) → rank the 16 draws ascending → that run's finishing order → points from block 2.
B57: Sanity check from EWC26: all 7 High-cohort teams finished top 8. The single miss was Karmine Corp (Medium) at 2nd — so a Medium team reaching a final is roughly the tail event this model should produce occasionally, not never.

Sheet PUBG Mobile
B2: PUBG Mobile — EWC 2026
B3: Battle royale. Listed on Liquipedia as 'PUBG Mobile World Cup 2026'. Every placement 1-8 pays a DIFFERENT club-point value — no shared bands, unlike the playoff titles.
B5: FORMAT | D5: FIELD SIZE | F5: TVI | H5: SEED METHOD | J5: SEED SOURCE | L5: PLACEMENT GRANULARITY
B6: Groups → Survival Stage → Grand Finals | D6: 32 teams | F6: 78 · High | H6: E — no credible seed | J6: n/a — see block 3 | L6: Exact 1-26, ties from 27th
B8: 1 · FIELD & RESULTS
B9: All 32 teams with exact placements and prize money from the Liquipedia prize table. Seed column is deliberately empty — see the seed note in block 3. Qualification route and region are recorded as data, not used as a seed.
B10: Club | C10: Region | D10: Seed | E10: Placement | F10: Points (auto) | G10: Official CC pts | H10: Δ check | I10: Prize (USD) | J10: Qualification route | L10: Club (canonical)
B11: S2G Esports | C11: Türkiye | E11: 1 | F11: =IF($E11="","",IFERROR(LOOKUP(VALUE(LEFT($E11&"",FIND("-",$E11&"-")-1)),$C$47:$C$55,$D$47:$D$55),"")) -> 1000 | G11: 1000 | H11: =IF($G11="","n/a",IF($F11=$G11,"ok","MISMATCH")) -> ok | I11: 555000 | J11: Türkiye Points (top 4) | L11: S2G Esports
B12: Nongshim RedForce | C12: Korea | E12: 2 | F12: =IF($E12="","",IFERROR(LOOKUP(VALUE(LEFT($E12&"",FIND("-",$E12&"-")-1)),$C$47:$C$55,$D$47:$D$55),"")) -> 750 | G12: 750 | H12: =IF($G12="","n/a",IF($F12=$G12,"ok","MISMATCH")) -> ok | I12: 293000 | J12: Korea (champion) | L12: Nongshim RedForce
B13: Aurora Gaming | C13: EECA | E13: 3 | F13: =IF($E13="","",IFERROR(LOOKUP(VALUE(LEFT($E13&"",FIND("-",$E13&"-")-1)),$C$47:$C$55,$D$47:$D$55),"")) -> 500 | G13: 500 | H13: =IF($G13="","n/a",IF($F13=$G13,"ok","MISMATCH")) -> ok | I13: 210000 | J13: EECA Points (top 3) | L13: Aurora Gaming
B14: eArena | C14: SEA | E14: 4 | F14: =IF($E14="","",IFERROR(LOOKUP(VALUE(LEFT($E14&"",FIND("-",$E14&"-")-1)),$C$47:$C$55,$D$47:$D$55),"")) -> 300 | G14: 300 | H14: =IF($G14="","n/a",IF($F14=$G14,"ok","MISMATCH")) -> ok | I14: 161000 | J14: Southeast Asia Points (top 4) | L14: eArena
B15: Tianba | C15: China | E15: 5 | F15: =IF($E15="","",IFERROR(LOOKUP(VALUE(LEFT($E15&"",FIND("-",$E15&"-")-1)),$C$47:$C$55,$D$47:$D$55),"")) -> 200 | G15: 200 | H15: =IF($G15="","n/a",IF($F15=$G15,"ok","MISMATCH")) -> ok | I15: 141000 | J15: 2026 PEL Points (top 3) | L15: Tianba
B16: 4Thrives Esports | C16: South Asia | E16: 6 | F16: =IF($E16="","",IFERROR(LOOKUP(VALUE(LEFT($E16&"",FIND("-",$E16&"-")-1)),$C$47:$C$55,$D$47:$D$55),"")) -> 150 | H16: =IF($G16="","n/a",IF($F16=$G16,"ok","MISMATCH")) -> n/a | I16: 161000 | J16: South Asia Points (top 2) | L16: 4thrives Esports
B17: Team Flash | C17: SEA | E17: 7 | F17: =IF($E17="","",IFERROR(LOOKUP(VALUE(LEFT($E17&"",FIND("-",$E17&"-")-1)),$C$47:$C$55,$D$47:$D$55),"")) -> 100 | G17: 100 | H17: =IF($G17="","n/a",IF($F17=$G17,"ok","MISMATCH")) -> ok | I17: 137500 | J17: Southeast Asia Points (top 4) | L17: Team Flash
B18: Horaa Esports | C18: South Asia | E18: 8 | F18: =IF($E18="","",IFERROR(LOOKUP(VALUE(LEFT($E18&"",FIND("-",$E18&"-")-1)),$C$47:$C$55,$D$47:$D$55),"")) -> 50 | G18: 50 | H18: =IF($G18="","n/a",IF($F18=$G18,"ok","MISMATCH")) -> ok | I18: 127500 | J18: South Asia Points (top 2) | L18: Horaa Esports
B19: Nigma Galaxy | C19: MENA | E19: 9 | F19: =IF($E19="","",IFERROR(LOOKUP(VALUE(LEFT($E19&"",FIND("-",$E19&"-")-1)),$C$47:$C$55,$D$47:$D$55),"")) -> 0 | G19: 0 | H19: =IF($G19="","n/a",IF($F19=$G19,"ok","MISMATCH")) -> ok | I19: 115000 | J19: MENA Points (top 5) | L19: Nigma Galaxy
B20: FURIA | C20: Americas | E20: 10 | F20: =IF($E20="","",IFERROR(LOOKUP(VALUE(LEFT($E20&"",FIND("-",$E20&"-")-1)),$C$47:$C$55,$D$47:$D$55),"")) -> 0 | G20: 0 | H20: =IF($G20="","n/a",IF($F20=$G20,"ok","MISMATCH")) -> ok | I20: 95000 | J20: Americas Points (top 3) | L20: FURIA
B21: ULF Esports | C21: Türkiye | E21: 11 | F21: =IF($E21="","",IFERROR(LOOKUP(VALUE(LEFT($E21&"",FIND("-",$E21&"-")-1)),$C$47:$C$55,$D$47:$D$55),"")) -> 0 | H21: =IF($G21="","n/a",IF($F21=$G21,"ok","MISMATCH")) -> n/a | I21: 92000 | J21: Türkiye Points (top 4) | L21: ULF Esports
B22: Team Vitality | C22: SEA | E22: 12 | F22: =IF($E22="","",IFERROR(LOOKUP(VALUE(LEFT($E22&"",FIND("-",$E22&"-")-1)),$C$47:$C$55,$D$47:$D$55),"")) -> 0 | G22: 0 | H22: =IF($G22="","n/a",IF($F22=$G22,"ok","MISMATCH")) -> ok | I22: 116000 | J22: Southeast Asia Points (as Bigetron by Vitality) | L22: Team Vitality
B23: GodLike Esports | C23: India | E23: 13 | F23: =IF($E23="","",IFERROR(LOOKUP(VALUE(LEFT($E23&"",FIND("-",$E23&"-")-1)),$C$47:$C$55,$D$47:$D$55),"")) -> 0 | H23: =IF($G23="","n/a",IF($F23=$G23,"ok","MISMATCH")) -> n/a | I23: 100000 | J23: 2026 BGMI Pro Series (champion) | L23: GodLike
B24: AlUla Club Esports | C24: MENA | E24: 14 | F24: =IF($E24="","",IFERROR(LOOKUP(VALUE(LEFT($E24&"",FIND("-",$E24&"-")-1)),$C$47:$C$55,$D$47:$D$55),"")) -> 0 | H24: =IF($G24="","n/a",IF($F24=$G24,"ok","MISMATCH")) -> n/a | I24: 76000 | J24: MENA Points (top 5) | L24: AlUla Club Esports
B25: Orangutan | C25: India | E25: 15 | F25: =IF($E25="","",IFERROR(LOOKUP(VALUE(LEFT($E25&"",FIND("-",$E25&"-")-1)),$C$47:$C$55,$D$47:$D$55),"")) -> 0 | H25: =IF($G25="","n/a",IF($F25=$G25,"ok","MISMATCH")) -> n/a | I25: 95000 | J25: 2026 India Points (champion) | L25: Orangutan
B26: IDA Esports | C26: Türkiye | E26: 16 | F26: =IF($E26="","",IFERROR(LOOKUP(VALUE(LEFT($E26&"",FIND("-",$E26&"-")-1)),$C$47:$C$55,$D$47:$D$55),"")) -> 0 | H26: =IF($G26="","n/a",IF($F26=$G26,"ok","MISMATCH")) -> n/a | I26: 90000 | J26: Türkiye Points (top 4) | L26: IDA Esports
B27: Wolves Esports | C27: Americas | E27: 17 | F27: =IF($E27="","",IFERROR(LOOKUP(VALUE(LEFT($E27&"",FIND("-",$E27&"-")-1)),$C$47:$C$55,$D$47:$D$55),"")) -> 0 | G27: 0 | H27: =IF($G27="","n/a",IF($F27=$G27,"ok","MISMATCH")) -> ok | I27: 34000 | J27: Americas Points (top 3) | L27: Wolves Esports
B28: GOAT Team | C28: EECA | E28: 18 | F28: =IF($E28="","",IFERROR(LOOKUP(VALUE(LEFT($E28&"",FIND("-",$E28&"-")-1)),$C$47:$C$55,$D$47:$D$55),"")) -> 0 | H28: =IF($G28="","n/a",IF($F28=$G28,"ok","MISMATCH")) -> n/a | I28: 37000 | J28: EECA Points (top 3) | L28: GOAT Team
B29: Alpha7 Esports | C29: Americas | E29: 19 | F29: =IF($E29="","",IFERROR(LOOKUP(VALUE(LEFT($E29&"",FIND("-",$E29&"-")-1)),$C$47:$C$55,$D$47:$D$55),"")) -> 0 | H29: =IF($G29="","n/a",IF($F29=$G29,"ok","MISMATCH")) -> n/a | I29: 36000 | J29: Americas Points (top 3) | L29: Alpha7 Esports
B30: AG.AL International | C30: China | E30: 20 | F30: =IF($E30="","",IFERROR(LOOKUP(VALUE(LEFT($E30&"",FIND("-",$E30&"-")-1)),$C$47:$C$55,$D$47:$D$55),"")) -> 0 | G30: 0 | H30: =IF($G30="","n/a",IF($F30=$G30,"ok","MISMATCH")) -> ok | I30: 36000 | J30: 2026 PEL Points (as All Gamers) | L30: AG.AL International
B31: DOPENESS | C31: Japan | E31: 21 | F31: =IF($E31="","",IFERROR(LOOKUP(VALUE(LEFT($E31&"",FIND("-",$E31&"-")-1)),$C$47:$C$55,$D$47:$D$55),"")) -> 0 | H31: =IF($G31="","n/a",IF($F31=$G31,"ok","MISMATCH")) -> n/a | I31: 29000 | J31: Japan (champion) | L31: DOPENESS
B32: Geekay Esports | C32: MENA | E32: 22 | F32: =IF($E32="","",IFERROR(LOOKUP(VALUE(LEFT($E32&"",FIND("-",$E32&"-")-1)),$C$47:$C$55,$D$47:$D$55),"")) -> 0 | G32: 0 | H32: =IF($G32="","n/a",IF($F32=$G32,"ok","MISMATCH")) -> ok | I32: 28000 | J32: MENA Points (top 5) | L32: Geekay Esports
B33: Rex Regum Qeon | C33: SEA | E33: 23 | F33: =IF($E33="","",IFERROR(LOOKUP(VALUE(LEFT($E33&"",FIND("-",$E33&"-")-1)),$C$47:$C$55,$D$47:$D$55),"")) -> 0 | G33: 0 | H33: =IF($G33="","n/a",IF($F33=$G33,"ok","MISMATCH")) -> ok | I33: 28000 | J33: Southeast Asia Points (as RRQ RYU) | L33: Rex Regum Qeon
B34: Yangon Galacticos | C34: SEA | E34: 24 | F34: =IF($E34="","",IFERROR(LOOKUP(VALUE(LEFT($E34&"",FIND("-",$E34&"-")-1)),$C$47:$C$55,$D$47:$D$55),"")) -> 0 | G34: 0 | H34: =IF($G34="","n/a",IF($F34=$G34,"ok","MISMATCH")) -> ok | I34: 30000 | J34: 2025 PMWC (defending champion) | L34: Yangon Galacticos
B35: DRX | C35: Korea | E35: 25 | F35: =IF($E35="","",IFERROR(LOOKUP(VALUE(LEFT($E35&"",FIND("-",$E35&"-")-1)),$C$47:$C$55,$D$47:$D$55),"")) -> 0 | G35: 0 | H35: =IF($G35="","n/a",IF($F35=$G35,"ok","MISMATCH")) -> ok | I35: 27000 | J35: 2026 Rivals Cup (champion) | L35: DRX
B36: GS 721 | C36: MENA | E36: 26 | F36: =IF($E36="","",IFERROR(LOOKUP(VALUE(LEFT($E36&"",FIND("-",$E36&"-")-1)),$C$47:$C$55,$D$47:$D$55),"")) -> 0 | H36: =IF($G36="","n/a",IF($F36=$G36,"ok","MISMATCH")) -> n/a | I36: 27000 | J36: MENA Points (as 721 Esports) | L36: GS 721
B37: XForce Rejects | C37: Africa | E37: 27-28 | F37: =IF($E37="","",IFERROR(LOOKUP(VALUE(LEFT($E37&"",FIND("-",$E37&"-")-1)),$C$47:$C$55,$D$47:$D$55),"")) -> 0 | H37: =IF($G37="","n/a",IF($F37=$G37,"ok","MISMATCH")) -> n/a | I37: 21000 | J37: Africa Points (champion) | L37: XForce Rejects
B38: ETSH Esports | C38: MENA | E38: 27-28 | F38: =IF($E38="","",IFERROR(LOOKUP(VALUE(LEFT($E38&"",FIND("-",$E38&"-")-1)),$C$47:$C$55,$D$47:$D$55),"")) -> 0 | H38: =IF($G38="","n/a",IF($F38=$G38,"ok","MISMATCH")) -> n/a | I38: 21000 | J38: MENA Points (top 5) | L38: ETSH Esports
B39: ThunderTalk Gaming | C39: China | E39: 29-30 | F39: =IF($E39="","",IFERROR(LOOKUP(VALUE(LEFT($E39&"",FIND("-",$E39&"-")-1)),$C$47:$C$55,$D$47:$D$55),"")) -> 0 | H39: =IF($G39="","n/a",IF($F39=$G39,"ok","MISMATCH")) -> n/a | I39: 20500 | J39: 2026 PEL Points (top 3) | L39: ThunderTalk Gaming
B40: TT Project | C40: EECA | E40: 29-30 | F40: =IF($E40="","",IFERROR(LOOKUP(VALUE(LEFT($E40&"",FIND("-",$E40&"-")-1)),$C$47:$C$55,$D$47:$D$55),"")) -> 0 | H40: =IF($G40="","n/a",IF($F40=$G40,"ok","MISMATCH")) -> n/a | I40: 20500 | J40: EECA Points (top 3) | L40: TT Project
B41: Gaming Stars Esports | C41: Türkiye | E41: 31-32 | F41: =IF($E41="","",IFERROR(LOOKUP(VALUE(LEFT($E41&"",FIND("-",$E41&"-")-1)),$C$47:$C$55,$D$47:$D$55),"")) -> 0 | H41: =IF($G41="","n/a",IF($F41=$G41,"ok","MISMATCH")) -> n/a | I41: 20000 | J41: Türkiye Points (top 4) | L41: Gaming Stars Esports
B42: Hustler Crew | C42: W. Europe | E42: 31-32 | F42: =IF($E42="","",IFERROR(LOOKUP(VALUE(LEFT($E42&"",FIND("-",$E42&"-")-1)),$C$47:$C$55,$D$47:$D$55),"")) -> 0 | H42: =IF($G42="","n/a",IF($F42=$G42,"ok","MISMATCH")) -> n/a | I42: 20000 | J42: Western Europe Points (champion) | L42: Hustler Crew
B44: TOTAL POINTS AWARDED | F44: =SUM(F11:F42) -> 3050
B45: 2 · POINT SYSTEM
B46: Place | C46: Club points
C47: 1 | D47: 1000
C48: 2 | D48: 750
C49: 3 | D49: 500
C50: 4 | D50: 300
C51: 5 | D51: 200
C52: 6 | D52: 150
C53: 7 | D53: 100
C54: 8 | D54: 50
C55: 9 | D55: 0 | E55: 9th and below — no award
B58: 3 · SEED — METHOD E, DELIBERATELY NONE
B59: Why no seed. Every team qualified by winning or placing in its own regional points race, so the only ranking that exists is WITHIN a region — there is no cross-region ladder that would let us say a 3rd-placed Türkiye team is stronger or weaker than a 2nd-placed SEA team. Manufacturing one would be a guess dressed as data. The 2026 result supports leaving it out: the top eight came from six different regions, and the champion, S2G Esports, qualified 3rd of four from Türkiye. What method E means in the model: every team shares the same mean strength, so outcomes are driven entirely by the title sigma. Expected club points are identical for all 32 teams at 3,050 / 32 = 95.3 per team. That is the correct representation of a title we cannot forecast. Region and qualification route are recorded above as data so that, once several editions exist, we can TEST whether region predicts placement — and upgrade this title to method D (cohort) only if the evidence supports it.
B65: Region | C65: Teams entered | D65: Best club points | E65: Teams in top 8
B66: SEA | C66: =COUNTIF($C$11:$C$42,$B66) -> 5 | D66: =IFERROR(SUMPRODUCT(MAX(($C$11:$C$42=$B66)*$F$11:$F$42)),0) -> 300 | E66: =SUMPRODUCT(($C$11:$C$42=$B66)*($F$11:$F$42>0)) -> 2
B67: MENA | C67: =COUNTIF($C$11:$C$42,$B67) -> 5 | D67: =IFERROR(SUMPRODUCT(MAX(($C$11:$C$42=$B67)*$F$11:$F$42)),0) -> 0 | E67: =SUMPRODUCT(($C$11:$C$42=$B67)*($F$11:$F$42>0)) -> 0
B68: Türkiye | C68: =COUNTIF($C$11:$C$42,$B68) -> 4 | D68: =IFERROR(SUMPRODUCT(MAX(($C$11:$C$42=$B68)*$F$11:$F$42)),0) -> 1000 | E68: =SUMPRODUCT(($C$11:$C$42=$B68)*($F$11:$F$42>0)) -> 1
B69: EECA | C69: =COUNTIF($C$11:$C$42,$B69) -> 3 | D69: =IFERROR(SUMPRODUCT(MAX(($C$11:$C$42=$B69)*$F$11:$F$42)),0) -> 500 | E69: =SUMPRODUCT(($C$11:$C$42=$B69)*($F$11:$F$42>0)) -> 1
B70: China | C70: =COUNTIF($C$11:$C$42,$B70) -> 3 | D70: =IFERROR(SUMPRODUCT(MAX(($C$11:$C$42=$B70)*$F$11:$F$42)),0) -> 200 | E70: =SUMPRODUCT(($C$11:$C$42=$B70)*($F$11:$F$42>0)) -> 1
B71: Americas | C71: =COUNTIF($C$11:$C$42,$B71) -> 3 | D71: =IFERROR(SUMPRODUCT(MAX(($C$11:$C$42=$B71)*$F$11:$F$42)),0) -> 0 | E71: =SUMPRODUCT(($C$11:$C$42=$B71)*($F$11:$F$42>0)) -> 0
B72: Korea | C72: =COUNTIF($C$11:$C$42,$B72) -> 2 | D72: =IFERROR(SUMPRODUCT(MAX(($C$11:$C$42=$B72)*$F$11:$F$42)),0) -> 750 | E72: =SUMPRODUCT(($C$11:$C$42=$B72)*($F$11:$F$42>0)) -> 1
B73: South Asia | C73: =COUNTIF($C$11:$C$42,$B73) -> 2 | D73: =IFERROR(SUMPRODUCT(MAX(($C$11:$C$42=$B73)*$F$11:$F$42)),0) -> 150 | E73: =SUMPRODUCT(($C$11:$C$42=$B73)*($F$11:$F$42>0)) -> 2
B74: India | C74: =COUNTIF($C$11:$C$42,$B74) -> 2 | D74: =IFERROR(SUMPRODUCT(MAX(($C$11:$C$42=$B74)*$F$11:$F$42)),0) -> 0 | E74: =SUMPRODUCT(($C$11:$C$42=$B74)*($F$11:$F$42>0)) -> 0
B75: Japan | C75: =COUNTIF($C$11:$C$42,$B75) -> 1 | D75: =IFERROR(SUMPRODUCT(MAX(($C$11:$C$42=$B75)*$F$11:$F$42)),0) -> 0 | E75: =SUMPRODUCT(($C$11:$C$42=$B75)*($F$11:$F$42>0)) -> 0
B76: Africa | C76: =COUNTIF($C$11:$C$42,$B76) -> 1 | D76: =IFERROR(SUMPRODUCT(MAX(($C$11:$C$42=$B76)*$F$11:$F$42)),0) -> 0 | E76: =SUMPRODUCT(($C$11:$C$42=$B76)*($F$11:$F$42>0)) -> 0
B77: W. Europe | C77: =COUNTIF($C$11:$C$42,$B77) -> 1 | D77: =IFERROR(SUMPRODUCT(MAX(($C$11:$C$42=$B77)*$F$11:$F$42)),0) -> 0 | E77: =SUMPRODUCT(($C$11:$C$42=$B77)*($F$11:$F$42>0)) -> 0
B79: This block is the evidence base for revisiting method E later. If one region were to dominate the top 8 across several editions, cohort seeding would become justified.

Sheet Fortnite Reload
B2: Fortnite Reload — EWC 2026
B3: Duos battle royale. Listed on Liquipedia as 'Reload Elite Series 2026 - Championship'. Same BR point curve as PUBG Mobile: every placement 1-8 pays a different value.
B5: FORMAT | D5: FIELD SIZE | F5: TVI | H5: SEED METHOD | J5: SEED SOURCE | L5: PLACEMENT GRANULARITY
B6: Duos BR — Reload mode | D6: 40 duos | F6: 80 · High | H6: E + elite override (hybrid) | J6: Reload-format results only — see block 3 | L6: Exact 1-34, ties from 35th
B8: 1 · FIELD & RESULTS
B9: All 40 duos with exact placements and prize money. Tier column is the hybrid seed input — default is Field for everyone, which behaves exactly as method E until you promote a duo to Elite.
B10: Club | C10: Duo | D10: Tier | E10: Placement | F10: Points (auto) | G10: Official CC pts | H10: Δ check | I10: Prize (USD) | J10: Notes | L10: Club (canonical)
B11: BIG | C11: vic0 & Malibuca | D11: Field | E11: 1 | F11: =IF($E11="","",IFERROR(LOOKUP(VALUE(LEFT($E11&"",FIND("-",$E11&"-")-1)),$C$57:$C$65,$D$57:$D$65),"")) -> 1000 | G11: 1000 | H11: =IF($G11="","n/a",IF($F11=$G11,"ok","MISMATCH")) -> ok | I11: 260000 | L11: BIG
B12: Mixed | C12: Momsy & SkyJump | D12: Field | E12: 2 | F12: =IF($E12="","",IFERROR(LOOKUP(VALUE(LEFT($E12&"",FIND("-",$E12&"-")-1)),$C$57:$C$65,$D$57:$D$65),"")) -> 750 | H12: =IF($G12="","n/a",IF($F12=$G12,"ok","MISMATCH")) -> n/a | I12: 150000 | J12: Momsy: Lyost Esport / SkyJump: Ravens Esports | L12: Mixed
B13: Aurora Gaming | C13: shxrk & t3eny | D13: Field | E13: 3 | F13: =IF($E13="","",IFERROR(LOOKUP(VALUE(LEFT($E13&"",FIND("-",$E13&"-")-1)),$C$57:$C$65,$D$57:$D$65),"")) -> 500 | G13: 500 | H13: =IF($G13="","n/a",IF($F13=$G13,"ok","MISMATCH")) -> ok | I13: 90000 | L13: Aurora Gaming
B14: HavoK by Vitality | C14: SwizzY & Pixie | D14: Field | E14: 4 | F14: =IF($E14="","",IFERROR(LOOKUP(VALUE(LEFT($E14&"",FIND("-",$E14&"-")-1)),$C$57:$C$65,$D$57:$D$65),"")) -> 300 | H14: =IF($G14="","n/a",IF($F14=$G14,"ok","MISMATCH")) -> n/a | I14: 60000 | J14: Scored as a separate club — canonical join changed to HavoK by Vitality | L14: HavoK by Vitality
B15: Leviatán | C15: Lewa & Romero | D15: Field | E15: 5 | F15: =IF($E15="","",IFERROR(LOOKUP(VALUE(LEFT($E15&"",FIND("-",$E15&"-")-1)),$C$57:$C$65,$D$57:$D$65),"")) -> 200 | G15: 200 | H15: =IF($G15="","n/a",IF($F15=$G15,"ok","MISMATCH")) -> ok | I15: 45000 | L15: Leviatán
B16: ROC Esports | C16: charyy & Kami | D16: Field | E16: 6 | F16: =IF($E16="","",IFERROR(LOOKUP(VALUE(LEFT($E16&"",FIND("-",$E16&"-")-1)),$C$57:$C$65,$D$57:$D$65),"")) -> 150 | G16: 150 | H16: =IF($G16="","n/a",IF($F16=$G16,"ok","MISMATCH")) -> ok | I16: 35000 | L16: ROC Esports
B17: Dignitas | C17: VicterV & Khanada | D17: Field | E17: 7 | F17: =IF($E17="","",IFERROR(LOOKUP(VALUE(LEFT($E17&"",FIND("-",$E17&"-")-1)),$C$57:$C$65,$D$57:$D$65),"")) -> 100 | G17: 100 | H17: =IF($G17="","n/a",IF($F17=$G17,"ok","MISMATCH")) -> ok | I17: 30000 | L17: Dignitas
B18: T1 | C18: Demus & Darm | D18: Field | E18: 8 | F18: =IF($E18="","",IFERROR(LOOKUP(VALUE(LEFT($E18&"",FIND("-",$E18&"-")-1)),$C$57:$C$65,$D$57:$D$65),"")) -> 50 | G18: 50 | H18: =IF($G18="","n/a",IF($F18=$G18,"ok","MISMATCH")) -> ok | I18: 28000 | L18: T1
B19: S8UL Esports | C19: Faded & Kaan | D19: Field | E19: 9 | F19: =IF($E19="","",IFERROR(LOOKUP(VALUE(LEFT($E19&"",FIND("-",$E19&"-")-1)),$C$57:$C$65,$D$57:$D$65),"")) -> 0 | G19: 0 | H19: =IF($G19="","n/a",IF($F19=$G19,"ok","MISMATCH")) -> ok | I19: 26000 | L19: S8UL Esports
B20: Vision Esports | C20: SaLva & Yassen | D20: Field | E20: 10 | F20: =IF($E20="","",IFERROR(LOOKUP(VALUE(LEFT($E20&"",FIND("-",$E20&"-")-1)),$C$57:$C$65,$D$57:$D$65),"")) -> 0 | H20: =IF($G20="","n/a",IF($F20=$G20,"ok","MISMATCH")) -> n/a | I20: 24000 | L20: Team Vision
B21: AG.AL International | C21: Sky & Scroll | D21: Field | E21: 11 | F21: =IF($E21="","",IFERROR(LOOKUP(VALUE(LEFT($E21&"",FIND("-",$E21&"-")-1)),$C$57:$C$65,$D$57:$D$65),"")) -> 0 | G21: 0 | H21: =IF($G21="","n/a",IF($F21=$G21,"ok","MISMATCH")) -> ok | I21: 22000 | L21: AG.AL International
B22: Team Falcons | C22: Peterbot & Pollo | D22: Field | E22: 12 | F22: =IF($E22="","",IFERROR(LOOKUP(VALUE(LEFT($E22&"",FIND("-",$E22&"-")-1)),$C$57:$C$65,$D$57:$D$65),"")) -> 0 | G22: 0 | H22: =IF($G22="","n/a",IF($F22=$G22,"ok","MISMATCH")) -> ok | I22: 20000 | L22: Team Falcons
B23: Team Vitality | C23: Tjino & PabloWingu | D23: Field | E23: 13 | F23: =IF($E23="","",IFERROR(LOOKUP(VALUE(LEFT($E23&"",FIND("-",$E23&"-")-1)),$C$57:$C$65,$D$57:$D$65),"")) -> 0 | G23: 0 | H23: =IF($G23="","n/a",IF($F23=$G23,"ok","MISMATCH")) -> ok | I23: 18000 | L23: Team Vitality
B24: Elite Esports | C24: josh & Eomzo | D24: Field | E24: 14 | F24: =IF($E24="","",IFERROR(LOOKUP(VALUE(LEFT($E24&"",FIND("-",$E24&"-")-1)),$C$57:$C$65,$D$57:$D$65),"")) -> 0 | G24: 0 | H24: =IF($G24="","n/a",IF($F24=$G24,"ok","MISMATCH")) -> ok | I24: 16000 | L24: Elite Esports
B25: Mixed | C25: Minipiyo & FuuKun | D25: Field | E25: 15 | F25: =IF($E25="","",IFERROR(LOOKUP(VALUE(LEFT($E25&"",FIND("-",$E25&"-")-1)),$C$57:$C$65,$D$57:$D$65),"")) -> 0 | H25: =IF($G25="","n/a",IF($F25=$G25,"ok","MISMATCH")) -> n/a | I25: 15000 | J25: Minipiyo: ZETA DIVISION / FuuKun: QT DIG | L25: Mixed
B26: Team Orchid | C26: Nociff & Izzi | D26: Field | E26: 16 | F26: =IF($E26="","",IFERROR(LOOKUP(VALUE(LEFT($E26&"",FIND("-",$E26&"-")-1)),$C$57:$C$65,$D$57:$D$65),"")) -> 0 | H26: =IF($G26="","n/a",IF($F26=$G26,"ok","MISMATCH")) -> n/a | I26: 14000 | L26: Team Orchid
B27: Mixed | C27: Muz & Sphinx | D27: Field | E27: 17 | F27: =IF($E27="","",IFERROR(LOOKUP(VALUE(LEFT($E27&"",FIND("-",$E27&"-")-1)),$C$57:$C$65,$D$57:$D$65),"")) -> 0 | H27: =IF($G27="","n/a",IF($F27=$G27,"ok","MISMATCH")) -> n/a | I27: 13000 | J27: Muz: XSET / Sphinx: unlisted | L27: Mixed
B28: Twisted Minds | C28: Cold & Rapid | D28: Field | E28: 18 | F28: =IF($E28="","",IFERROR(LOOKUP(VALUE(LEFT($E28&"",FIND("-",$E28&"-")-1)),$C$57:$C$65,$D$57:$D$65),"")) -> 0 | G28: 0 | H28: =IF($G28="","n/a",IF($F28=$G28,"ok","MISMATCH")) -> ok | I28: 12000 | L28: Twisted Minds
B29: Mixed | C29: Goofy & ZDog | D29: Field | E29: 19 | F29: =IF($E29="","",IFERROR(LOOKUP(VALUE(LEFT($E29&"",FIND("-",$E29&"-")-1)),$C$57:$C$65,$D$57:$D$65),"")) -> 0 | H29: =IF($G29="","n/a",IF($F29=$G29,"ok","MISMATCH")) -> n/a | I29: 11000 | J29: Goofy: PWR / ZDog: JFT Esports | L29: Mixed
B30: Twisted Minds | C30: Acorn & Boltz | D30: Field | E30: 20 | F30: =IF($E30="","",IFERROR(LOOKUP(VALUE(LEFT($E30&"",FIND("-",$E30&"-")-1)),$C$57:$C$65,$D$57:$D$65),"")) -> 0 | H30: =IF($G30="","n/a",IF($F30=$G30,"ok","MISMATCH")) -> n/a | I30: 10000 | L30: Twisted Minds
B31: ZETA DIVISION | C31: Koyota & yuma | D31: Field | E31: 21 | F31: =IF($E31="","",IFERROR(LOOKUP(VALUE(LEFT($E31&"",FIND("-",$E31&"-")-1)),$C$57:$C$65,$D$57:$D$65),"")) -> 0 | G31: 0 | H31: =IF($G31="","n/a",IF($F31=$G31,"ok","MISMATCH")) -> ok | I31: 9500 | L31: ZETA DIVISION
B32: Mixed | C32: Bugha & Braydz | D32: Field | E32: 22 | F32: =IF($E32="","",IFERROR(LOOKUP(VALUE(LEFT($E32&"",FIND("-",$E32&"-")-1)),$C$57:$C$65,$D$57:$D$65),"")) -> 0 | H32: =IF($G32="","n/a",IF($F32=$G32,"ok","MISMATCH")) -> n/a | I32: 9000 | J32: Braydz: XP42 Esports / Bugha: unlisted | L32: Mixed
B33: FURIA | C33: Night & 916Gon | D33: Field | E33: 23 | F33: =IF($E33="","",IFERROR(LOOKUP(VALUE(LEFT($E33&"",FIND("-",$E33&"-")-1)),$C$57:$C$65,$D$57:$D$65),"")) -> 0 | G33: 0 | H33: =IF($G33="","n/a",IF($F33=$G33,"ok","MISMATCH")) -> ok | I33: 8500 | L33: FURIA
B34: Mixed | C34: Cringe & Volko | D34: Field | E34: 24 | F34: =IF($E34="","",IFERROR(LOOKUP(VALUE(LEFT($E34&"",FIND("-",$E34&"-")-1)),$C$57:$C$65,$D$57:$D$65),"")) -> 0 | H34: =IF($G34="","n/a",IF($F34=$G34,"ok","MISMATCH")) -> n/a | I34: 8000 | J34: Cringe: 7VEN / Volko: Northern Star Gaming | L34: Mixed
B35: JOGO | C35: Oatley & Spookz | D35: Field | E35: 25 | F35: =IF($E35="","",IFERROR(LOOKUP(VALUE(LEFT($E35&"",FIND("-",$E35&"-")-1)),$C$57:$C$65,$D$57:$D$65),"")) -> 0 | H35: =IF($G35="","n/a",IF($F35=$G35,"ok","MISMATCH")) -> n/a | I35: 7500 | L35: JOGO
B36: REJECT | C36: Mofu & tomat | D36: Field | E36: 26 | F36: =IF($E36="","",IFERROR(LOOKUP(VALUE(LEFT($E36&"",FIND("-",$E36&"-")-1)),$C$57:$C$65,$D$57:$D$65),"")) -> 0 | G36: 0 | H36: =IF($G36="","n/a",IF($F36=$G36,"ok","MISMATCH")) -> ok | I36: 7000 | L36: REJECT
B37: Mixed | C37: Mshary & 5aald | D37: Field | E37: 27 | F37: =IF($E37="","",IFERROR(LOOKUP(VALUE(LEFT($E37&"",FIND("-",$E37&"-")-1)),$C$57:$C$65,$D$57:$D$65),"")) -> 0 | H37: =IF($G37="","n/a",IF($F37=$G37,"ok","MISMATCH")) -> n/a | I37: 6500 | J37: Mshary: Vision Esports / 5aald: unlisted | L37: Mixed
B38: RVL ESPORT | C38: Moda & Rew | D38: Field | E38: 28 | F38: =IF($E38="","",IFERROR(LOOKUP(VALUE(LEFT($E38&"",FIND("-",$E38&"-")-1)),$C$57:$C$65,$D$57:$D$65),"")) -> 0 | H38: =IF($G38="","n/a",IF($F38=$G38,"ok","MISMATCH")) -> n/a | I38: 6000 | L38: RVL ESPORT
B39: Mixed | C39: Vazen & Anon | D39: Field | E39: 29 | F39: =IF($E39="","",IFERROR(LOOKUP(VALUE(LEFT($E39&"",FIND("-",$E39&"-")-1)),$C$57:$C$65,$D$57:$D$65),"")) -> 0 | H39: =IF($G39="","n/a",IF($F39=$G39,"ok","MISMATCH")) -> n/a | I39: 5500 | J39: Vazen: Coast Esports / Anon: PWR | L39: Mixed
B40: Geekay Esports | C40: panzer & Japko | D40: Field | E40: 30 | F40: =IF($E40="","",IFERROR(LOOKUP(VALUE(LEFT($E40&"",FIND("-",$E40&"-")-1)),$C$57:$C$65,$D$57:$D$65),"")) -> 0 | G40: 0 | H40: =IF($G40="","n/a",IF($F40=$G40,"ok","MISMATCH")) -> ok | I40: 5000 | L40: Geekay Esports
B41: FUT Esports | C41: Edson & Phzin | D41: Field | E41: 31 | F41: =IF($E41="","",IFERROR(LOOKUP(VALUE(LEFT($E41&"",FIND("-",$E41&"-")-1)),$C$57:$C$65,$D$57:$D$65),"")) -> 0 | G41: 0 | H41: =IF($G41="","n/a",IF($F41=$G41,"ok","MISMATCH")) -> ok | I41: 4500 | L41: FUT Esports
B42: Mixed | C42: Shadow & Vergo | D42: Field | E42: 32 | F42: =IF($E42="","",IFERROR(LOOKUP(VALUE(LEFT($E42&"",FIND("-",$E42&"-")-1)),$C$57:$C$65,$D$57:$D$65),"")) -> 0 | H42: =IF($G42="","n/a",IF($F42=$G42,"ok","MISMATCH")) -> n/a | I42: 4000 | J42: Shadow: Natrix Esports / Vergo: Gentle Mates | L42: Mixed
B43: Unlisted | C43: Aoxy & Jojofishy | D43: Field | E43: 33 | F43: =IF($E43="","",IFERROR(LOOKUP(VALUE(LEFT($E43&"",FIND("-",$E43&"-")-1)),$C$57:$C$65,$D$57:$D$65),"")) -> 0 | H43: =IF($G43="","n/a",IF($F43=$G43,"ok","MISMATCH")) -> n/a | I43: 3500 | L43: Unlisted
B44: ONIC Esports | C44: phoenix & Retro | D44: Field | E44: 34 | F44: =IF($E44="","",IFERROR(LOOKUP(VALUE(LEFT($E44&"",FIND("-",$E44&"-")-1)),$C$57:$C$65,$D$57:$D$65),"")) -> 0 | H44: =IF($G44="","n/a",IF($F44=$G44,"ok","MISMATCH")) -> n/a | I44: 3000 | L44: ONIC Esports
B45: Mixed | C45: Rainy & Nalu | D45: Field | E45: 35-36 | F45: =IF($E45="","",IFERROR(LOOKUP(VALUE(LEFT($E45&"",FIND("-",$E45&"-")-1)),$C$57:$C$65,$D$57:$D$65),"")) -> 0 | H45: =IF($G45="","n/a",IF($F45=$G45,"ok","MISMATCH")) -> n/a | I45: 2500 | J45: Rainy: DetonatioN FocusMe / Nalu: KIT Gaming Elite | L45: Mixed
B46: Fnatic | C46: Salko & Inact | D46: Field | E46: 35-36 | F46: =IF($E46="","",IFERROR(LOOKUP(VALUE(LEFT($E46&"",FIND("-",$E46&"-")-1)),$C$57:$C$65,$D$57:$D$65),"")) -> 0 | G46: 0 | H46: =IF($G46="","n/a",IF($F46=$G46,"ok","MISMATCH")) -> ok | I46: 2500 | J46: Fnatic entry | L46: Fnatic
B47: Mixed | C47: EpikWhale & PXMP | D47: Field | E47: 37-38 | F47: =IF($E47="","",IFERROR(LOOKUP(VALUE(LEFT($E47&"",FIND("-",$E47&"-")-1)),$C$57:$C$65,$D$57:$D$65),"")) -> 0 | H47: =IF($G47="","n/a",IF($F47=$G47,"ok","MISMATCH")) -> n/a | I47: 2250 | J47: EpikWhale: XP42 Esports / PXMP: Elite Esports | L47: Mixed
B48: Mixed | C48: Seven & axadasz | D48: Field | E48: 37-38 | F48: =IF($E48="","",IFERROR(LOOKUP(VALUE(LEFT($E48&"",FIND("-",$E48&"-")-1)),$C$57:$C$65,$D$57:$D$65),"")) -> 0 | H48: =IF($G48="","n/a",IF($F48=$G48,"ok","MISMATCH")) -> n/a | I48: 2250 | J48: Seven: 7VEN / axadasz: Natrix Esports | L48: Mixed
B49: PWR | C49: alex & Wreckless | D49: Field | E49: 39-40 | F49: =IF($E49="","",IFERROR(LOOKUP(VALUE(LEFT($E49&"",FIND("-",$E49&"-")-1)),$C$57:$C$65,$D$57:$D$65),"")) -> 0 | H49: =IF($G49="","n/a",IF($F49=$G49,"ok","MISMATCH")) -> n/a | I49: 2000 | L49: PWR
B50: Al Ahli Esports | C50: Snowvaks & Henchman | D50: Field | E50: 39-40 | F50: =IF($E50="","",IFERROR(LOOKUP(VALUE(LEFT($E50&"",FIND("-",$E50&"-")-1)),$C$57:$C$65,$D$57:$D$65),"")) -> 0 | H50: =IF($G50="","n/a",IF($F50=$G50,"ok","MISMATCH")) -> n/a | I50: 2000 | L50: Al Ahli Esports
B52: TOTAL POINTS AWARDED | F52: =SUM(F11:F50) -> 3050
B53: 3,050 club points awarded (BR curve). Prize money sums to $1,000,000 of the $1,025,000 pool.
B55: 2 · POINT SYSTEM
B56: Place | C56: Club points
C57: 1 | D57: 1000
C58: 2 | D58: 750
C59: 3 | D59: 500
C60: 4 | D60: 300
C61: 5 | D61: 200
C62: 6 | D62: 150
C63: 7 | D63: 100
C64: 8 | D64: 50
C65: 9 | D65: 0 | E65: 9th and below — no award
B68: 3 · HYBRID SEED — WHY, AND THE TRAP TO AVOID
B69: The hybrid. Default is method E: every duo shares one mean strength, so the title sigma alone drives outcomes. Promoting a duo to Elite in the Tier column gives it a stronger mean while the rest of the field stays undifferentiated — mechanically this is a two-cohort version of method D, with a small top band and one large flat band. It is the right shape when a handful of entrants are genuinely stronger but the remaining field cannot be ordered. THE TRAP: seed on RELOAD form, not Fortnite reputation. EWC26 is the evidence. Peterbot, widely rated the best Fortnite player in the world, finished 12th. Bugha, the 2019 World Cup champion, finished 22nd. EpikWhale finished 37th-38th. Meanwhile the winners, vic0 and Malibuca, arrived on the back of consecutive Reload LAN wins. Reload is a distinct mode with its own skillset, and general Fortnite pedigree predicted almost nothing here. If the Elite tier is populated from name recognition it will make the model worse than method E, not better. Populate it only from recent Reload-format results, and keep it small - two to four duos.
B76: Tier | C76: Duos (auto) | D76: Band from | E76: Band to | F76: Mean (mu) | G76: Within sigma
B77: Elite | C77: =COUNTIF($D$11:$D$50,$B77) -> 0 | D77: =1 -> 1 | E77: =D77+C77-1 -> 0 | F77: =IF(C77=0,"",(D77+E77)/2) | G77: =IF(C77=0,"",(E77-D77+1)/SQRT(12))
B78: Field | C78: =COUNTIF($D$11:$D$50,$B78) -> 40 | D78: =E77+1 -> 1 | E78: =D78+C78-1 -> 40 | F78: =IF(C78=0,"",(D78+E78)/2) -> 20.5 | G78: =IF(C78=0,"",(E78-D78+1)/SQRT(12)) -> 11.547005
B80: With every duo set to Field the Elite band is empty and the model is pure method E — expected points identical for all 40 duos at 3,050 / 40 = 76.3.
B81: OPEN QUESTION — mixed-club duos. Ten of the 40 duos pair players from different clubs (marked 'Mixed'). It is not established how the Club Championship allocates points for those, and no mixed duo finished top 8 except 2nd place (Momsy of Lyost with SkyJump of Ravens), neither of whom is a CC top-24 club, so it cannot be verified from the data we hold. Resolve before simulating this title.
B83: ANOMALY — HavoK by Vitality finished 4th, worth 300 points, but Team Vitality scored 0 in Fortnite. Either HavoK counts as a separate club, or the entry was ineligible for club points (the Clubs page marks some entries as not eligible due to joint ventures or late signings). Worth confirming, as it affects how partner-brand entries are modelled. RESOLVED: with all 25 titles built, crediting the 300 to Team Vitality puts them 300 above their official 3,300, and removing it reconciles them exactly. The entry is therefore joined as its own club, HavoK by Vitality, not as a Vitality entry.

Sheet Trackmania
B2: Trackmania — EWC 2026
B3: 1v1 racing. Seeds from the Elite Cup 2026 final standings — Ubisoft Nadeo's official Road-to-EWC ladder, method A.
B5: FORMAT | D5: FIELD SIZE | F5: TVI | H5: SEED METHOD | J5: SEED SOURCE | L5: PLACEMENT GRANULARITY
B6: Knockout, 32 players | D6: 32 players | F6: 22 · Low | H6: A — official qualification ladder | J6: Elite Cup 2026 standings (Feb–May 26) | L6: Bands (5-6, 7-8, then fours)
B8: 1 · FIELD & RESULTS
B9: All 32 players. Seed is the field ranked 1-32 by Elite Cup finishing position; the raw Elite Cup rank is kept alongside so the gap between ladder form and event result stays visible.
B10: Club | C10: Player | D10: Seed | E10: Elite Cup rank | F10: Placement | G10: Points (auto) | H10: Official CC pts | I10: Δ check | J10: Prize (USD) | K10: Notes | M10: Club (canonical)
B11: AG.AL International | C11: Gwen | D11: 9 | E11: 9 | F11: 1 | G11: =IF($F11="","",IFERROR(LOOKUP(VALUE(LEFT($F11&"",FIND("-",$F11&"-")-1)),$C$50:$C$56,$D$50:$D$56),"")) -> 1000 | H11: 1000 | I11: =IF($H11="","n/a",IF($G11=$H11,"ok","MISMATCH")) -> ok | J11: 130000 | K11: competes as All Gamers Global | M11: AG.AL International
B12: Team Liquid | C12: Epos | D12: 17 | E12: 18 | F12: 2 | G12: =IF($F12="","",IFERROR(LOOKUP(VALUE(LEFT($F12&"",FIND("-",$F12&"-")-1)),$C$50:$C$56,$D$50:$D$56),"")) -> 750 | H12: 750 | I12: =IF($H12="","n/a",IF($G12=$H12,"ok","MISMATCH")) -> ok | J12: 70000 | M12: Team Liquid
B13: Team Vitality | C13: Pac | D13: 13 | E13: 13 | F13: 3 | G13: =IF($F13="","",IFERROR(LOOKUP(VALUE(LEFT($F13&"",FIND("-",$F13&"-")-1)),$C$50:$C$56,$D$50:$D$56),"")) -> 500 | H13: 500 | I13: =IF($H13="","n/a",IF($G13=$H13,"ok","MISMATCH")) -> ok | J13: 35000 | M13: Team Vitality
B14: Natus Vincere | C14: mime | D14: 12 | E14: 12 | F14: 4 | G14: =IF($F14="","",IFERROR(LOOKUP(VALUE(LEFT($F14&"",FIND("-",$F14&"-")-1)),$C$50:$C$56,$D$50:$D$56),"")) -> 300 | H14: 300 | I14: =IF($H14="","n/a",IF($G14=$H14,"ok","MISMATCH")) -> ok | J14: 25000 | M14: Natus Vincere
B15: Team Nemesis | C15: eLconn21 | D15: 6 | E15: 6 | F15: 5-6 | G15: =IF($F15="","",IFERROR(LOOKUP(VALUE(LEFT($F15&"",FIND("-",$F15&"-")-1)),$C$50:$C$56,$D$50:$D$56),"")) -> 200 | H15: 200 | I15: =IF($H15="","n/a",IF($G15=$H15,"ok","MISMATCH")) -> ok | J15: 20000 | M15: Team Nemesis
B16: BIG | C16: GranaDy | D16: 2 | E16: 2 | F16: 5-6 | G16: =IF($F16="","",IFERROR(LOOKUP(VALUE(LEFT($F16&"",FIND("-",$F16&"-")-1)),$C$50:$C$56,$D$50:$D$56),"")) -> 200 | H16: 200 | I16: =IF($H16="","n/a",IF($G16=$H16,"ok","MISMATCH")) -> ok | J16: 20000 | M16: BIG
B17: Team Liquid | C17: Otaaaq | D17: 10 | E17: 10 | F17: 7-8 | G17: =IF($F17="","",IFERROR(LOOKUP(VALUE(LEFT($F17&"",FIND("-",$F17&"-")-1)),$C$50:$C$56,$D$50:$D$56),"")) -> 100 | I17: =IF($H17="","n/a",IF($G17=$H17,"ok","MISMATCH")) -> n/a | J17: 15000 | K17: Liquid's second entry — best-only rule means it scores nothing | M17: Team Liquid
B18: GodLike Esports | C18: Stufts | D18: 16 | E18: 17 | F18: 7-8 | G18: =IF($F18="","",IFERROR(LOOKUP(VALUE(LEFT($F18&"",FIND("-",$F18&"-")-1)),$C$50:$C$56,$D$50:$D$56),"")) -> 100 | I18: =IF($H18="","n/a",IF($G18=$H18,"ok","MISMATCH")) -> n/a | J18: 15000 | M18: GodLike
B19: AG.AL International | C19: Binkss | D19: 1 | E19: 1 | F19: 9-12 | G19: =IF($F19="","",IFERROR(LOOKUP(VALUE(LEFT($F19&"",FIND("-",$F19&"-")-1)),$C$50:$C$56,$D$50:$D$56),"")) -> 0 | I19: =IF($H19="","n/a",IF($G19=$H19,"ok","MISMATCH")) -> n/a | J19: 12500 | K19: Elite Cup winner; AG.AL second entry | M19: AG.AL International
B20: Team Falcons | C20: Carl Jr. | D20: 8 | E20: 8 | F20: 9-12 | G20: =IF($F20="","",IFERROR(LOOKUP(VALUE(LEFT($F20&"",FIND("-",$F20&"-")-1)),$C$50:$C$56,$D$50:$D$56),"")) -> 0 | H20: 0 | I20: =IF($H20="","n/a",IF($G20=$H20,"ok","MISMATCH")) -> ok | J20: 12500 | M20: Team Falcons
B21: BIG | C21: Massa | D21: 3 | E21: 3 | F21: 9-12 | G21: =IF($F21="","",IFERROR(LOOKUP(VALUE(LEFT($F21&"",FIND("-",$F21&"-")-1)),$C$50:$C$56,$D$50:$D$56),"")) -> 0 | I21: =IF($H21="","n/a",IF($G21=$H21,"ok","MISMATCH")) -> n/a | J21: 12500 | K21: BIG second entry | M21: BIG
B22: VP x Neon | C22: Pusztitopako | D22: 21 | E22: 26 | F22: 9-12 | G22: =IF($F22="","",IFERROR(LOOKUP(VALUE(LEFT($F22&"",FIND("-",$F22&"-")-1)),$C$50:$C$56,$D$50:$D$56),"")) -> 0 | I22: =IF($H22="","n/a",IF($G22=$H22,"ok","MISMATCH")) -> n/a | J22: 12500 | K22: partner brand — points did not accrue to Virtus.pro | M22: VP x Neon
B23: Twisted Minds | C23: Bren | D23: 15 | E23: 16 | F23: 13-16 | G23: =IF($F23="","",IFERROR(LOOKUP(VALUE(LEFT($F23&"",FIND("-",$F23&"-")-1)),$C$50:$C$56,$D$50:$D$56),"")) -> 0 | H23: 0 | I23: =IF($H23="","n/a",IF($G23=$H23,"ok","MISMATCH")) -> ok | J23: 10000 | M23: Twisted Minds
B24: w. | C24: josh1248 | D24: 19 | E24: 20 | F24: 13-16 | G24: =IF($F24="","",IFERROR(LOOKUP(VALUE(LEFT($F24&"",FIND("-",$F24&"-")-1)),$C$50:$C$56,$D$50:$D$56),"")) -> 0 | I24: =IF($H24="","n/a",IF($G24=$H24,"ok","MISMATCH")) -> n/a | J24: 10000 | M24: w.
B25: (no club) | C25: neon | D25: 24 | E25: 44 | F25: 13-16 | G25: =IF($F25="","",IFERROR(LOOKUP(VALUE(LEFT($F25&"",FIND("-",$F25&"-")-1)),$C$50:$C$56,$D$50:$D$56),"")) -> 0 | I25: =IF($H25="","n/a",IF($G25=$H25,"ok","MISMATCH")) -> n/a | J25: 10000 | M25: (no club)
B26: w. | C26: Richie | D26: 20 | E26: 24 | F26: 13-16 | G26: =IF($F26="","",IFERROR(LOOKUP(VALUE(LEFT($F26&"",FIND("-",$F26&"-")-1)),$C$50:$C$56,$D$50:$D$56),"")) -> 0 | I26: =IF($H26="","n/a",IF($G26=$H26,"ok","MISMATCH")) -> n/a | J26: 10000 | K26: listed as Richie1308 in Elite Cup | M26: w.
B27: ROC Esports | C27: Mudda | D27: 4 | E27: 4 | F27: 17-20 | G27: =IF($F27="","",IFERROR(LOOKUP(VALUE(LEFT($F27&"",FIND("-",$F27&"-")-1)),$C$50:$C$56,$D$50:$D$56),"")) -> 0 | H27: 0 | I27: =IF($H27="","n/a",IF($G27=$H27,"ok","MISMATCH")) -> ok | J27: 8000 | M27: ROC Esports
B28: FUT Esports | C28: Nayko | D28: 7 | E28: 7 | F28: 17-20 | G28: =IF($F28="","",IFERROR(LOOKUP(VALUE(LEFT($F28&"",FIND("-",$F28&"-")-1)),$C$50:$C$56,$D$50:$D$56),"")) -> 0 | H28: 0 | I28: =IF($H28="","n/a",IF($G28=$H28,"ok","MISMATCH")) -> ok | J28: 8000 | M28: FUT Esports
B29: S8UL Esports | C29: Whizzy | D29: 18 | E29: 19 | F29: 17-20 | G29: =IF($F29="","",IFERROR(LOOKUP(VALUE(LEFT($F29&"",FIND("-",$F29&"-")-1)),$C$50:$C$56,$D$50:$D$56),"")) -> 0 | H29: 0 | I29: =IF($H29="","n/a",IF($G29=$H29,"ok","MISMATCH")) -> ok | J29: 8000 | M29: S8UL Esports
B30: Gen.G Esports | C30: Wosile | D30: 5 | E30: 5 | F30: 17-20 | G30: =IF($F30="","",IFERROR(LOOKUP(VALUE(LEFT($F30&"",FIND("-",$F30&"-")-1)),$C$50:$C$56,$D$50:$D$56),"")) -> 0 | H30: 0 | I30: =IF($H30="","n/a",IF($G30=$H30,"ok","MISMATCH")) -> ok | J30: 8000 | M30: Gen.G Esports
B31: (no club) | C31: Affi | D31: 14 | E31: 14 | F31: 21-24 | G31: =IF($F31="","",IFERROR(LOOKUP(VALUE(LEFT($F31&"",FIND("-",$F31&"-")-1)),$C$50:$C$56,$D$50:$D$56),"")) -> 0 | I31: =IF($H31="","n/a",IF($G31=$H31,"ok","MISMATCH")) -> n/a | J31: 6000 | M31: (no club)
B32: Team Heretics | C32: Flimsy | D32: 25 | E32: 45 | F32: 21-24 | G32: =IF($F32="","",IFERROR(LOOKUP(VALUE(LEFT($F32&"",FIND("-",$F32&"-")-1)),$C$50:$C$56,$D$50:$D$56),"")) -> 0 | H32: 0 | I32: =IF($H32="","n/a",IF($G32=$H32,"ok","MISMATCH")) -> ok | J32: 6000 | M32: Team Heretics
B33: (no club) | C33: LinkMax | D33: 28 | E33: 65 | F33: 21-24 | G33: =IF($F33="","",IFERROR(LOOKUP(VALUE(LEFT($F33&"",FIND("-",$F33&"-")-1)),$C$50:$C$56,$D$50:$D$56),"")) -> 0 | I33: =IF($H33="","n/a",IF($G33=$H33,"ok","MISMATCH")) -> n/a | J33: 6000 | K33: UNVERIFIED Elite Cup match — two entries named 'link' (65, 82) | M33: (no club)
B34: (no club) | C34: Soulja | D34: 11 | E34: 11 | F34: 21-24 | G34: =IF($F34="","",IFERROR(LOOKUP(VALUE(LEFT($F34&"",FIND("-",$F34&"-")-1)),$C$50:$C$56,$D$50:$D$56),"")) -> 0 | I34: =IF($H34="","n/a",IF($G34=$H34,"ok","MISMATCH")) -> n/a | J34: 6000 | M34: (no club)
B35: Rex Regum Qeon | C35: Cemko | D35: 23 | E35: 36 | F35: 25-28 | G35: =IF($F35="","",IFERROR(LOOKUP(VALUE(LEFT($F35&"",FIND("-",$F35&"-")-1)),$C$50:$C$56,$D$50:$D$56),"")) -> 0 | H35: 0 | I35: =IF($H35="","n/a",IF($G35=$H35,"ok","MISMATCH")) -> ok | J35: 4000 | M35: Rex Regum Qeon
B36: Titan Esports Club | C36: Charles | D36: 26 | E36: 48 | F36: 25-28 | G36: =IF($F36="","",IFERROR(LOOKUP(VALUE(LEFT($F36&"",FIND("-",$F36&"-")-1)),$C$50:$C$56,$D$50:$D$56),"")) -> 0 | H36: 0 | I36: =IF($H36="","n/a",IF($G36=$H36,"ok","MISMATCH")) -> ok | J36: 4000 | M36: Titan Esports Club
B37: GodLike Esports | C37: L1ngo | D37: 22 | E37: 30 | F37: 25-28 | G37: =IF($F37="","",IFERROR(LOOKUP(VALUE(LEFT($F37&"",FIND("-",$F37&"-")-1)),$C$50:$C$56,$D$50:$D$56),"")) -> 0 | I37: =IF($H37="","n/a",IF($G37=$H37,"ok","MISMATCH")) -> n/a | J37: 4000 | K37: GodLike second entry | M37: GodLike
B38: S8UL Esports | C38: Neal | D38: 29 | E38: 66 | F38: 25-28 | G38: =IF($F38="","",IFERROR(LOOKUP(VALUE(LEFT($F38&"",FIND("-",$F38&"-")-1)),$C$50:$C$56,$D$50:$D$56),"")) -> 0 | I38: =IF($H38="","n/a",IF($G38=$H38,"ok","MISMATCH")) -> n/a | J38: 4000 | K38: S8UL second entry | M38: S8UL Esports
B39: Sentinels | C39: Baiwack | D39: 32 | E39: 108 | F39: 29-32 | G39: =IF($F39="","",IFERROR(LOOKUP(VALUE(LEFT($F39&"",FIND("-",$F39&"-")-1)),$C$50:$C$56,$D$50:$D$56),"")) -> 0 | H39: 0 | I39: =IF($H39="","n/a",IF($G39=$H39,"ok","MISMATCH")) -> ok | J39: 2000 | M39: Sentinels
B40: Fnatic | C40: JSwag | D40: 30 | E40: 68 | F40: 29-32 | G40: =IF($F40="","",IFERROR(LOOKUP(VALUE(LEFT($F40&"",FIND("-",$F40&"-")-1)),$C$50:$C$56,$D$50:$D$56),"")) -> 0 | H40: 0 | I40: =IF($H40="","n/a",IF($G40=$H40,"ok","MISMATCH")) -> ok | J40: 2000 | K40: Fnatic entry; listed as J_Swag in Elite Cup | M40: Fnatic
B41: Leviatán | C41: noiszia | D41: 27 | E41: 56 | F41: 29-32 | G41: =IF($F41="","",IFERROR(LOOKUP(VALUE(LEFT($F41&"",FIND("-",$F41&"-")-1)),$C$50:$C$56,$D$50:$D$56),"")) -> 0 | H41: 0 | I41: =IF($H41="","n/a",IF($G41=$H41,"ok","MISMATCH")) -> ok | J41: 2000 | M41: Leviatán
B42: S8UL Esports | C42: Spark | D42: 31 | E42: 95 | F42: 29-32 | G42: =IF($F42="","",IFERROR(LOOKUP(VALUE(LEFT($F42&"",FIND("-",$F42&"-")-1)),$C$50:$C$56,$D$50:$D$56),"")) -> 0 | I42: =IF($H42="","n/a",IF($G42=$H42,"ok","MISMATCH")) -> n/a | J42: 2000 | K42: S8UL third entry | M42: S8UL Esports
B44: TOTAL POINTS AWARDED | G44: =SUM(G11:G42) -> 3150
B45: 3,150 club points — a THIRD distinct total. Playoff titles award 3,350, battle royales 3,050, Trackmania 3,150. Prize money sums to the full $500,000.
B48: 2 · POINT SYSTEM
B49: From place | C49: Club points | D49: Band
C50: 1 | D50: 1000 | E50: 1st
C51: 2 | D51: 750 | E51: 2nd
C52: 3 | D52: 500 | E52: 3rd
C53: 4 | D53: 300 | E53: 4th
C54: 5 | D54: 200 | E54: 5th-6th
C55: 7 | D55: 100 | E55: 7th-8th
C56: 9 | D56: 0 | E56: 9th-32nd
B59: 3 · SEED SOURCE — Elite Cup 2026
B60: The Elite Cup is Ubisoft Nadeo's official Road-to-EWC ladder, run online from February to May 2026 across ten map-nations, with 126 ranked participants. It is the only published pre-event ranking for Trackmania, it is the mechanism that actually awarded EWC slots, and it is ordinal rather than a rating — so seeds carry rank but no strength gaps. WHAT 2026 SHOWED: the ladder did not transfer cleanly to the LAN. Elite Cup winner Binkss finished 9th-12th; 2nd-placed GranaDy took 5th-6th; 3rd-placed Massa 9th-12th; 4th-placed Mudda 17th-20th. The EWC champion Gwen came from 9th on the ladder and the runner-up Epos from 18th. That is a weaker seed-to-outcome relationship than the TVI of 22 implies, and worth watching: Trackmania is scored as a low-volatility title on the strength of an elite that converts, but the ladder rank itself proved a poor predictor of finishing position at this event.
B67: Seed | C67: Player | D67: Elite Cup rank | E67: Result | F67: Seed − result
B68: 1 | C68: Binkss | D68: 1 | E68: 9-12 | F68: -8
B69: 2 | C69: GranaDy | D69: 2 | E69: 5-6 | F69: -3
B70: 3 | C70: Massa | D70: 3 | E70: 9-12 | F70: -6
B71: 4 | C71: Mudda | D71: 4 | E71: 17-20 | F71: -13
B72: 5 | C72: Wosile | D72: 5 | E72: 17-20 | F72: -12
B73: 6 | C73: eLconn21 | D73: 6 | E73: 5-6 | F73: 1
B74: 7 | C74: Nayko | D74: 7 | E74: 17-20 | F74: -10
B75: 8 | C75: Carl Jr. | D75: 8 | E75: 9-12 | F75: -1
B76: 9 | C76: Gwen | D76: 9 | E76: 1 | F76: 8
B77: 10 | C77: Otaaaq | D77: 10 | E77: 7-8 | F77: 3
B78: 11 | C78: Soulja | D78: 11 | E78: 21-24 | F78: -10
B79: 12 | C79: mime | D79: 12 | E79: 4 | F79: 8
... B99: 32 | C99: Baiwack | D99: 108 | E99: 29-32 | F99: 3

Sheet Dota 2
B2: Dota 2 — EWC 2026
B3: Seeds from the ESL Pro Tour 2025/2026 Leaderboard — method A, and unusually good, because EPT publishes numeric points rather than bare ranks.
B5: FORMAT | D5: FIELD SIZE | F5: TVI | H5: SEED METHOD | J5: SEED SOURCE | L5: PLACEMENT GRANULARITY
B6: Round-robin groups → single-elim | D6: 24 teams | F6: 55 · Medium | H6: A — circuit points | J6: ESL Pro Tour 2025/26 Leaderboard | L6: Bands (5-8, then fours)
B8: 1 · FIELD & RESULTS
B9: All 24 teams. Seed ranks the field by EPT points; five teams carry no EPT ranking and are seeded last, flagged in Notes. Event names differ from club names in several cases (PVISION/PARIVISION, BB Team/BetBoom, PTime/PlayTime) — the Club column carries the canonical name used for reconciliation.
B10: Club | C10: Event name | D10: Seed | E10: EPT rank | F10: EPT points | G10: Placement | H10: Points (auto) | I10: Official CC pts | J10: Δ check | K10: Prize (USD) | L10: Notes | N10: Club (canonical)
B11: PARIVISION | C11: PVISION | D11: 1 | E11: 2 | F11: 14510 | G11: 1 | H11: =IF($G11="","",IFERROR(LOOKUP(VALUE(LEFT($G11&"",FIND("-",$G11&"-")-1)),$C$40:$C$45,$D$40:$D$45),"")) -> 1000 | I11: 1000 | J11: =IF($I11="","n/a",IF($H11=$I11,"ok","MISMATCH")) -> ok | K11: 750000 | L11: EPT #2 | N11: PARIVISION
B12: BetBoom Team | C12: BB Team | D12: 8 | E12: 9 | F12: 2860 | G12: 2 | H12: =IF($G12="","",IFERROR(LOOKUP(VALUE(LEFT($G12&"",FIND("-",$G12&"-")-1)),$C$40:$C$45,$D$40:$D$45),"")) -> 750 | I12: 750 | J12: =IF($I12="","n/a",IF($H12=$I12,"ok","MISMATCH")) -> ok | K12: 340000 | L12: EPT #9 | N12: BetBoom Team
B13: Team Yandex | C13: Team Yandex | D13: 4 | E13: 5 | F13: 10400 | G13: 3 | H13: =IF($G13="","",IFERROR(LOOKUP(VALUE(LEFT($G13&"",FIND("-",$G13&"-")-1)),$C$40:$C$45,$D$40:$D$45),"")) -> 500 | I13: 500 | J13: =IF($I13="","n/a",IF($H13=$I13,"ok","MISMATCH")) -> ok | K13: 200000 | N13: Team Yandex
B14: Vici Gaming | C14: Vici Gaming | D14: 14 | E14: 16 | F14: 655 | G14: 4 | H14: =IF($G14="","",IFERROR(LOOKUP(VALUE(LEFT($G14&"",FIND("-",$G14&"-")-1)),$C$40:$C$45,$D$40:$D$45),"")) -> 300 | I14: 300 | J14: =IF($I14="","n/a",IF($H14=$I14,"ok","MISMATCH")) -> ok | K14: 120000 | L14: EPT #16 — deep run from a low seed | N14: Vici Gaming
B15: Nigma Galaxy | C15: Nigma Galaxy | D15: 15 | E15: 17 | F15: 640 | G15: 5-8 | H15: =IF($G15="","",IFERROR(LOOKUP(VALUE(LEFT($G15&"",FIND("-",$G15&"-")-1)),$C$40:$C$45,$D$40:$D$45),"")) -> 200 | I15: 200 | J15: =IF($I15="","n/a",IF($H15=$I15,"ok","MISMATCH")) -> ok | K15: 70000 | N15: Nigma Galaxy
B16: Team Falcons | C16: Team Falcons | D16: 6 | E16: 7 | F16: 8125 | G16: 5-8 | H16: =IF($G16="","",IFERROR(LOOKUP(VALUE(LEFT($G16&"",FIND("-",$G16&"-")-1)),$C$40:$C$45,$D$40:$D$45),"")) -> 200 | I16: 200 | J16: =IF($I16="","n/a",IF($H16=$I16,"ok","MISMATCH")) -> ok | K16: 70000 | N16: Team Falcons
B17: Team Spirit | C17: Team Spirit | D17: 5 | E17: 6 | F17: 10300 | G17: 5-8 | H17: =IF($G17="","",IFERROR(LOOKUP(VALUE(LEFT($G17&"",FIND("-",$G17&"-")-1)),$C$40:$C$45,$D$40:$D$45),"")) -> 200 | I17: 200 | J17: =IF($I17="","n/a",IF($H17=$I17,"ok","MISMATCH")) -> ok | K17: 70000 | N17: Team Spirit
B18: Rune Eaters | C18: Rune Eaters | D18: 20 | E18: — | G18: 5-8 | H18: =IF($G18="","",IFERROR(LOOKUP(VALUE(LEFT($G18&"",FIND("-",$G18&"-")-1)),$C$40:$C$45,$D$40:$D$45),"")) -> 200 | J18: =IF($I18="","n/a",IF($H18=$I18,"ok","MISMATCH")) -> n/a | K18: 70000 | L18: NOT on the EPT leaderboard — unranked entry reaching top 8 | N18: Rune Eaters Esports
B19: LGD Gaming | C19: LGD Gaming | D19: 21 | E19: — | G19: 9-12 | H19: =IF($G19="","",IFERROR(LOOKUP(VALUE(LEFT($G19&"",FIND("-",$G19&"-")-1)),$C$40:$C$45,$D$40:$D$45),"")) -> 0 | J19: =IF($I19="","n/a",IF($H19=$I19,"ok","MISMATCH")) -> n/a | K19: 40000 | L19: not on EPT leaderboard | N19: LGD Gaming
B20: 1w Team | C20: 1w | D20: 18 | E20: 22 | F20: 140 | G20: 9-12 | H20: =IF($G20="","",IFERROR(LOOKUP(VALUE(LEFT($G20&"",FIND("-",$G20&"-")-1)),$C$40:$C$45,$D$40:$D$45),"")) -> 0 | J20: =IF($I20="","n/a",IF($H20=$I20,"ok","MISMATCH")) -> n/a | K20: 40000 | N20: 1w Team
B21: Team Liquid | C21: Team Liquid | D21: 7 | E21: 8 | F21: 4650 | G21: 9-12 | H21: =IF($G21="","",IFERROR(LOOKUP(VALUE(LEFT($G21&"",FIND("-",$G21&"-")-1)),$C$40:$C$45,$D$40:$D$45),"")) -> 0 | I21: 0 | J21: =IF($I21="","n/a",IF($H21=$I21,"ok","MISMATCH")) -> ok | K21: 40000 | N21: Team Liquid
B22: Aurora Gaming | C22: Aurora Gaming | D22: 2 | E22: 3 | F22: 13230 | G22: 9-12 | H22: =IF($G22="","",IFERROR(LOOKUP(VALUE(LEFT($G22&"",FIND("-",$G22&"-")-1)),$C$40:$C$45,$D$40:$D$45),"")) -> 0 | I22: 0 | J22: =IF($I22="","n/a",IF($H22=$I22,"ok","MISMATCH")) -> ok | K22: 40000 | L22: EPT #3 — biggest underperformance in the field | N22: Aurora Gaming
B23: MOUZ | C23: MOUZ | D23: 9 | E23: 10 | F23: 2760 | G23: 13-16 | H23: =IF($G23="","",IFERROR(LOOKUP(VALUE(LEFT($G23&"",FIND("-",$G23&"-")-1)),$C$40:$C$45,$D$40:$D$45),"")) -> 0 | I23: 0 | J23: =IF($I23="","n/a",IF($H23=$I23,"ok","MISMATCH")) -> ok | K23: 20000 | N23: MOUZ
B24: PlayTime | C24: PTime | D24: 10 | E24: 11 | F24: 2662 | G24: 13-16 | H24: =IF($G24="","",IFERROR(LOOKUP(VALUE(LEFT($G24&"",FIND("-",$G24&"-")-1)),$C$40:$C$45,$D$40:$D$45),"")) -> 0 | J24: =IF($I24="","n/a",IF($H24=$I24,"ok","MISMATCH")) -> n/a | K24: 20000 | N24: PlayTime
B25: Xtreme Gaming | C25: Xtreme Gaming | D25: 3 | E25: 4 | F25: 10560 | G25: 13-16 | H25: =IF($G25="","",IFERROR(LOOKUP(VALUE(LEFT($G25&"",FIND("-",$G25&"-")-1)),$C$40:$C$45,$D$40:$D$45),"")) -> 0 | J25: =IF($I25="","n/a",IF($H25=$I25,"ok","MISMATCH")) -> n/a | K25: 20000 | L25: EPT #4 | N25: Xtreme Gaming
B26: Virtus.pro | C26: Virtus.pro | D26: 12 | E26: 13 | F26: 1975 | G26: 13-16 | H26: =IF($G26="","",IFERROR(LOOKUP(VALUE(LEFT($G26&"",FIND("-",$G26&"-")-1)),$C$40:$C$45,$D$40:$D$45),"")) -> 0 | I26: 0 | J26: =IF($I26="","n/a",IF($H26=$I26,"ok","MISMATCH")) -> ok | K26: 20000 | N26: Virtus.pro
B27: GamerLegion | C27: GamerLegion | D27: 13 | E27: 15 | F27: 1172 | G27: 17-20 | H27: =IF($G27="","",IFERROR(LOOKUP(VALUE(LEFT($G27&"",FIND("-",$G27&"-")-1)),$C$40:$C$45,$D$40:$D$45),"")) -> 0 | J27: =IF($I27="","n/a",IF($H27=$I27,"ok","MISMATCH")) -> n/a | K27: 10000 | N27: GamerLegion
B28: Level UP | C28: Level UP | D28: 22 | E28: — | G28: 17-20 | H28: =IF($G28="","",IFERROR(LOOKUP(VALUE(LEFT($G28&"",FIND("-",$G28&"-")-1)),$C$40:$C$45,$D$40:$D$45),"")) -> 0 | J28: =IF($I28="","n/a",IF($H28=$I28,"ok","MISMATCH")) -> n/a | K28: 10000 | L28: not on EPT leaderboard | N28: Level UP
B29: REKONIX | C29: REKONIX | D29: 17 | E29: 21 | F29: 160 | G29: 17-20 | H29: =IF($G29="","",IFERROR(LOOKUP(VALUE(LEFT($G29&"",FIND("-",$G29&"-")-1)),$C$40:$C$45,$D$40:$D$45),"")) -> 0 | J29: =IF($I29="","n/a",IF($H29=$I29,"ok","MISMATCH")) -> n/a | K29: 10000 | N29: REKONIX
B30: OG | C30: OG | D30: 11 | E30: 12 | F30: 2180 | G30: 17-20 | H30: =IF($G30="","",IFERROR(LOOKUP(VALUE(LEFT($G30&"",FIND("-",$G30&"-")-1)),$C$40:$C$45,$D$40:$D$45),"")) -> 0 | J30: =IF($I30="","n/a",IF($H30=$I30,"ok","MISMATCH")) -> n/a | K30: 10000 | N30: OG
B31: Poor Rangers | C31: Poor Rangers | D31: 16 | E31: 19 | F31: 400 | G31: 21-24 | H31: =IF($G31="","",IFERROR(LOOKUP(VALUE(LEFT($G31&"",FIND("-",$G31&"-")-1)),$C$40:$C$45,$D$40:$D$45),"")) -> 0 | J31: =IF($I31="","n/a",IF($H31=$I31,"ok","MISMATCH")) -> n/a | K31: 7500 | L31: matched to 'Power Rangers' on EPT — VERIFY | N31: Poor Rangers
B32: L1 TEAM | C32: L1 TEAM | D32: 23 | E32: — | G32: 21-24 | H32: =IF($G32="","",IFERROR(LOOKUP(VALUE(LEFT($G32&"",FIND("-",$G32&"-")-1)),$C$40:$C$45,$D$40:$D$45),"")) -> 0 | J32: =IF($I32="","n/a",IF($H32=$I32,"ok","MISMATCH")) -> n/a | K32: 7500 | L32: not on EPT leaderboard | N32: L1 TEAM
B33: Team Nemesis | C33: Team Nemesis | D33: 19 | E33: — | F33: 0 | G33: 21-24 | H33: =IF($G33="","",IFERROR(LOOKUP(VALUE(LEFT($G33&"",FIND("-",$G33&"-")-1)),$C$40:$C$45,$D$40:$D$45),"")) -> 0 | I33: 0 | J33: =IF($I33="","n/a",IF($H33=$I33,"ok","MISMATCH")) -> ok | K33: 7500 | L33: on EPT leaderboard with 0 points | N33: Team Nemesis
B34: IC x Insanity | C34: IC x Insanity | D34: 24 | E34: — | G34: 21-24 | H34: =IF($G34="","",IFERROR(LOOKUP(VALUE(LEFT($G34&"",FIND("-",$G34&"-")-1)),$C$40:$C$45,$D$40:$D$45),"")) -> 0 | J34: =IF($I34="","n/a",IF($H34=$I34,"ok","MISMATCH")) -> n/a | K34: 7500 | L34: not on EPT leaderboard | N34: IC x Insanity
B36: TOTAL POINTS AWARDED | H36: =SUM(H11:H34) -> 3350
B37: 3,350 club points — the standard playoff curve. Prize money sums to the full $2,000,000.
B38: 2 · POINT SYSTEM
B39: From place | C39: Club points | D39: Band
C40: 1 | D40: 1000 | E40: 1st
C41: 2 | D41: 750 | E41: 2nd
C42: 3 | D42: 500 | E42: 3rd
C43: 4 | D43: 300 | E43: 4th
C44: 5 | D44: 200 | E44: 5th-8th
C45: 9 | D45: 0 | E45: 9th-24th
B48: 3 · SEED SOURCE — ESL Pro Tour 2025/26 Leaderboard
B49: The EPT leaderboard is the season-long ESL circuit ranking and the best seed source we have for Dota: it carries numeric points, so strength gaps are measurable rather than ordinal — Tundra on 16,710 versus Execration on 48 is a real distance, not just 24 places. TWO CAVEATS. First, five EWC entrants (Rune Eaters, LGD Gaming, Level UP, L1 TEAM, IC x Insanity) do not appear on the leaderboard at all; they are seeded last here, but that is an assumption, not a measurement — and Rune Eaters promptly finished 5th-8th, so the assumption was wrong for them. Second, the leaderboard is not an EWC qualification ladder: EPT #1 Tundra Esports did not attend at all. WHAT 2026 SHOWED: mixed. The champion PVISION came from EPT #2, and Spirit and Falcons converted top-seven seeds into top-eight finishes. But Aurora at EPT #3 went out in 9th-12th, Xtreme Gaming at #4 in 13th-16th, and Vici Gaming reached 4th from #16. That spread is consistent with a TVI of 55 — favourites go deep more often than not, but conversion is unreliable.
B56: EPT rank | C56: Team | D56: EPT points | E56: At EWC?
B57: 1 | C57: Tundra Esports | D57: 16710 | E57: no
B58: 2 | C58: PARIVISION | D58: 14510 | E58: Yes
B59: 3 | C59: Aurora Gaming | D59: 13230 | E59: Yes
B60: 4 | C60: Xtreme Gaming | D60: 10560 | E60: Yes
B61: 5 | C61: Team Yandex | D61: 10400 | E61: Yes
B62: 6 | C62: Team Spirit | D62: 10300 | E62: Yes
B63: 7 | C63: Team Falcons | D63: 8125 | E63: Yes
B64: 8 | C64: Team Liquid | D64: 4650 | E64: Yes
B65: 9 | C65: BetBoom Team | D65: 2860 | E65: Yes
B66: 10 | C66: MOUZ | D66: 2760 | E66: Yes
B67: 11 | C67: PlayTime | D67: 2662 | E67: Yes
B68: 12 | C68: OG | D68: 2180 | E68: Yes
... B80: 24 | C80: Execration | D80: 48 | E80: no

Sheet Tekken 8
B2: Tekken 8 — EWC 2026
B3: 1v1 fighting game. Seeds from the Tekken World Tour 2026 Global Points Standings — method A, 250 ranked players with numeric points.
B5: FORMAT | D5: FIELD SIZE | F5: TVI | H5: SEED METHOD | J5: SEED SOURCE | L5: PLACEMENT GRANULARITY
B6: Bracket, 32 players | D6: 32 players | F6: 36 · Low | H6: A — circuit points | J6: TWT 2026 Global Points Standings | L6: Bands (5-8, 9-12, 13-16, 17-24, 25-32)
B8: 1 · FIELD & RESULTS
B9: All 32 players. Seed ranks the field by TWT global points; the raw TWT rank sits alongside so the gap between circuit form and event result stays visible.
B10: Club | C10: Player | D10: Seed | E10: TWT rank | F10: TWT points | G10: Placement | H10: Points (auto) | I10: Official CC pts | J10: Δ check | K10: Prize (USD) | L10: Notes | N10: Club (canonical)
B11: AG.AL International | C11: M. Zubair | D11: 27 | E11: 52 | F11: 315 | G11: 1 | H11: =IF($G11="","",IFERROR(LOOKUP(VALUE(LEFT($G11&"",FIND("-",$G11&"-")-1)),$C$48:$C$53,$D$48:$D$53),"")) -> 1000 | I11: 1000 | J11: =IF($I11="","n/a",IF($H11=$I11,"ok","MISMATCH")) -> ok | K11: 250000 | L11: major overperformance vs seed (27 → 1) | N11: AG.AL International
B12: DRX | C12: LowHigh | D12: 4 | E12: 4 | F12: 1385 | G12: 2 | H12: =IF($G12="","",IFERROR(LOOKUP(VALUE(LEFT($G12&"",FIND("-",$G12&"-")-1)),$C$48:$C$53,$D$48:$D$53),"")) -> 750 | I12: 750 | J12: =IF($I12="","n/a",IF($H12=$I12,"ok","MISMATCH")) -> ok | K12: 130000 | N12: DRX
B13: (no club tag) | C13: Yagami | D13: 19 | E13: 23 | F13: 660 | G13: 3 | H13: =IF($G13="","",IFERROR(LOOKUP(VALUE(LEFT($G13&"",FIND("-",$G13&"-")-1)),$C$48:$C$53,$D$48:$D$53),"")) -> 500 | J13: =IF($I13="","n/a",IF($H13=$I13,"ok","MISMATCH")) -> n/a | K13: 70000 | L13: major overperformance vs seed (19 → 3) | N13: (no club tag)
B14: Twisted Minds | C14: Arslan Ash | D14: 2 | E14: 2 | F14: 1520 | G14: 4 | H14: =IF($G14="","",IFERROR(LOOKUP(VALUE(LEFT($G14&"",FIND("-",$G14&"-")-1)),$C$48:$C$53,$D$48:$D$53),"")) -> 300 | I14: 300 | J14: =IF($I14="","n/a",IF($H14=$I14,"ok","MISMATCH")) -> ok | K14: 50000 | N14: Twisted Minds
B15: Team Vitality | C15: JeonDDing | D15: 13 | E15: 14 | F15: 925 | G15: 5-8 | H15: =IF($G15="","",IFERROR(LOOKUP(VALUE(LEFT($G15&"",FIND("-",$G15&"-")-1)),$C$48:$C$53,$D$48:$D$53),"")) -> 200 | I15: 200 | J15: =IF($I15="","n/a",IF($H15=$I15,"ok","MISMATCH")) -> ok | K15: 37500 | N15: Team Vitality
B16: SOOPers | C16: ULSAN | D16: 9 | E16: 9 | F16: 1095 | G16: 5-8 | H16: =IF($G16="","",IFERROR(LOOKUP(VALUE(LEFT($G16&"",FIND("-",$G16&"-")-1)),$C$48:$C$53,$D$48:$D$53),"")) -> 200 | I16: 200 | J16: =IF($I16="","n/a",IF($H16=$I16,"ok","MISMATCH")) -> ok | K16: 37500 | N16: SOOPers
B17: REJECT | C17: Raef | D17: 31 | E17: 81 | F17: 221 | G17: 5-8 | H17: =IF($G17="","",IFERROR(LOOKUP(VALUE(LEFT($G17&"",FIND("-",$G17&"-")-1)),$C$48:$C$53,$D$48:$D$53),"")) -> 200 | I17: 200 | J17: =IF($I17="","n/a",IF($H17=$I17,"ok","MISMATCH")) -> ok | K17: 37500 | L17: major overperformance vs seed (31 → 5-8) | N17: REJECT
B18: Team Falcons | C18: Numan Ch | D18: 28 | E18: 61 | F18: 270 | G18: 5-8 | H18: =IF($G18="","",IFERROR(LOOKUP(VALUE(LEFT($G18&"",FIND("-",$G18&"-")-1)),$C$48:$C$53,$D$48:$D$53),"")) -> 200 | I18: 200 | J18: =IF($I18="","n/a",IF($H18=$I18,"ok","MISMATCH")) -> ok | K18: 37500 | L18: major overperformance vs seed (28 → 5-8) | N18: Team Falcons
B19: SOOPers | C19: CBM | D19: 21 | E19: 27 | F19: 630 | G19: 9-12 | H19: =IF($G19="","",IFERROR(LOOKUP(VALUE(LEFT($G19&"",FIND("-",$G19&"-")-1)),$C$48:$C$53,$D$48:$D$53),"")) -> 0 | J19: =IF($I19="","n/a",IF($H19=$I19,"ok","MISMATCH")) -> n/a | K19: 27500 | N19: SOOPers
B20: Team Falcons | C20: Usama Abbasi | D20: 25 | E20: 48 | F20: 350 | G20: 9-12 | H20: =IF($G20="","",IFERROR(LOOKUP(VALUE(LEFT($G20&"",FIND("-",$G20&"-")-1)),$C$48:$C$53,$D$48:$D$53),"")) -> 0 | J20: =IF($I20="","n/a",IF($H20=$I20,"ok","MISMATCH")) -> n/a | K20: 27500 | L20: major overperformance vs seed (25 → 9-12) | N20: Team Falcons
B21: Team Falcons | C21: Farzeen | D21: 5 | E21: 5 | F21: 1340 | G21: 9-12 | H21: =IF($G21="","",IFERROR(LOOKUP(VALUE(LEFT($G21&"",FIND("-",$G21&"-")-1)),$C$48:$C$53,$D$48:$D$53),"")) -> 0 | J21: =IF($I21="","n/a",IF($H21=$I21,"ok","MISMATCH")) -> n/a | K21: 27500 | N21: Team Falcons
B22: YAMASA | C22: NOBI | D22: 12 | E22: 13 | F22: 950 | G22: 9-12 | H22: =IF($G22="","",IFERROR(LOOKUP(VALUE(LEFT($G22&"",FIND("-",$G22&"-")-1)),$C$48:$C$53,$D$48:$D$53),"")) -> 0 | J22: =IF($I22="","n/a",IF($H22=$I22,"ok","MISMATCH")) -> n/a | K22: 27500 | N22: YAMASA
B23: GodLike Esports | C23: KEISUKE | D23: 14 | E23: 15 | F23: 840 | G23: 13-16 | H23: =IF($G23="","",IFERROR(LOOKUP(VALUE(LEFT($G23&"",FIND("-",$G23&"-")-1)),$C$48:$C$53,$D$48:$D$53),"")) -> 0 | J23: =IF($I23="","n/a",IF($H23=$I23,"ok","MISMATCH")) -> n/a | K23: 20000 | N23: GodLike
B24: Al Qadsiah | C24: THE JON | D24: 30 | E24: 74 | F24: 240 | G24: 13-16 | H24: =IF($G24="","",IFERROR(LOOKUP(VALUE(LEFT($G24&"",FIND("-",$G24&"-")-1)),$C$48:$C$53,$D$48:$D$53),"")) -> 0 | J24: =IF($I24="","n/a",IF($H24=$I24,"ok","MISMATCH")) -> n/a | K24: 20000 | L24: major overperformance vs seed (30 → 13-16) | N24: Al Qadsiah
B25: The Vicious | C25: Qasim Meer | D25: 24 | E25: 31 | F25: 525 | G25: 13-16 | H25: =IF($G25="","",IFERROR(LOOKUP(VALUE(LEFT($G25&"",FIND("-",$G25&"-")-1)),$C$48:$C$53,$D$48:$D$53),"")) -> 0 | I25: 0 | J25: =IF($I25="","n/a",IF($H25=$I25,"ok","MISMATCH")) -> ok | K25: 20000 | N25: The Vicious
B26: Virtus.pro | C26: Mangja | D26: 8 | E26: 8 | F26: 1200 | G26: 13-16 | H26: =IF($G26="","",IFERROR(LOOKUP(VALUE(LEFT($G26&"",FIND("-",$G26&"-")-1)),$C$48:$C$53,$D$48:$D$53),"")) -> 0 | I26: 0 | J26: =IF($I26="","n/a",IF($H26=$I26,"ok","MISMATCH")) -> ok | K26: 20000 | N26: Virtus.pro
B27: Good 8 Squad | C27: MATSUBA | D27: 22 | E27: 28 | F27: 620 | G27: 17-24 | H27: =IF($G27="","",IFERROR(LOOKUP(VALUE(LEFT($G27&"",FIND("-",$G27&"-")-1)),$C$48:$C$53,$D$48:$D$53),"")) -> 0 | J27: =IF($I27="","n/a",IF($H27=$I27,"ok","MISMATCH")) -> n/a | K27: 12500 | N27: Good 8 Squad
B28: Twisted Minds | C28: Hafiz Tanveer | D28: 16 | E28: 18 | F28: 750 | G28: 17-24 | H28: =IF($G28="","",IFERROR(LOOKUP(VALUE(LEFT($G28&"",FIND("-",$G28&"-")-1)),$C$48:$C$53,$D$48:$D$53),"")) -> 0 | J28: =IF($I28="","n/a",IF($H28=$I28,"ok","MISMATCH")) -> n/a | K28: 12500 | N28: Twisted Minds
B29: ONIC | C29: REST | D29: 15 | E29: 17 | F29: 785 | G29: 17-24 | H29: =IF($G29="","",IFERROR(LOOKUP(VALUE(LEFT($G29&"",FIND("-",$G29&"-")-1)),$C$48:$C$53,$D$48:$D$53),"")) -> 0 | I29: 0 | J29: =IF($I29="","n/a",IF($H29=$I29,"ok","MISMATCH")) -> ok | K29: 12500 | N29: ONIC
B30: VARREL | C30: Rangchu | D30: 3 | E30: 3 | F30: 1510 | G30: 17-24 | H30: =IF($G30="","",IFERROR(LOOKUP(VALUE(LEFT($G30&"",FIND("-",$G30&"-")-1)),$C$48:$C$53,$D$48:$D$53),"")) -> 0 | I30: 0 | J30: =IF($I30="","n/a",IF($H30=$I30,"ok","MISMATCH")) -> ok | K30: 12500 | N30: VARREL
B31: Gen.G Esports | C31: Mulgold | D31: 6 | E31: 6 | F31: 1310 | G31: 17-24 | H31: =IF($G31="","",IFERROR(LOOKUP(VALUE(LEFT($G31&"",FIND("-",$G31&"-")-1)),$C$48:$C$53,$D$48:$D$53),"")) -> 0 | I31: 0 | J31: =IF($I31="","n/a",IF($H31=$I31,"ok","MISMATCH")) -> ok | K31: 12500 | N31: Gen.G Esports
B32: Team Falcons | C32: ATIF | D32: 1 | E32: 1 | F32: 1550 | G32: 17-24 | H32: =IF($G32="","",IFERROR(LOOKUP(VALUE(LEFT($G32&"",FIND("-",$G32&"-")-1)),$C$48:$C$53,$D$48:$D$53),"")) -> 0 | J32: =IF($I32="","n/a",IF($H32=$I32,"ok","MISMATCH")) -> n/a | K32: 12500 | L32: major underperformance vs seed (1 → 17-24) | N32: Team Falcons
B33: NASR eSports | C33: Tekken Master | D33: 32 | E33: 104 | F33: 195 | G33: 17-24 | H33: =IF($G33="","",IFERROR(LOOKUP(VALUE(LEFT($G33&"",FIND("-",$G33&"-")-1)),$C$48:$C$53,$D$48:$D$53),"")) -> 0 | J33: =IF($I33="","n/a",IF($H33=$I33,"ok","MISMATCH")) -> n/a | K33: 12500 | L33: major overperformance vs seed (32 → 17-24) | N33: NASR eSports
B34: VARREL | C34: AO | D34: 20 | E34: 26 | F34: 640 | G34: 17-24 | H34: =IF($G34="","",IFERROR(LOOKUP(VALUE(LEFT($G34&"",FIND("-",$G34&"-")-1)),$C$48:$C$53,$D$48:$D$53),"")) -> 0 | J34: =IF($I34="","n/a",IF($H34=$I34,"ok","MISMATCH")) -> n/a | K34: 12500 | N34: VARREL
B35: Zero Tenacity | C35: Breadman | D35: 29 | E35: 63 | F35: 265 | G35: 25-32 | H35: =IF($G35="","",IFERROR(LOOKUP(VALUE(LEFT($G35&"",FIND("-",$G35&"-")-1)),$C$48:$C$53,$D$48:$D$53),"")) -> 0 | J35: =IF($I35="","n/a",IF($H35=$I35,"ok","MISMATCH")) -> n/a | K35: 7500 | N35: Zero Tenacity
B36: Ninjas in Pyjamas | C36: Meo-IL | D36: 10 | E36: 10 | F36: 1060 | G36: 25-32 | H36: =IF($G36="","",IFERROR(LOOKUP(VALUE(LEFT($G36&"",FIND("-",$G36&"-")-1)),$C$48:$C$53,$D$48:$D$53),"")) -> 0 | I36: 0 | J36: =IF($I36="","n/a",IF($H36=$I36,"ok","MISMATCH")) -> ok | K36: 7500 | L36: major underperformance vs seed (10 → 25-32) | N36: Ninjas in Pyjamas
B37: FOX eSport | C37: Sin | D37: 18 | E37: 21 | F37: 690 | G37: 25-32 | H37: =IF($G37="","",IFERROR(LOOKUP(VALUE(LEFT($G37&"",FIND("-",$G37&"-")-1)),$C$48:$C$53,$D$48:$D$53),"")) -> 0 | J37: =IF($I37="","n/a",IF($H37=$I37,"ok","MISMATCH")) -> n/a | K37: 7500 | N37: FOX eSport
B38: DRX | C38: iKARi | D38: 11 | E38: 11 | F38: 1000 | G38: 25-32 | H38: =IF($G38="","",IFERROR(LOOKUP(VALUE(LEFT($G38&"",FIND("-",$G38&"-")-1)),$C$48:$C$53,$D$48:$D$53),"")) -> 0 | J38: =IF($I38="","n/a",IF($H38=$I38,"ok","MISMATCH")) -> n/a | K38: 7500 | N38: DRX
B39: Zero Tenacity | C39: qudans | D39: 23 | E39: 29 | F39: 560 | G39: 25-32 | H39: =IF($G39="","",IFERROR(LOOKUP(VALUE(LEFT($G39&"",FIND("-",$G39&"-")-1)),$C$48:$C$53,$D$48:$D$53),"")) -> 0 | J39: =IF($I39="","n/a",IF($H39=$I39,"ok","MISMATCH")) -> n/a | K39: 7500 | N39: Zero Tenacity
B40: (no club tag) | C40: AK | D40: 17 | E40: 20 | F40: 700 | G40: 25-32 | H40: =IF($G40="","",IFERROR(LOOKUP(VALUE(LEFT($G40&"",FIND("-",$G40&"-")-1)),$C$48:$C$53,$D$48:$D$53),"")) -> 0 | J40: =IF($I40="","n/a",IF($H40=$I40,"ok","MISMATCH")) -> n/a | K40: 7500 | N40: (no club tag)
B41: DRX | C41: KNEE | D41: 7 | E41: 7 | F41: 1270 | G41: 25-32 | H41: =IF($G41="","",IFERROR(LOOKUP(VALUE(LEFT($G41&"",FIND("-",$G41&"-")-1)),$C$48:$C$53,$D$48:$D$53),"")) -> 0 | J41: =IF($I41="","n/a",IF($H41=$I41,"ok","MISMATCH")) -> n/a | K41: 7500 | L41: major underperformance vs seed (7 → 25-32) | N41: DRX
B42: Synergy FGC | C42: NinjaKilla212 | D42: 26 | E42: 50 | F42: 330 | G42: 25-32 | H42: =IF($G42="","",IFERROR(LOOKUP(VALUE(LEFT($G42&"",FIND("-",$G42&"-")-1)),$C$48:$C$53,$D$48:$D$53),"")) -> 0 | J42: =IF($I42="","n/a",IF($H42=$I42,"ok","MISMATCH")) -> n/a | K42: 7500 | N42: Synergy FGC
B44: TOTAL POINTS AWARDED | H44: =SUM(H11:H42) -> 3350
B45: 3,350 club points — standard playoff curve. Prize money sums to the full $1,000,000.
B46: 2 · POINT SYSTEM
B47: From place | C47: Club points | D47: Band
C48: 1 | D48: 1000 | E48: 1st
C49: 2 | D49: 750 | E49: 2nd
C50: 3 | D50: 500 | E50: 3rd
C51: 4 | D51: 300 | E51: 4th
C52: 5 | D52: 200 | E52: 5th-8th
C53: 9 | D53: 0 | E53: 9th-32nd
B56: 3 · SEED SOURCE — TWT 2026 Global Points, and a serious warning
B57: The Tekken World Tour Global Points Standings rank 250 players with numeric season points, and EWC 2026 sits on the TWT circuit, so on paper this is a strong method A source — comparable in quality to VRS or the EPT leaderboard. IN PRACTICE IT PREDICTED ALMOST NOTHING AT THIS EVENT. Champion M. Zubair entered as TWT #52, seeded 27th of 32. The top of the circuit collapsed: TWT #1 ATIF finished 17th-24th, #3 Rangchu 17th-24th, #6 Mulgold 17th-24th, #7 Knee 25th-32nd, #10 Meo-IL 25th-32nd. Meanwhile Raef at TWT #81 reached 5th-8th and Numan Ch at #61 did the same. TWO READINGS, and the data cannot yet separate them. Either Tekken's TVI of 36 is far too low and this is a genuinely high-variance title, or TWT points measure something different from single-event LAN strength — they accumulate across a season of open tournaments, so they reward attendance volume as much as peak quality. The second reading is supported by the fact that the 2025 EWC champion Ulsan, who is a proven LAN performer, entered at TWT #9 and finished 5th-8th. DO NOT recalibrate the TVI from this single event — but flag Tekken as the title where seed quality most needs a second edition of evidence.
B65: Seed | C65: Player | D65: TWT rank | E65: Result | F65: Seed − result
B66: 1 | C66: ATIF | D66: 1 | E66: 17-24 | F66: -16
B67: 2 | C67: Arslan Ash | D67: 2 | E67: 4 | F67: -2
B68: 3 | C68: Rangchu | D68: 3 | E68: 17-24 | F68: -14
B69: 4 | C69: LowHigh | D69: 4 | E69: 2 | F69: 2
B70: 5 | C70: Farzeen | D70: 5 | E70: 9-12 | F70: -4
B71: 6 | C71: Mulgold | D71: 6 | E71: 17-24 | F71: -11
B72: 7 | C72: KNEE | D72: 7 | E72: 25-32 | F72: -18
B73: 8 | C73: Mangja | D73: 8 | E73: 13-16 | F73: -5
B74: 9 | C74: ULSAN | D74: 9 | E74: 5-8 | F74: 4
B75: 10 | C75: Meo-IL | D75: 10 | E75: 25-32 | F75: -15
B76: 11 | C76: iKARi | D76: 11 | E76: 25-32 | F76: -14
B77: 12 | C77: NOBI | D77: 13 | E77: 9-12 | F77: 3
... B97: 32 | C97: Tekken Master | D97: 104 | E97: 17-24 | F97: 15
B99: NOTE on unmatched clubs: Yagami (3rd) and AK (25th-32nd) carry no club tag on Liquipedia. Weibo Gaming shows 0 points in Tekken on the CC standings, which is consistent with AK being their entry, but this is inference — verify before relying on it.

Sheet Street Fighter 6
B2: Street Fighter 6 — EWC 2026
B3: HYBRID SEED. CPT 2026 points where they exist (13 of 32); a manually assigned Tier for the other 19. Both resolve to a mean and a sigma, so the engine treats them identically.
B5: FORMAT | D5: FIELD SIZE | F5: TVI | H5: SEED METHOD | J5: SEED SOURCE | L5: PLACEMENT GRANULARITY
B6: Bracket, 32 players | D6: 32 players | F6: 58 · Medium | H6: C + D hybrid | J6: CPT 2026 points / manual tier | L6: Bands (5-8, 9-12, 13-16, 17-24, 25-32)
B8: 1 · FIELD & RESULTS
B9: All 32 players. CPT-ranked players carry a numeric seed. For the 19 unranked, set Tier in the dropdown — base it on RECENT form (last 12-18 months), not career honours; see block 3 for why. Tier is greyed out for CPT-ranked players, whose seed comes from points.
B10: Club | C10: Player | D10: Seed | E10: CPT rank | F10: CPT points | G10: Tier (unranked only) | H10: Placement | I10: Points (auto) | J10: Official CC pts | K10: Δ check | L10: Prize (USD) | M10: Seed confidence | O10: Club (canonical)
B11: Team Falcons | C11: Craime | D11: 6 | E11: 9 | F11: 360 | G11: — | H11: 1 | I11: =IF($H11="","",IFERROR(LOOKUP(VALUE(LEFT($H11&"",FIND("-",$H11&"-")-1)),$C$48:$C$53,$D$48:$D$53),"")) -> 1000 | J11: 1000 | K11: =IF($J11="","n/a",IF($I11=$J11,"ok","MISMATCH")) -> ok | L11: 250000 | M11: A/C ranked | O11: Team Falcons
B12: SBI e-Sports | C12: Hibiki | E12: — | G12: Medium | H12: 2 | I12: =IF($H12="","",IFERROR(LOOKUP(VALUE(LEFT($H12&"",FIND("-",$H12&"-")-1)),$C$48:$C$53,$D$48:$D$53),"")) -> 750 | J12: 750 | K12: =IF($J12="","n/a",IF($I12=$J12,"ok","MISMATCH")) -> ok | L12: 130000 | M12: unranked — no CPT points | O12: SBI e-Sports
B13: REJECT | C13: Hinao | D13: 8 | E13: 12 | F13: 300 | G13: — | H13: 3 | I13: =IF($H13="","",IFERROR(LOOKUP(VALUE(LEFT($H13&"",FIND("-",$H13&"-")-1)),$C$48:$C$53,$D$48:$D$53),"")) -> 500 | J13: 500 | K13: =IF($J13="","n/a",IF($I13=$J13,"ok","MISMATCH")) -> ok | L13: 70000 | M13: A/C ranked | O13: REJECT
B14: ZETA DIVISION | C14: Yamaguchi | E14: — | G14: Medium | H14: 4 | I14: =IF($H14="","",IFERROR(LOOKUP(VALUE(LEFT($H14&"",FIND("-",$H14&"-")-1)),$C$48:$C$53,$D$48:$D$53),"")) -> 300 | J14: 300 | K14: =IF($J14="","n/a",IF($I14=$J14,"ok","MISMATCH")) -> ok | L14: 50000 | M14: unranked — no CPT points | O14: ZETA DIVISION
B15: ONIC | C15: Booce_Lee | D15: 2 | E15: 2 | F15: 620 | G15: — | H15: 5-8 | I15: =IF($H15="","",IFERROR(LOOKUP(VALUE(LEFT($H15&"",FIND("-",$H15&"-")-1)),$C$48:$C$53,$D$48:$D$53),"")) -> 200 | J15: 200 | K15: =IF($J15="","n/a",IF($I15=$J15,"ok","MISMATCH")) -> ok | L15: 37500 | M15: A/C ranked | O15: ONIC
B16: Weibo Gaming | C16: MenaRD | E16: — | G16: Medium | H16: 5-8 | I16: =IF($H16="","",IFERROR(LOOKUP(VALUE(LEFT($H16&"",FIND("-",$H16&"-")-1)),$C$48:$C$53,$D$48:$D$53),"")) -> 200 | J16: 200 | K16: =IF($J16="","n/a",IF($I16=$J16,"ok","MISMATCH")) -> ok | L16: 37500 | M16: unranked — no CPT points | O16: Weibo Gaming
B17: DRX | C17: Leshar | E17: — | G17: Medium | H17: 5-8 | I17: =IF($H17="","",IFERROR(LOOKUP(VALUE(LEFT($H17&"",FIND("-",$H17&"-")-1)),$C$48:$C$53,$D$48:$D$53),"")) -> 200 | J17: 200 | K17: =IF($J17="","n/a",IF($I17=$J17,"ok","MISMATCH")) -> ok | L17: 37500 | M17: unranked — no CPT points | O17: DRX
B18: Saishunkan Sol Kumamoto | C18: kobayan | D18: 7 | E18: 10 | F18: 360 | G18: — | H18: 5-8 | I18: =IF($H18="","",IFERROR(LOOKUP(VALUE(LEFT($H18&"",FIND("-",$H18&"-")-1)),$C$48:$C$53,$D$48:$D$53),"")) -> 200 | J18: 200 | K18: =IF($J18="","n/a",IF($I18=$J18,"ok","MISMATCH")) -> ok | L18: 37500 | M18: A/C ranked | O18: Saishunkan Sol Kumamoto
B19: FAV gaming | C19: moke | E19: — | G19: Medium | H19: 9-12 | I19: =IF($H19="","",IFERROR(LOOKUP(VALUE(LEFT($H19&"",FIND("-",$H19&"-")-1)),$C$48:$C$53,$D$48:$D$53),"")) -> 0 | K19: =IF($J19="","n/a",IF($I19=$J19,"ok","MISMATCH")) -> n/a | L19: 27500 | M19: unranked — no CPT points | O19: FAV gaming
B20: Crazy Raccoon | C20: Dual Kevin | D20: 11 | E20: 18 | F20: 200 | G20: — | H20: 9-12 | I20: =IF($H20="","",IFERROR(LOOKUP(VALUE(LEFT($H20&"",FIND("-",$H20&"-")-1)),$C$48:$C$53,$D$48:$D$53),"")) -> 0 | J20: 0 | K20: =IF($J20="","n/a",IF($I20=$J20,"ok","MISMATCH")) -> ok | L20: 27500 | M20: A/C ranked | O20: Crazy Raccoon
B21: ZETA DIVISION | C21: Higuchi | D21: 5 | E21: 7 | F21: 430 | G21: — | H21: 9-12 | I21: =IF($H21="","",IFERROR(LOOKUP(VALUE(LEFT($H21&"",FIND("-",$H21&"-")-1)),$C$48:$C$53,$D$48:$D$53),"")) -> 0 | K21: =IF($J21="","n/a",IF($I21=$J21,"ok","MISMATCH")) -> n/a | L21: 27500 | M21: A/C ranked | O21: ZETA DIVISION
B22: Team Falcons | C22: Micky | D22: 1 | E22: 1 | F22: 650 | G22: — | H22: 9-12 | I22: =IF($H22="","",IFERROR(LOOKUP(VALUE(LEFT($H22&"",FIND("-",$H22&"-")-1)),$C$48:$C$53,$D$48:$D$53),"")) -> 0 | K22: =IF($J22="","n/a",IF($I22=$J22,"ok","MISMATCH")) -> n/a | L22: 27500 | M22: A/C ranked | O22: Team Falcons
B23: VARREL | C23: Tokido | D23: 12 | E23: 23 | F23: 170 | G23: — | H23: 13-16 | I23: =IF($H23="","",IFERROR(LOOKUP(VALUE(LEFT($H23&"",FIND("-",$H23&"-")-1)),$C$48:$C$53,$D$48:$D$53),"")) -> 0 | J23: 0 | K23: =IF($J23="","n/a",IF($I23=$J23,"ok","MISMATCH")) -> ok | L23: 20000 | M23: A/C ranked | O23: VARREL
B24: Team Heretics | C24: Lexx | E24: — | G24: Medium | H24: 13-16 | I24: =IF($H24="","",IFERROR(LOOKUP(VALUE(LEFT($H24&"",FIND("-",$H24&"-")-1)),$C$48:$C$53,$D$48:$D$53),"")) -> 0 | J24: 0 | K24: =IF($J24="","n/a",IF($I24=$J24,"ok","MISMATCH")) -> ok | L24: 20000 | M24: unranked — no CPT points | O24: Team Heretics
B25: (no club tag) | C25: Nephew | E25: — | G25: Medium | H25: 13-16 | I25: =IF($H25="","",IFERROR(LOOKUP(VALUE(LEFT($H25&"",FIND("-",$H25&"-")-1)),$C$48:$C$53,$D$48:$D$53),"")) -> 0 | K25: =IF($J25="","n/a",IF($I25=$J25,"ok","MISMATCH")) -> n/a | L25: 20000 | M25: unranked — no CPT points | O25: (no club tag)
B26: Good 8 Squad | C26: gachikun | D26: 10 | E26: 15 | F26: 220 | G26: — | H26: 13-16 | I26: =IF($H26="","",IFERROR(LOOKUP(VALUE(LEFT($H26&"",FIND("-",$H26&"-")-1)),$C$48:$C$53,$D$48:$D$53),"")) -> 0 | K26: =IF($J26="","n/a",IF($I26=$J26,"ok","MISMATCH")) -> n/a | L26: 20000 | M26: A/C ranked | O26: Good 8 Squad
B27: AG.AL International | C27: Kilzyou | D27: 4 | E27: 4 | F27: 550 | G27: — | H27: 17-24 | I27: =IF($H27="","",IFERROR(LOOKUP(VALUE(LEFT($H27&"",FIND("-",$H27&"-")-1)),$C$48:$C$53,$D$48:$D$53),"")) -> 0 | J27: 0 | K27: =IF($J27="","n/a",IF($I27=$J27,"ok","MISMATCH")) -> ok | L27: 12500 | M27: A/C ranked | O27: AG.AL International
B28: REJECT | C28: Daigo | E28: — | G28: Medium | H28: 17-24 | I28: =IF($H28="","",IFERROR(LOOKUP(VALUE(LEFT($H28&"",FIND("-",$H28&"-")-1)),$C$48:$C$53,$D$48:$D$53),"")) -> 0 | K28: =IF($J28="","n/a",IF($I28=$J28,"ok","MISMATCH")) -> n/a | L28: 12500 | M28: unranked — no CPT points | O28: REJECT
B29: Red Dunes Esports | C29: AngryBird | E29: — | G29: Medium | H29: 17-24 | I29: =IF($H29="","",IFERROR(LOOKUP(VALUE(LEFT($H29&"",FIND("-",$H29&"-")-1)),$C$48:$C$53,$D$48:$D$53),"")) -> 0 | K29: =IF($J29="","n/a",IF($I29=$J29,"ok","MISMATCH")) -> n/a | L29: 12500 | M29: unranked — no CPT points | O29: Red Dunes Esports
B30: Good 8 Squad | C30: Sahara | E30: — | G30: Medium | H30: 17-24 | I30: =IF($H30="","",IFERROR(LOOKUP(VALUE(LEFT($H30&"",FIND("-",$H30&"-")-1)),$C$48:$C$53,$D$48:$D$53),"")) -> 0 | K30: =IF($J30="","n/a",IF($I30=$J30,"ok","MISMATCH")) -> n/a | L30: 12500 | M30: unranked — no CPT points | O30: Good 8 Squad
B31: RIDDLE | C31: Shigematsu | E31: — | G31: Medium | H31: 17-24 | I31: =IF($H31="","",IFERROR(LOOKUP(VALUE(LEFT($H31&"",FIND("-",$H31&"-")-1)),$C$48:$C$53,$D$48:$D$53),"")) -> 0 | K31: =IF($J31="","n/a",IF($I31=$J31,"ok","MISMATCH")) -> n/a | L31: 12500 | M31: unranked — no CPT points | O31: RIDDLE
B32: GodLike Esports | C32: Caba | E32: — | G32: Medium | H32: 17-24 | I32: =IF($H32="","",IFERROR(LOOKUP(VALUE(LEFT($H32&"",FIND("-",$H32&"-")-1)),$C$48:$C$53,$D$48:$D$53),"")) -> 0 | K32: =IF($J32="","n/a",IF($I32=$J32,"ok","MISMATCH")) -> n/a | L32: 12500 | M32: unranked — no CPT points | O32: GodLike
B33: Ninjas in Pyjamas | C33: Phenom | E33: — | G33: Medium | H33: 17-24 | I33: =IF($H33="","",IFERROR(LOOKUP(VALUE(LEFT($H33&"",FIND("-",$H33&"-")-1)),$C$48:$C$53,$D$48:$D$53),"")) -> 0 | J33: 0 | K33: =IF($J33="","n/a",IF($I33=$J33,"ok","MISMATCH")) -> ok | L33: 12500 | M33: unranked — no CPT points | O33: Ninjas in Pyjamas
B34: Team Nemesis | C34: Xian | E34: — | G34: Medium | H34: 17-24 | I34: =IF($H34="","",IFERROR(LOOKUP(VALUE(LEFT($H34&"",FIND("-",$H34&"-")-1)),$C$48:$C$53,$D$48:$D$53),"")) -> 0 | J34: 0 | K34: =IF($J34="","n/a",IF($I34=$J34,"ok","MISMATCH")) -> ok | L34: 12500 | M34: unranked — no CPT points | O34: Team Nemesis
B35: DetonatioN FocusMe | C35: Itabashi Zangief | E35: — | G35: Medium | H35: 25-32 | I35: =IF($H35="","",IFERROR(LOOKUP(VALUE(LEFT($H35&"",FIND("-",$H35&"-")-1)),$C$48:$C$53,$D$48:$D$53),"")) -> 0 | K35: =IF($J35="","n/a",IF($I35=$J35,"ok","MISMATCH")) -> n/a | L35: 7500 | M35: unranked — no CPT points | O35: DetonatioN FocusMe
B36: Red Dunes Esports | C36: Big Bird | E36: — | G36: Medium | H36: 25-32 | I36: =IF($H36="","",IFERROR(LOOKUP(VALUE(LEFT($H36&"",FIND("-",$H36&"-")-1)),$C$48:$C$53,$D$48:$D$53),"")) -> 0 | K36: =IF($J36="","n/a",IF($I36=$J36,"ok","MISMATCH")) -> n/a | L36: 7500 | M36: unranked — no CPT points | O36: Red Dunes Esports
B37: FlyQuest | C37: Punk | D37: 3 | E37: 3 | F37: 600 | G37: — | H37: 25-32 | I37: =IF($H37="","",IFERROR(LOOKUP(VALUE(LEFT($H37&"",FIND("-",$H37&"-")-1)),$C$48:$C$53,$D$48:$D$53),"")) -> 0 | K37: =IF($J37="","n/a",IF($I37=$J37,"ok","MISMATCH")) -> n/a | L37: 7500 | M37: A/C ranked | O37: FlyQuest
B38: Leviatán | C38: Chris Tatarian | E38: — | G38: Medium | H38: 25-32 | I38: =IF($H38="","",IFERROR(LOOKUP(VALUE(LEFT($H38&"",FIND("-",$H38&"-")-1)),$C$48:$C$53,$D$48:$D$53),"")) -> 0 | J38: 0 | K38: =IF($J38="","n/a",IF($I38=$J38,"ok","MISMATCH")) -> ok | L38: 7500 | M38: unranked — no CPT points | O38: Leviatán
B39: REJECT | C39: Fuudo | D39: 13 | E39: 26 | F39: 150 | G39: — | H39: 25-32 | I39: =IF($H39="","",IFERROR(LOOKUP(VALUE(LEFT($H39&"",FIND("-",$H39&"-")-1)),$C$48:$C$53,$D$48:$D$53),"")) -> 0 | K39: =IF($J39="","n/a",IF($I39=$J39,"ok","MISMATCH")) -> n/a | L39: 7500 | M39: A/C ranked | O39: REJECT
B40: Ninjas in Pyjamas | C40: Juicyjoe | E40: — | G40: Medium | H40: 25-32 | I40: =IF($H40="","",IFERROR(LOOKUP(VALUE(LEFT($H40&"",FIND("-",$H40&"-")-1)),$C$48:$C$53,$D$48:$D$53),"")) -> 0 | K40: =IF($J40="","n/a",IF($I40=$J40,"ok","MISMATCH")) -> n/a | L40: 7500 | M40: unranked — no CPT points | O40: Ninjas in Pyjamas
B41: 2Game Esports | C41: Blaz | D41: 9 | E41: 14 | F41: 250 | G41: — | H41: 25-32 | I41: =IF($H41="","",IFERROR(LOOKUP(VALUE(LEFT($H41&"",FIND("-",$H41&"-")-1)),$C$48:$C$53,$D$48:$D$53),"")) -> 0 | K41: =IF($J41="","n/a",IF($I41=$J41,"ok","MISMATCH")) -> n/a | L41: 7500 | M41: A/C ranked | O41: 2Game Esports
B42: Team Falcons | C42: Xiaohai | E42: — | G42: Medium | H42: 25-32 | I42: =IF($H42="","",IFERROR(LOOKUP(VALUE(LEFT($H42&"",FIND("-",$H42&"-")-1)),$C$48:$C$53,$D$48:$D$53),"")) -> 0 | K42: =IF($J42="","n/a",IF($I42=$J42,"ok","MISMATCH")) -> n/a | L42: 7500 | M42: unranked — no CPT points | O42: Team Falcons
B44: TOTAL POINTS AWARDED | I44: =SUM(I11:I42) -> 3350
B45: 3,350 club points — standard playoff curve. Prize money sums to the full $1,000,000.
B46: 2 · POINT SYSTEM
B47: From place | C47: Club points | D47: Band
C48: 1 | D48: 1000 | E48: 1st
C49: 2 | D49: 750 | E49: 2nd
C50: 3 | D50: 500 | E50: 3rd
C51: 4 | D51: 300 | E51: 4th
C52: 5 | D52: 200 | E52: 5th-8th
C53: 9 | D53: 0 | E53: 9th-32nd
B56: 3 · WHY HYBRID — CPT POINTS PLUS A MANUAL TIER
B57: The Capcom Pro Tour 2026 Global Leaderboard covers only 13 of the 32 entrants — the rest arrived via auto-qualification, the Last Chance Qualifier, or regional routes that do not feed the global table. Leaving all 19 as one flat bucket is demonstrably wrong: FOUR of the eight top-eight finishers were unranked (Hibiki 2nd, Yamaguchi 4th, MenaRD 5th-8th, Leshar 5th-8th). Hence the Tier column. BASE THE TIER ON RECENT FORM, NOT CAREER HONOURS. This is the important instruction, and 2026 is the evidence. A pedigree-based tier would have promoted the decorated veterans - and every one of them collapsed: Xiaohai 25th-32nd, Itabashi Zangief 25th-32nd, Daigo 17th-24th, Xian 17th-24th, Phenom 17th-24th. Meanwhile the two unranked players who reached the podium places, Hibiki and Yamaguchi, are recent-era competitors rather than crossover legends. MenaRD is the one big name who delivered. Use Capcom Cup 11/12 finishes, EWC 2025 SF6 and Evo 2025/26 as the basis; a name that has not placed deep in the last 12-18 months belongs in Medium or Low regardless of its trophy cabinet. REJECTED ALTERNATIVE: the Capcom Cup auto-qualified list looks predictive (five of seven made top 8) but is CONTAMINATED — winning EWC itself grants a Capcom Cup slot, so it is partly an output of this event. Using it would leak the result into the seed. ALSO NOTE: CPT was weak even where it had coverage — #1 Micky finished 9th-12th, #3 Punk 25th-32nd, #4 Kilzyou 17th-24th, and champion Craime entered at #9. Across Tekken, SF6, Fatal Fury and Fortnite Reload the same pattern holds: season-long circuit points and career reputation both underperform, while recent format-specific form does not.
B66: Tier | C66: Players (auto) | D66: Band from | E66: Band to | F66: Mean (mu) | G66: Within sigma
B67: High | C67: =COUNTIF($G$11:$G$42,$B67) -> 0 | D67: =14 -> 14 | E67: =D67+C67-1 -> 13 | F67: =IF(C67=0,"",(D67+E67)/2) | G67: =IF(C67=0,"",(E67-D67+1)/SQRT(12))
B68: Medium | C68: =COUNTIF($G$11:$G$42,$B68) -> 19 | D68: =E67+1 -> 14 | E68: =D68+C68-1 -> 32 | F68: =IF(C68=0,"",(D68+E68)/2) -> 23 | G68: =IF(C68=0,"",(E68-D68+1)/SQRT(12)) -> 5.4848276
B69: Low | C69: =COUNTIF($G$11:$G$42,$B69) -> 0 | D69: =E68+1 -> 33 | E69: =D69+C69-1 -> 32 | F69: =IF(C69=0,"",(D69+E69)/2) | G69: =IF(C69=0,"",(E69-D69+1)/SQRT(12))
B71: Tier bands start at position 14 because the 13 CPT-ranked players occupy seeds 1-13. Bands re-tile automatically as you reassign tiers. Defaults are all Medium — change them before simulating.

Sheet Fatal Fury CotW
B2: Fatal Fury: City of the Wolves — EWC 2026
B3: Seed method E — no credible pre-event ranking exists. The reasoning is in block 3; this is a deliberate choice, not a gap in the research.
B5: FORMAT | D5: FIELD SIZE | F5: TVI | H5: SEED METHOD | J5: SEED SOURCE | L5: PLACEMENT GRANULARITY
B6: Bracket, 32 players | D6: 32 players | F6: 45 · Medium | H6: E — no credible seed | J6: n/a | L6: Bands (5-8, 9-12, 13-16, 17-24, 25-32)
B8: 1 · FIELD & RESULTS
B9: All 32 players. Seed column intentionally empty — every player shares the same mean strength under method E.
B10: Club | C10: Player | D10: Seed | E10: Placement | F10: Points (auto) | G10: Official CC pts | H10: Δ check | I10: Prize (USD) | J10: Notes | L10: Club (canonical)
B11: Natus Vincere | C11: DarkAngel | E11: 1 | F11: =IF($E11="","",IFERROR(LOOKUP(VALUE(LEFT($E11&"",FIND("-",$E11&"-")-1)),$C$48:$C$53,$D$48:$D$53),"")) -> 1000 | G11: 1000 | H11: =IF($G11="","n/a",IF($F11=$G11,"ok","MISMATCH")) -> ok | I11: 250000 | L11: Natus Vincere
B12: Virtus.pro | C12: mi2ha4 | E12: 2 | F12: =IF($E12="","",IFERROR(LOOKUP(VALUE(LEFT($E12&"",FIND("-",$E12&"-")-1)),$C$48:$C$53,$D$48:$D$53),"")) -> 750 | G12: 750 | H12: =IF($G12="","n/a",IF($F12=$G12,"ok","MISMATCH")) -> ok | I12: 130000 | L12: Virtus.pro
B13: Saishunkan Sol Kumamoto | C13: Nemo | E13: 3 | F13: =IF($E13="","",IFERROR(LOOKUP(VALUE(LEFT($E13&"",FIND("-",$E13&"-")-1)),$C$48:$C$53,$D$48:$D$53),"")) -> 500 | G13: 500 | H13: =IF($G13="","n/a",IF($F13=$G13,"ok","MISMATCH")) -> ok | I13: 70000 | L13: Saishunkan Sol Kumamoto
B14: REJECT | C14: Laggia | E14: 4 | F14: =IF($E14="","",IFERROR(LOOKUP(VALUE(LEFT($E14&"",FIND("-",$E14&"-")-1)),$C$48:$C$53,$D$48:$D$53),"")) -> 300 | G14: 300 | H14: =IF($G14="","n/a",IF($F14=$G14,"ok","MISMATCH")) -> ok | I14: 50000 | L14: REJECT
B15: T1 | C15: ZJZ | E15: 5-8 | F15: =IF($E15="","",IFERROR(LOOKUP(VALUE(LEFT($E15&"",FIND("-",$E15&"-")-1)),$C$48:$C$53,$D$48:$D$53),"")) -> 200 | G15: 200 | H15: =IF($G15="","n/a",IF($F15=$G15,"ok","MISMATCH")) -> ok | I15: 37500 | L15: T1
B16: Weibo Gaming | C16: NaiWang | E16: 5-8 | F16: =IF($E16="","",IFERROR(LOOKUP(VALUE(LEFT($E16&"",FIND("-",$E16&"-")-1)),$C$48:$C$53,$D$48:$D$53),"")) -> 200 | G16: 200 | H16: =IF($G16="","n/a",IF($F16=$G16,"ok","MISMATCH")) -> ok | I16: 37500 | L16: Weibo Gaming
B17: Elite Esports | C17: Reynald | E17: 5-8 | F17: =IF($E17="","",IFERROR(LOOKUP(VALUE(LEFT($E17&"",FIND("-",$E17&"-")-1)),$C$48:$C$53,$D$48:$D$53),"")) -> 200 | G17: 200 | H17: =IF($G17="","n/a",IF($F17=$G17,"ok","MISMATCH")) -> ok | I17: 37500 | L17: Elite Esports
B18: Team Vitality | C18: K-TOP | E18: 5-8 | F18: =IF($E18="","",IFERROR(LOOKUP(VALUE(LEFT($E18&"",FIND("-",$E18&"-")-1)),$C$48:$C$53,$D$48:$D$53),"")) -> 200 | G18: 200 | H18: =IF($G18="","n/a",IF($F18=$G18,"ok","MISMATCH")) -> ok | I18: 37500 | L18: Team Vitality
B19: Team Falcons | C19: Kindevu | E19: 9-12 | F19: =IF($E19="","",IFERROR(LOOKUP(VALUE(LEFT($E19&"",FIND("-",$E19&"-")-1)),$C$48:$C$53,$D$48:$D$53),"")) -> 0 | G19: 0 | H19: =IF($G19="","n/a",IF($F19=$G19,"ok","MISMATCH")) -> ok | I19: 27500 | L19: Team Falcons
B20: GodLike Esports | C20: SCORE | E20: 9-12 | F20: =IF($E20="","",IFERROR(LOOKUP(VALUE(LEFT($E20&"",FIND("-",$E20&"-")-1)),$C$48:$C$53,$D$48:$D$53),"")) -> 0 | H20: =IF($G20="","n/a",IF($F20=$G20,"ok","MISMATCH")) -> n/a | I20: 27500 | L20: GodLike
B21: Team Falcons | C21: SHADOW X | E21: 9-12 | F21: =IF($E21="","",IFERROR(LOOKUP(VALUE(LEFT($E21&"",FIND("-",$E21&"-")-1)),$C$48:$C$53,$D$48:$D$53),"")) -> 0 | H21: =IF($G21="","n/a",IF($F21=$G21,"ok","MISMATCH")) -> n/a | I21: 27500 | L21: Team Falcons
B22: AG.AL International | C22: Vxbao | E22: 9-12 | F22: =IF($E22="","",IFERROR(LOOKUP(VALUE(LEFT($E22&"",FIND("-",$E22&"-")-1)),$C$48:$C$53,$D$48:$D$53),"")) -> 0 | G22: 0 | H22: =IF($G22="","n/a",IF($F22=$G22,"ok","MISMATCH")) -> ok | I22: 27500 | L22: AG.AL International
B23: Weibo Gaming | C23: POONGKO | E23: 13-16 | F23: =IF($E23="","",IFERROR(LOOKUP(VALUE(LEFT($E23&"",FIND("-",$E23&"-")-1)),$C$48:$C$53,$D$48:$D$53),"")) -> 0 | H23: =IF($G23="","n/a",IF($F23=$G23,"ok","MISMATCH")) -> n/a | I23: 20000 | L23: Weibo Gaming
B24: DetonatioN FocusMe | C24: GO1 | E24: 13-16 | F24: =IF($E24="","",IFERROR(LOOKUP(VALUE(LEFT($E24&"",FIND("-",$E24&"-")-1)),$C$48:$C$53,$D$48:$D$53),"")) -> 0 | H24: =IF($G24="","n/a",IF($F24=$G24,"ok","MISMATCH")) -> n/a | I24: 20000 | L24: DetonatioN FocusMe
B25: Team Vitality | C25: Fenritti | E25: 13-16 | F25: =IF($E25="","",IFERROR(LOOKUP(VALUE(LEFT($E25&"",FIND("-",$E25&"-")-1)),$C$48:$C$53,$D$48:$D$53),"")) -> 0 | H25: =IF($G25="","n/a",IF($F25=$G25,"ok","MISMATCH")) -> n/a | I25: 20000 | L25: Team Vitality
B26: Yesports | C26: RB | E26: 13-16 | F26: =IF($E26="","",IFERROR(LOOKUP(VALUE(LEFT($E26&"",FIND("-",$E26&"-")-1)),$C$48:$C$53,$D$48:$D$53),"")) -> 0 | H26: =IF($G26="","n/a",IF($F26=$G26,"ok","MISMATCH")) -> n/a | I26: 20000 | L26: Yesports
B27: Team Falcons | C27: Xiaohai | E27: 17-24 | F27: =IF($E27="","",IFERROR(LOOKUP(VALUE(LEFT($E27&"",FIND("-",$E27&"-")-1)),$C$48:$C$53,$D$48:$D$53),"")) -> 0 | H27: =IF($G27="","n/a",IF($F27=$G27,"ok","MISMATCH")) -> n/a | I27: 12500 | L27: Team Falcons
B28: Team Vitality | C28: H-DOPE | E28: 17-24 | F28: =IF($E28="","",IFERROR(LOOKUP(VALUE(LEFT($E28&"",FIND("-",$E28&"-")-1)),$C$48:$C$53,$D$48:$D$53),"")) -> 0 | H28: =IF($G28="","n/a",IF($F28=$G28,"ok","MISMATCH")) -> n/a | I28: 12500 | L28: Team Vitality
B29: (no club tag) | C29: abao | E29: 17-24 | F29: =IF($E29="","",IFERROR(LOOKUP(VALUE(LEFT($E29&"",FIND("-",$E29&"-")-1)),$C$48:$C$53,$D$48:$D$53),"")) -> 0 | H29: =IF($G29="","n/a",IF($F29=$G29,"ok","MISMATCH")) -> n/a | I29: 12500 | L29: (no club tag)
B30: Clan Del Mal | C30: Neku | E30: 17-24 | F30: =IF($E30="","",IFERROR(LOOKUP(VALUE(LEFT($E30&"",FIND("-",$E30&"-")-1)),$C$48:$C$53,$D$48:$D$53),"")) -> 0 | H30: =IF($G30="","n/a",IF($F30=$G30,"ok","MISMATCH")) -> n/a | I30: 12500 | L30: Clan Del Mal
B31: (no club tag) | C31: Pida | E31: 17-24 | F31: =IF($E31="","",IFERROR(LOOKUP(VALUE(LEFT($E31&"",FIND("-",$E31&"-")-1)),$C$48:$C$53,$D$48:$D$53),"")) -> 0 | H31: =IF($G31="","n/a",IF($F31=$G31,"ok","MISMATCH")) -> n/a | I31: 12500 | L31: (no club tag)
B32: Team Falcons | C32: mok | E32: 17-24 | F32: =IF($E32="","",IFERROR(LOOKUP(VALUE(LEFT($E32&"",FIND("-",$E32&"-")-1)),$C$48:$C$53,$D$48:$D$53),"")) -> 0 | H32: =IF($G32="","n/a",IF($F32=$G32,"ok","MISMATCH")) -> n/a | I32: 12500 | L32: Team Falcons
B33: S Factor | C33: Gummy | E33: 17-24 | F33: =IF($E33="","",IFERROR(LOOKUP(VALUE(LEFT($E33&"",FIND("-",$E33&"-")-1)),$C$48:$C$53,$D$48:$D$53),"")) -> 0 | H33: =IF($G33="","n/a",IF($F33=$G33,"ok","MISMATCH")) -> n/a | I33: 12500 | L33: S Factor
B34: (no club tag) | C34: Senaru | E34: 17-24 | F34: =IF($E34="","",IFERROR(LOOKUP(VALUE(LEFT($E34&"",FIND("-",$E34&"-")-1)),$C$48:$C$53,$D$48:$D$53),"")) -> 0 | H34: =IF($G34="","n/a",IF($F34=$G34,"ok","MISMATCH")) -> n/a | I34: 12500 | L34: (no club tag)
B35: Weibo Gaming | C35: XiaoCai | E35: 25-32 | F35: =IF($E35="","",IFERROR(LOOKUP(VALUE(LEFT($E35&"",FIND("-",$E35&"-")-1)),$C$48:$C$53,$D$48:$D$53),"")) -> 0 | H35: =IF($G35="","n/a",IF($F35=$G35,"ok","MISMATCH")) -> n/a | I35: 7500 | L35: Weibo Gaming
B36: Gen.G Esports | C36: Dany "El Maza" | E36: 25-32 | F36: =IF($E36="","",IFERROR(LOOKUP(VALUE(LEFT($E36&"",FIND("-",$E36&"-")-1)),$C$48:$C$53,$D$48:$D$53),"")) -> 0 | G36: 0 | H36: =IF($G36="","n/a",IF($F36=$G36,"ok","MISMATCH")) -> ok | I36: 7500 | L36: Gen.G Esports
B37: Titan Esports Club | C37: Lancer | E37: 25-32 | F37: =IF($E37="","",IFERROR(LOOKUP(VALUE(LEFT($E37&"",FIND("-",$E37&"-")-1)),$C$48:$C$53,$D$48:$D$53),"")) -> 0 | G37: 0 | H37: =IF($G37="","n/a",IF($F37=$G37,"ok","MISMATCH")) -> ok | I37: 7500 | L37: Titan Esports Club
B38: AG.AL International | C38: Basher | E38: 25-32 | F38: =IF($E38="","",IFERROR(LOOKUP(VALUE(LEFT($E38&"",FIND("-",$E38&"-")-1)),$C$48:$C$53,$D$48:$D$53),"")) -> 0 | H38: =IF($G38="","n/a",IF($F38=$G38,"ok","MISMATCH")) -> n/a | I38: 7500 | L38: AG.AL International
B39: Ninjas in Pyjamas | C39: KojiKOG | E39: 25-32 | F39: =IF($E39="","",IFERROR(LOOKUP(VALUE(LEFT($E39&"",FIND("-",$E39&"-")-1)),$C$48:$C$53,$D$48:$D$53),"")) -> 0 | G39: 0 | H39: =IF($G39="","n/a",IF($F39=$G39,"ok","MISMATCH")) -> ok | I39: 7500 | L39: Ninjas in Pyjamas
B40: Team Falcons | C40: AbuOmar | E40: 25-32 | F40: =IF($E40="","",IFERROR(LOOKUP(VALUE(LEFT($E40&"",FIND("-",$E40&"-")-1)),$C$48:$C$53,$D$48:$D$53),"")) -> 0 | H40: =IF($G40="","n/a",IF($F40=$G40,"ok","MISMATCH")) -> n/a | I40: 7500 | L40: Team Falcons
B41: Titan Esports Club | C41: TheGio | E41: 25-32 | F41: =IF($E41="","",IFERROR(LOOKUP(VALUE(LEFT($E41&"",FIND("-",$E41&"-")-1)),$C$48:$C$53,$D$48:$D$53),"")) -> 0 | H41: =IF($G41="","n/a",IF($F41=$G41,"ok","MISMATCH")) -> n/a | I41: 7500 | L41: Titan Esports Club
B42: ONIC | C42: NYChrisG | E42: 25-32 | F42: =IF($E42="","",IFERROR(LOOKUP(VALUE(LEFT($E42&"",FIND("-",$E42&"-")-1)),$C$48:$C$53,$D$48:$D$53),"")) -> 0 | G42: 0 | H42: =IF($G42="","n/a",IF($F42=$G42,"ok","MISMATCH")) -> ok | I42: 7500 | L42: ONIC
B44: TOTAL POINTS AWARDED | F44: =SUM(F11:F42) -> 3350
B45: 3,350 club points — standard playoff curve. Prize money sums to the full $1,000,000.
B46: 2 · POINT SYSTEM
B47: From place | C47: Club points | D47: Band
C48: 1 | D48: 1000 | E48: 1st
C49: 2 | D49: 750 | E49: 2nd
C50: 3 | D50: 500 | E50: 3rd
C51: 4 | D51: 300 | E51: 4th
C52: 5 | D52: 200 | E52: 5th-8th
C53: 9 | D53: 0 | E53: 9th-32nd
B56: 3 · WHY METHOD E
B57: Fatal Fury: City of the Wolves launched in 2025 and EWC 2026 is only its second appearance. There is no season-long ranking equivalent to the Tekken World Tour or Capcom Pro Tour tables: the SNK World Championship Finals is where this event QUALIFIES PLAYERS TO, not a ladder they arrive with. Liquipedia carries no global points standing for the title. So there is genuinely nothing to seed from — declaring that is more useful than constructing a proxy from reputation. The temptation would be to seed on FGC pedigree, since several entrants are decorated in other games — Xiaohai, GO1, Nemo, Poongko all have major titles elsewhere. The 2026 result argues against exactly that: GO1 finished 13th-16th, Xiaohai 17th-24th, Poongko 13th-16th, while the winner DarkAngel and runner-up mi2ha4 are CotW specialists rather than crossover names. This mirrors the Fortnite Reload lesson — in a young title, general reputation is a poor guide, and format-specific form is what matters. WHEN TO REVISIT: once SNK publishes a season-long points table, or after a second or third edition provides seed-versus-outcome data of its own, this should be upgraded to method C or D. Until then every player shares one mean and outcomes come entirely from the title sigma.

Sheet TFT
B2: Teamfight Tactics — EWC 2026
B3: Squads format, 4 players per club. Method D applied: cohorts are assigned by rule — High for Chinese and South Korean clubs, Medium for all others. The rule and its evidence are in block 3.
B5: FORMAT | D5: FIELD SIZE | F5: TVI | H5: SEED METHOD | J5: SEED SOURCE | L5: PLACEMENT GRANULARITY
B6: GSL groups → single-elim | D6: 16 teams | F6: 65 · High | H6: D — cohort by region | J6: Rule: CN + KR = High, else Medium | L6: Bands (5-8, 9-12, 13-16)
B8: 1 · FIELD & RESULTS
B9: All 16 teams. Cohort is applied automatically from Region by the rule above — change a Region and set the Cohort to match, or override the Cohort directly. Region is inferred from club origin; the event page does not record which qualifier each club entered through.
B10: Club | C10: Region | D10: Cohort | E10: Placement | F10: Points (auto) | G10: CC eligible? | H10: Eligible pts | I10: Official CC pts | J10: Δ check | K10: Prize (USD) | L10: Notes | N10: Club (canonical)
B11: Team Vision | C11: CN | D11: High | E11: 1 | F11: =IF($E11="","",IFERROR(LOOKUP(VALUE(LEFT($E11&"",FIND("-",$E11&"-")-1)),$C$34:$C$39,$D$34:$D$39),"")) -> 1000 | G11: Yes | H11: =IF($G11="VOID",0,$F11) -> 1000 | I11: 1000 | J11: =IF($I11="","n/a",IF($H11=$I11,"ok","MISMATCH")) -> ok | K11: 150000 | N11: Team Vision
B12: Aurora Gaming | C12: CN | D12: High | E12: 2 | F12: =IF($E12="","",IFERROR(LOOKUP(VALUE(LEFT($E12&"",FIND("-",$E12&"-")-1)),$C$34:$C$39,$D$34:$D$39),"")) -> 750 | G12: Yes | H12: =IF($G12="VOID",0,$F12) -> 750 | I12: 750 | J12: =IF($I12="","n/a",IF($H12=$I12,"ok","MISMATCH")) -> ok | K12: 90000 | N12: Aurora Gaming
B13: AG.AL International | C13: CN | D13: High | E13: 3 | F13: =IF($E13="","",IFERROR(LOOKUP(VALUE(LEFT($E13&"",FIND("-",$E13&"-")-1)),$C$34:$C$39,$D$34:$D$39),"")) -> 500 | G13: Yes | H13: =IF($G13="VOID",0,$F13) -> 500 | I13: 500 | J13: =IF($I13="","n/a",IF($H13=$I13,"ok","MISMATCH")) -> ok | K13: 50000 | N13: AG.AL International
B14: Flash Wolves | C14: TW | D14: Medium | E14: 4 | F14: =IF($E14="","",IFERROR(LOOKUP(VALUE(LEFT($E14&"",FIND("-",$E14&"-")-1)),$C$34:$C$39,$D$34:$D$39),"")) -> 300 | G14: Yes | H14: =IF($G14="VOID",0,$F14) -> 300 | I14: 300 | J14: =IF($I14="","n/a",IF($H14=$I14,"ok","MISMATCH")) -> ok | K14: 30000 | N14: Flash Wolves
B15: Nongshim RedForce | C15: KR | D15: High | E15: 5-8 | F15: =IF($E15="","",IFERROR(LOOKUP(VALUE(LEFT($E15&"",FIND("-",$E15&"-")-1)),$C$34:$C$39,$D$34:$D$39),"")) -> 200 | G15: VOID | H15: =IF($G15="VOID",0,$F15) -> 0 | J15: =IF($I15="","n/a",IF($H15=$I15,"ok","MISMATCH")) -> n/a | K15: 20000 | L15: VOIDED — squad signed past the Team Deadline | N15: Nongshim RedForce
B16: Virtus.pro | C16: EMEA | D16: Medium | E16: 5-8 | F16: =IF($E16="","",IFERROR(LOOKUP(VALUE(LEFT($E16&"",FIND("-",$E16&"-")-1)),$C$34:$C$39,$D$34:$D$39),"")) -> 200 | G16: Yes | H16: =IF($G16="VOID",0,$F16) -> 200 | I16: 200 | J16: =IF($I16="","n/a",IF($H16=$I16,"ok","MISMATCH")) -> ok | K16: 20000 | N16: Virtus.pro
B17: Weibo Gaming | C17: CN | D17: High | E17: 5-8 | F17: =IF($E17="","",IFERROR(LOOKUP(VALUE(LEFT($E17&"",FIND("-",$E17&"-")-1)),$C$34:$C$39,$D$34:$D$39),"")) -> 200 | G17: Yes | H17: =IF($G17="VOID",0,$F17) -> 200 | I17: 200 | J17: =IF($I17="","n/a",IF($H17=$I17,"ok","MISMATCH")) -> ok | K17: 20000 | L17: invited, not via qualifier | N17: Weibo Gaming
B18: GodLike Esports | C18: IN | D18: Medium | E18: 5-8 | F18: =IF($E18="","",IFERROR(LOOKUP(VALUE(LEFT($E18&"",FIND("-",$E18&"-")-1)),$C$34:$C$39,$D$34:$D$39),"")) -> 200 | G18: Yes | H18: =IF($G18="VOID",0,$F18) -> 200 | J18: =IF($I18="","n/a",IF($H18=$I18,"ok","MISMATCH")) -> n/a | K18: 20000 | N18: GodLike
B19: T1 | C19: KR | D19: High | E19: 9-12 | F19: =IF($E19="","",IFERROR(LOOKUP(VALUE(LEFT($E19&"",FIND("-",$E19&"-")-1)),$C$34:$C$39,$D$34:$D$39),"")) -> 0 | G19: Yes | H19: =IF($G19="VOID",0,$F19) -> 0 | I19: 0 | J19: =IF($I19="","n/a",IF($H19=$I19,"ok","MISMATCH")) -> ok | K19: 15000 | N19: T1
B20: Movistar KOI | C20: EMEA | D20: Medium | E20: 9-12 | F20: =IF($E20="","",IFERROR(LOOKUP(VALUE(LEFT($E20&"",FIND("-",$E20&"-")-1)),$C$34:$C$39,$D$34:$D$39),"")) -> 0 | G20: Yes | H20: =IF($G20="VOID",0,$F20) -> 0 | I20: 0 | J20: =IF($I20="","n/a",IF($H20=$I20,"ok","MISMATCH")) -> ok | K20: 15000 | N20: Movistar KOI
B21: MOUZ | C21: EMEA | D21: Medium | E21: 9-12 | F21: =IF($E21="","",IFERROR(LOOKUP(VALUE(LEFT($E21&"",FIND("-",$E21&"-")-1)),$C$34:$C$39,$D$34:$D$39),"")) -> 0 | G21: Yes | H21: =IF($G21="VOID",0,$F21) -> 0 | I21: 0 | J21: =IF($I21="","n/a",IF($H21=$I21,"ok","MISMATCH")) -> ok | K21: 15000 | N21: MOUZ
B22: ZETA DIVISION | C22: JP | D22: Medium | E22: 9-12 | F22: =IF($E22="","",IFERROR(LOOKUP(VALUE(LEFT($E22&"",FIND("-",$E22&"-")-1)),$C$34:$C$39,$D$34:$D$39),"")) -> 0 | G22: Yes | H22: =IF($G22="VOID",0,$F22) -> 0 | I22: 0 | J22: =IF($I22="","n/a",IF($H22=$I22,"ok","MISMATCH")) -> ok | K22: 15000 | N22: ZETA DIVISION
B23: Fnatic | C23: EMEA | D23: Medium | E23: 13-16 | F23: =IF($E23="","",IFERROR(LOOKUP(VALUE(LEFT($E23&"",FIND("-",$E23&"-")-1)),$C$34:$C$39,$D$34:$D$39),"")) -> 0 | G23: Yes | H23: =IF($G23="VOID",0,$F23) -> 0 | I23: 0 | J23: =IF($I23="","n/a",IF($H23=$I23,"ok","MISMATCH")) -> ok | K23: 10000 | L23: Fnatic entry | N23: Fnatic
B24: Team Vitality | C24: EMEA | D24: Medium | E24: 13-16 | F24: =IF($E24="","",IFERROR(LOOKUP(VALUE(LEFT($E24&"",FIND("-",$E24&"-")-1)),$C$34:$C$39,$D$34:$D$39),"")) -> 0 | G24: Yes | H24: =IF($G24="VOID",0,$F24) -> 0 | I24: 0 | J24: =IF($I24="","n/a",IF($H24=$I24,"ok","MISMATCH")) -> ok | K24: 10000 | N24: Team Vitality
B25: JD Gaming | C25: CN | D25: High | E25: 13-16 | F25: =IF($E25="","",IFERROR(LOOKUP(VALUE(LEFT($E25&"",FIND("-",$E25&"-")-1)),$C$34:$C$39,$D$34:$D$39),"")) -> 0 | G25: Yes | H25: =IF($G25="VOID",0,$F25) -> 0 | I25: 0 | J25: =IF($I25="","n/a",IF($H25=$I25,"ok","MISMATCH")) -> ok | K25: 10000 | N25: JD Gaming
B26: Team Nemesis | C26: EMEA | D26: Medium | E26: 13-16 | F26: =IF($E26="","",IFERROR(LOOKUP(VALUE(LEFT($E26&"",FIND("-",$E26&"-")-1)),$C$34:$C$39,$D$34:$D$39),"")) -> 0 | G26: Yes | H26: =IF($G26="VOID",0,$F26) -> 0 | I26: 0 | J26: =IF($I26="","n/a",IF($H26=$I26,"ok","MISMATCH")) -> ok | K26: 10000 | N26: Team Nemesis
B28: TOTAL POINTS AWARDED | H28: =SUM(H11:H26) -> 3150
B29: 3,150 ELIGIBLE club points: the curve awards 3,350, but Nongshim RedForce's 200 was voided for signing past the Team Deadline. Prize money sums to the full $500,000.
B32: 2 · POINT SYSTEM
B33: From place | C33: Club points | D33: Band
C34: 1 | D34: 1000 | E34: 1st
C35: 2 | D35: 750 | E35: 2nd
C36: 3 | D36: 500 | E36: 3rd
C37: 4 | D37: 300 | E37: 4th
C38: 5 | D38: 200 | E38: 5th-8th
C39: 9 | D39: 0 | E39: 9th-16th
B42: 3 · SEED — METHOD E TODAY, WITH A REGIONAL CASE FOR UPGRADING
B43: THE RULE: High cohort = clubs from China or South Korea. Medium = everyone else. Applied programmatically from the Region column, so it is reproducible rather than hand-picked club by club. WHY: there is no pre-event ranking for TFT — teams arrive through separate regional qualifiers that produce no cross-region ordering — but region itself carried a clear signal in 2026. The CN/KR cohort converted five of seven entries into top-eight finishes (71%); everyone else converted three of nine (33%), against a 50% baseline. The top three were all Chinese: Team Vision, Aurora Gaming and AG.AL International. TWO JUDGEMENT CALLS WORTH KNOWING. Flash Wolves (Taiwan) sits in Medium because the rule is CN and KR specifically, yet they finished 4th — the single biggest cost of drawing the line that way. Including Taiwan would raise the High cohort to 75% conversion, but that would be fitting the rule to one result rather than to a stated principle. ZETA DIVISION (Japan) likewise stays Medium and finished 9th-12th, which supports the exclusion. STILL ONE EDITION OF EVIDENCE. TFT carries a high TVI of 65, so the cohort structure and the volatility term are pulling against each other by design: even High-cohort clubs will scatter widely in simulation. Recompute the regional block below after each new edition — a second consistent year would make this rule solid rather than provisional.
B51: Region | C51: Entries | D51: Top-8 finishes | E51: Top-8 rate | F51: Best result
B52: CN | C52: =COUNTIF($C$11:$C$26,$B52) -> 5 | D52: =SUMPRODUCT(($C$11:$C$26=$B52)*($F$11:$F$26>0)) -> 4 | E52: =IF(C52=0,"",D52/C52) -> 0.8 | F52: =IFERROR(SUMPRODUCT(MAX(($C$11:$C$26=$B52)*$H$11:$H$26)),0) -> 1000
B53: KR | C53: =COUNTIF($C$11:$C$26,$B53) -> 2 | D53: =SUMPRODUCT(($C$11:$C$26=$B53)*($F$11:$F$26>0)) -> 1 | E53: =IF(C53=0,"",D53/C53) -> 0.5 | F53: =IFERROR(SUMPRODUCT(MAX(($C$11:$C$26=$B53)*$H$11:$H$26)),0) -> 0
B54: JP | C54: =COUNTIF($C$11:$C$26,$B54) -> 1 | D54: =SUMPRODUCT(($C$11:$C$26=$B54)*($F$11:$F$26>0)) -> 0 | E54: =IF(C54=0,"",D54/C54) -> 0 | F54: =IFERROR(SUMPRODUCT(MAX(($C$11:$C$26=$B54)*$H$11:$H$26)),0) -> 0
B55: TW | C55: =COUNTIF($C$11:$C$26,$B55) -> 1 | D55: =SUMPRODUCT(($C$11:$C$26=$B55)*($F$11:$F$26>0)) -> 1 | E55: =IF(C55=0,"",D55/C55) -> 1 | F55: =IFERROR(SUMPRODUCT(MAX(($C$11:$C$26=$B55)*$H$11:$H$26)),0) -> 300
B56: IN | C56: =COUNTIF($C$11:$C$26,$B56) -> 1 | D56: =SUMPRODUCT(($C$11:$C$26=$B56)*($F$11:$F$26>0)) -> 1 | E56: =IF(C56=0,"",D56/C56) -> 1 | F56: =IFERROR(SUMPRODUCT(MAX(($C$11:$C$26=$B56)*$H$11:$H$26)),0) -> 200
B57: EMEA | C57: =COUNTIF($C$11:$C$26,$B57) -> 6 | D57: =SUMPRODUCT(($C$11:$C$26=$B57)*($F$11:$F$26>0)) -> 1 | E57: =IF(C57=0,"",D57/C57) -> 0.16666667 | F57: =IFERROR(SUMPRODUCT(MAX(($C$11:$C$26=$B57)*$H$11:$H$26)),0) -> 200
B59: Random baseline for top-8 rate is 50% (8 of 16 teams). Recompute after each edition to test whether the CN/KR rule holds.
B61: Cohort | C61: Clubs (auto) | D61: Band from | E61: Band to | F61: Mean (mu) | G61: Within sigma
B62: High | C62: =COUNTIF($D$11:$D$26,$B62) -> 7 | D62: =1 -> 1 | E62: =D62+C62-1 -> 7 | F62: =IF(C62=0,"",(D62+E62)/2) -> 4 | G62: =IF(C62=0,"",(E62-D62+1)/SQRT(12)) -> 2.0207259
B63: Medium | C63: =COUNTIF($D$11:$D$26,$B63) -> 9 | D63: =E62+1 -> 8 | E63: =D63+C63-1 -> 16 | F63: =IF(C63=0,"",(D63+E63)/2) -> 12 | G63: =IF(C63=0,"",(E63-D63+1)/SQRT(12)) -> 2.5980762
B64: Low | C64: =COUNTIF($D$11:$D$26,$B64) -> 0 | D64: =E63+1 -> 17 | E64: =D64+C64-1 -> 16 | F64: =IF(C64=0,"",(D64+E64)/2) | G64: =IF(C64=0,"",(E64-D64+1)/SQRT(12))

Sheet Rainbow Six
B2: Rainbow Six Siege — EWC 2026
B3: Seed method A — Six Invitational 2027 Global Points Standings. EWC awards no SI points and the later season events were unplayed, so that table is a clean pre-event snapshot.
B5: FORMAT | D5: FIELD SIZE | F5: TVI | H5: SEED METHOD | J5: SEED SOURCE | L5: PLACEMENT GRANULARITY
B6: Groups → playoffs | D6: 22 teams | F6: 30 · Low | H6: A — circuit points | J6: SI 2027 Global Standings | L6: Bands (5-8, 9-12, 13-16, then pairs)
B8: 1 · FIELD & RESULTS
B9: All 22 teams, ranked by SI points. Two teams (Al-Ula Club, MIBR.LOS) do not appear on the standings and are seeded last — an assumption, flagged in Notes.
B10: Club | C10: Region | D10: Seed | E10: SI rank | F10: SI points | G10: Placement | H10: Points (auto) | I10: CC eligible? | J10: Eligible pts | K10: Official CC pts | L10: Δ check | M10: Prize (USD) | N10: Notes | P10: Club (canonical)
B11: FaZe Clan | C11: South America | D11: 2 | E11: 1 | F11: 1610 | G11: 1 | H11: =IF($G11="","",IFERROR(LOOKUP(VALUE(LEFT($G11&"",FIND("-",$G11&"-")-1)),$C$40:$C$45,$D$40:$D$45),"")) -> 1000 | I11: Yes | J11: =IF($I11="VOID",0,$H11) -> 1000 | K11: 1000 | L11: =IF($K11="","n/a",IF($J11=$K11,"ok","MISMATCH")) -> ok | M11: 750000 | P11: FaZe Clan
B12: FURIA | C12: South America | D12: 12 | E12: 15 | F12: 890 | G12: 2 | H12: =IF($G12="","",IFERROR(LOOKUP(VALUE(LEFT($G12&"",FIND("-",$G12&"-")-1)),$C$40:$C$45,$D$40:$D$45),"")) -> 750 | I12: Yes | J12: =IF($I12="VOID",0,$H12) -> 750 | K12: 750 | L12: =IF($K12="","n/a",IF($J12=$K12,"ok","MISMATCH")) -> ok | M12: 350000 | N12: major overperformance (seed 12 → 2) | P12: FURIA
B13: DarkZero | C13: North America | D13: 1 | E13: 2 | F13: 1890 | G13: 3 | H13: =IF($G13="","",IFERROR(LOOKUP(VALUE(LEFT($G13&"",FIND("-",$G13&"-")-1)),$C$40:$C$45,$D$40:$D$45),"")) -> 500 | I13: Yes | J13: =IF($I13="VOID",0,$H13) -> 500 | L13: =IF($K13="","n/a",IF($J13=$K13,"ok","MISMATCH")) -> n/a | M13: 200000 | P13: DarkZero Esports
B14: Geekay Esports | C14: Europe MENA | D14: 18 | E14: 33 | F14: 270 | G14: 4 | H14: =IF($G14="","",IFERROR(LOOKUP(VALUE(LEFT($G14&"",FIND("-",$G14&"-")-1)),$C$40:$C$45,$D$40:$D$45),"")) -> 300 | I14: VOID | J14: =IF($I14="VOID",0,$H14) -> 0 | L14: =IF($K14="","n/a",IF($J14=$K14,"ok","MISMATCH")) -> n/a | M14: 115000 | N14: VOIDED — roster changes past the Deadline | P14: Geekay Esports
B15: Wildcard | C15: North America | D15: 5 | E15: 5 | F15: 1495 | G15: 5-8 | H15: =IF($G15="","",IFERROR(LOOKUP(VALUE(LEFT($G15&"",FIND("-",$G15&"-")-1)),$C$40:$C$45,$D$40:$D$45),"")) -> 200 | I15: Yes | J15: =IF($I15="VOID",0,$H15) -> 200 | K15: 200 | L15: =IF($K15="","n/a",IF($J15=$K15,"ok","MISMATCH")) -> ok | M15: 60000 | P15: Wildcard
B16: Weibo Gaming | C16: Asia Pacific | D16: 7 | E16: 8 | F16: 1310 | G16: 5-8 | H16: =IF($G16="","",IFERROR(LOOKUP(VALUE(LEFT($G16&"",FIND("-",$G16&"-")-1)),$C$40:$C$45,$D$40:$D$45),"")) -> 200 | I16: Yes | J16: =IF($I16="VOID",0,$H16) -> 200 | K16: 200 | L16: =IF($K16="","n/a",IF($J16=$K16,"ok","MISMATCH")) -> ok | M16: 60000 | P16: Weibo Gaming
B17: Team Liquid | C17: South America | D17: 15 | E17: 26 | F17: 350 | G17: 5-8 | H17: =IF($G17="","",IFERROR(LOOKUP(VALUE(LEFT($G17&"",FIND("-",$G17&"-")-1)),$C$40:$C$45,$D$40:$D$45),"")) -> 200 | I17: Yes | J17: =IF($I17="VOID",0,$H17) -> 200 | K17: 200 | L17: =IF($K17="","n/a",IF($J17=$K17,"ok","MISMATCH")) -> ok | M17: 60000 | N17: major overperformance (seed 15 → 5-8) | P17: Team Liquid
B18: Team Secret | C18: Europe MENA | D18: 20 | E18: 60 | F18: 80 | G18: 5-8 | H18: =IF($G18="","",IFERROR(LOOKUP(VALUE(LEFT($G18&"",FIND("-",$G18&"-")-1)),$C$40:$C$45,$D$40:$D$45),"")) -> 200 | I18: Yes | J18: =IF($I18="VOID",0,$H18) -> 200 | K18: 200 | L18: =IF($K18="","n/a",IF($J18=$K18,"ok","MISMATCH")) -> ok | M18: 60000 | N18: major overperformance (seed 20 → 5-8) | P18: Team Secret
B19: Team Falcons | C19: Europe MENA | D19: 6 | E19: 6 | F19: 1435 | G19: 9-12 | H19: =IF($G19="","",IFERROR(LOOKUP(VALUE(LEFT($G19&"",FIND("-",$G19&"-")-1)),$C$40:$C$45,$D$40:$D$45),"")) -> 0 | I19: Yes | J19: =IF($I19="VOID",0,$H19) -> 0 | K19: 0 | L19: =IF($K19="","n/a",IF($J19=$K19,"ok","MISMATCH")) -> ok | M19: 35000 | P19: Team Falcons
B20: CAG by VARREL | C20: Asia Pacific | D20: 10 | E20: 12 | F20: 1010 | G20: 9-12 | H20: =IF($G20="","",IFERROR(LOOKUP(VALUE(LEFT($G20&"",FIND("-",$G20&"-")-1)),$C$40:$C$45,$D$40:$D$45),"")) -> 0 | I20: Yes | J20: =IF($I20="VOID",0,$H20) -> 0 | L20: =IF($K20="","n/a",IF($J20=$K20,"ok","MISMATCH")) -> n/a | M20: 35000 | P20: CAG by VARREL
B21: Fnatic | C21: Europe MENA | D21: 19 | E21: 34 | F21: 260 | G21: 9-12 | H21: =IF($G21="","",IFERROR(LOOKUP(VALUE(LEFT($G21&"",FIND("-",$G21&"-")-1)),$C$40:$C$45,$D$40:$D$45),"")) -> 0 | I21: Yes | J21: =IF($I21="VOID",0,$H21) -> 0 | K21: 0 | L21: =IF($K21="","n/a",IF($J21=$K21,"ok","MISMATCH")) -> ok | M21: 35000 | N21: Fnatic entry | P21: Fnatic
B22: Virtus.pro | C22: Europe MENA | D22: 8 | E22: 10 | F22: 1125 | G22: 9-12 | H22: =IF($G22="","",IFERROR(LOOKUP(VALUE(LEFT($G22&"",FIND("-",$G22&"-")-1)),$C$40:$C$45,$D$40:$D$45),"")) -> 0 | I22: Yes | J22: =IF($I22="VOID",0,$H22) -> 0 | K22: 0 | L22: =IF($K22="","n/a",IF($J22=$K22,"ok","MISMATCH")) -> ok | M22: 35000 | P22: Virtus.pro
B23: AG.AL International | C23: CN | D23: 9 | E23: 11 | F23: 1040 | G23: 13-16 | H23: =IF($G23="","",IFERROR(LOOKUP(VALUE(LEFT($G23&"",FIND("-",$G23&"-")-1)),$C$40:$C$45,$D$40:$D$45),"")) -> 0 | I23: Yes | J23: =IF($I23="VOID",0,$H23) -> 0 | K23: 0 | L23: =IF($K23="","n/a",IF($J23=$K23,"ok","MISMATCH")) -> ok | M23: 25000 | P23: AG.AL International
B24: M80 | C24: North America | D24: 14 | E24: 25 | F24: 360 | G24: 13-16 | H24: =IF($G24="","",IFERROR(LOOKUP(VALUE(LEFT($G24&"",FIND("-",$G24&"-")-1)),$C$40:$C$45,$D$40:$D$45),"")) -> 0 | I24: Yes | J24: =IF($I24="VOID",0,$H24) -> 0 | L24: =IF($K24="","n/a",IF($J24=$K24,"ok","MISMATCH")) -> n/a | M24: 25000 | P24: M80
B25: EDward Gaming | C25: CN | D25: 11 | E25: 14 | F25: 895 | G25: 13-16 | H25: =IF($G25="","",IFERROR(LOOKUP(VALUE(LEFT($G25&"",FIND("-",$G25&"-")-1)),$C$40:$C$45,$D$40:$D$45),"")) -> 0 | I25: Yes | J25: =IF($I25="VOID",0,$H25) -> 0 | K25: 0 | L25: =IF($K25="","n/a",IF($J25=$K25,"ok","MISMATCH")) -> ok | M25: 25000 | P25: EDward Gaming
B26: ENTERPRISE Esports | C26: Asia Pacific | D26: 3 | E26: 3 | F26: 1560 | G26: 13-16 | H26: =IF($G26="","",IFERROR(LOOKUP(VALUE(LEFT($G26&"",FIND("-",$G26&"-")-1)),$C$40:$C$45,$D$40:$D$45),"")) -> 0 | I26: Yes | J26: =IF($I26="VOID",0,$H26) -> 0 | L26: =IF($K26="","n/a",IF($J26=$K26,"ok","MISMATCH")) -> n/a | M26: 25000 | N26: major underperformance (seed 3 → 13-16) | P26: ENTERPRISE Esports
B27: Shopify Rebellion | C27: North America | D27: 4 | E27: 4 | F27: 1515 | G27: 17-18 | H27: =IF($G27="","",IFERROR(LOOKUP(VALUE(LEFT($G27&"",FIND("-",$G27&"-")-1)),$C$40:$C$45,$D$40:$D$45),"")) -> 0 | I27: Yes | J27: =IF($I27="VOID",0,$H27) -> 0 | K27: 0 | L27: =IF($K27="","n/a",IF($J27=$K27,"ok","MISMATCH")) -> ok | M27: 20000 | N27: major underperformance (seed 4 → 17-18) | P27: Shopify Rebellion
B28: Al-Ula Club | C28: Europe MENA | D28: 21 | E28: — | G28: 17-18 | H28: =IF($G28="","",IFERROR(LOOKUP(VALUE(LEFT($G28&"",FIND("-",$G28&"-")-1)),$C$40:$C$45,$D$40:$D$45),"")) -> 0 | I28: Yes | J28: =IF($I28="VOID",0,$H28) -> 0 | L28: =IF($K28="","n/a",IF($J28=$K28,"ok","MISMATCH")) -> n/a | M28: 20000 | N28: not on SI standings — seeded last by assumption | P28: Al-Ula Club
B29: TYLOO | C29: CN | D29: 16 | E29: 26 | F29: 350 | G29: 19-20 | H29: =IF($G29="","",IFERROR(LOOKUP(VALUE(LEFT($G29&"",FIND("-",$G29&"-")-1)),$C$40:$C$45,$D$40:$D$45),"")) -> 0 | I29: Yes | J29: =IF($I29="VOID",0,$H29) -> 0 | L29: =IF($K29="","n/a",IF($J29=$K29,"ok","MISMATCH")) -> n/a | M29: 17500 | P29: TYLOO
B30: MIBR.LOS | C30: South America | D30: 22 | E30: — | G30: 19-20 | H30: =IF($G30="","",IFERROR(LOOKUP(VALUE(LEFT($G30&"",FIND("-",$G30&"-")-1)),$C$40:$C$45,$D$40:$D$45),"")) -> 0 | I30: Yes | J30: =IF($I30="VOID",0,$H30) -> 0 | K30: 0 | L30: =IF($K30="","n/a",IF($J30=$K30,"ok","MISMATCH")) -> ok | M30: 17500 | N30: not on SI standings — seeded last by assumption | P30: MIBR.LOS
B31: Chiefs Esports Club | C31: Asia Pacific | D31: 13 | E31: 21 | F31: 475 | G31: 21-22 | H31: =IF($G31="","",IFERROR(LOOKUP(VALUE(LEFT($G31&"",FIND("-",$G31&"-")-1)),$C$40:$C$45,$D$40:$D$45),"")) -> 0 | I31: Yes | J31: =IF($I31="VOID",0,$H31) -> 0 | L31: =IF($K31="","n/a",IF($J31=$K31,"ok","MISMATCH")) -> n/a | M31: 15000 | P31: Chiefs Esports Club
B32: KINGZERO eSports | C32: CN | D32: 17 | E32: 32 | F32: 280 | G32: 21-22 | H32: =IF($G32="","",IFERROR(LOOKUP(VALUE(LEFT($G32&"",FIND("-",$G32&"-")-1)),$C$40:$C$45,$D$40:$D$45),"")) -> 0 | I32: Yes | J32: =IF($I32="VOID",0,$H32) -> 0 | L32: =IF($K32="","n/a",IF($J32=$K32,"ok","MISMATCH")) -> n/a | M32: 15000 | P32: KINGZERO-eSports
B34: TOTAL POINTS AWARDED | J34: =SUM(J11:J32) -> 3050
B35: 3,050 ELIGIBLE club points: the curve awards 3,350, but Geekay Esports' 300 was voided for roster changes past the Deadline. Prize money sums to the full $2,000,000.
B38: 2 · POINT SYSTEM
B39: From place | C39: Club points | D39: Band
C40: 1 | D40: 1000 | E40: 1st
C41: 2 | D41: 750 | E41: 2nd
C42: 3 | D42: 500 | E42: 3rd
C43: 4 | D43: 300 | E43: 4th
C44: 5 | D44: 200 | E44: 5th-8th
C45: 9 | D45: 0 | E45: 9th-22nd
B48: 3 · SEED SOURCE — SI 2027 Global Standings
B49: Why this source is clean. Ubisoft's Six Invitational points are the ecosystem's own ranking and they decide SI qualification, so teams take them seriously. Critically, EWC itself awards NO SI points, and the two later season events on the table (Regional Leagues 2, November Major) were unplayed at the time of writing — so the standings are a genuine pre-event snapshot built from the Regional Kickoff, the May Major and Regional Leagues 1. No result leakage. ONE DISCREPANCY WORTH KNOWING: Liquipedia's own rank column does not order strictly by points — FaZe are listed 1st on 1,610 while DarkZero sit 2nd on 1,890. The seeds here are built from POINTS descending, since points are the measurable quantity; the published rank is kept alongside so the difference is visible. WHAT 2026 SHOWED: middling. Champion FaZe entered as the 2nd-highest-pointed team and DarkZero, top on points, took 3rd — the very top converted well. Below that it fell apart: ENTERPRISE (seed 3) finished 13th-16th, Shopify Rebellion (seed 4) 17th-18th, and Falcons (seed 6) 9th-12th, while runner-up FURIA came from seed 12, Geekay reached 4th from seed 18, and Team Secret made the top eight from seed 20 on just 80 points. This is now a recurring shape across titles: the elite converts, the middle of the seed list predicts very little. Worth holding in mind when the TVI is eventually recalibrated — R6 carries a low 30, which fits the top of the field but not the rest of it.
B57: Seed | C57: Club | D57: SI points | E57: Result | F57: Seed − result
B58: 1 | C58: DarkZero | D58: 1890 | E58: 3 | F58: -2
B59: 2 | C59: FaZe Clan | D59: 1610 | E59: 1 | F59: 1
B60: 3 | C60: ENTERPRISE Esports | D60: 1560 | E60: 13-16 | F60: -10
B61: 4 | C61: Shopify Rebellion | D61: 1515 | E61: 17-18 | F61: -13
B62: 5 | C62: Wildcard | D62: 1495 | E62: 5-8 | F62: 0
B63: 6 | C63: Team Falcons | D63: 1435 | E63: 9-12 | F63: -3
B64: 7 | C64: Weibo Gaming | D64: 1310 | E64: 5-8 | F64: 2
B65: 8 | C65: Virtus.pro | D65: 1125 | E65: 9-12 | F65: -1
B66: 9 | C66: AG.AL International | D66: 1040 | E66: 13-16 | F66: -4
B67: 10 | C67: CAG by VARREL | D67: 1010 | E67: 9-12 | F67: 1
B68: 11 | C68: EDward Gaming | D68: 895 | E68: 13-16 | F68: -2
B69: 12 | C69: FURIA | D69: 890 | E69: 2 | F69: 10
... B77: 20 | C77: Team Secret | D77: 80 | E77: 5-8 | F77: 15
B78: 21 | C78: Al-Ula Club | E78: 17-18 | F78: 4
B79: 22 | C79: MIBR.LOS | E79: 19-20 | F79: 3

Sheet Warzone
B2: Warzone — EWC 2026
B3: Trios battle royale, listed on Liquipedia as 'Warzone Resurgence Series 2026 Championship'. Seed method B — qualification route and timing, not a ranking.
B5: FORMAT | D5: FIELD SIZE | F5: TVI | H5: SEED METHOD | J5: SEED SOURCE | L5: PLACEMENT GRANULARITY
B6: Groups → Survival → Finals | D6: 32 trios | F6: 75 · High | H6: B — qualification route | J6: Invite → LANs → regional opens | L6: Exact 1-26, ties from 27th
B8: 1 · FIELD & RESULTS
B9: All 32 trios, ordered by the qualification-route seed. Six seeds are marked INFERRED — the qualifier result and the EWC field disagree on the org name, so the slot is matched by field position rather than a verified link.
B10: Club | C10: Seed | D10: Route | E10: Qual. place | F10: Placement | G10: Points (auto) | H10: Official CC pts | I10: Δ check | J10: Prize (USD) | K10: Seed basis | M10: Club (canonical)
B11: Twisted Minds | C11: 1 | D11: Invited | E11: — | F11: 4 | G11: =IF($F11="","",IFERROR(LOOKUP(VALUE(LEFT($F11&"",FIND("-",$F11&"-")-1)),$C$50:$C$58,$D$50:$D$58),"")) -> 300 | H11: 300 | I11: =IF($H11="","n/a",IF($G11=$H11,"ok","MISMATCH")) -> ok | J11: 72000 | K11: defending champion, invited | M11: Twisted Minds
B12: Team Falcons | C12: 2 | D12: Birmingham | E12: 1 | F12: 16 | G12: =IF($F12="","",IFERROR(LOOKUP(VALUE(LEFT($F12&"",FIND("-",$F12&"-")-1)),$C$50:$C$58,$D$50:$D$58),"")) -> 0 | H12: 0 | I12: =IF($H12="","n/a",IF($G12=$H12,"ok","MISMATCH")) -> ok | J12: 11500 | K12: won DH Birmingham | M12: Team Falcons
B13: Leviatán | C13: 3 | D13: Birmingham | E13: 3 | F13: 7 | G13: =IF($F13="","",IFERROR(LOOKUP(VALUE(LEFT($F13&"",FIND("-",$F13&"-")-1)),$C$50:$C$58,$D$50:$D$58),"")) -> 100 | H13: 100 | I13: =IF($H13="","n/a",IF($G13=$H13,"ok","MISMATCH")) -> ok | J13: 35000 | K13: INFERRED: Birmingham 3rd was Los Corillos; Leviatán occupies that slot in the EWC field | M13: Leviatán
B14: Ravens Esports | C14: 4 | D14: Birmingham | E14: 4 | F14: 13 | G14: =IF($F14="","",IFERROR(LOOKUP(VALUE(LEFT($F14&"",FIND("-",$F14&"-")-1)),$C$50:$C$58,$D$50:$D$58),"")) -> 0 | I14: =IF($H14="","n/a",IF($G14=$H14,"ok","MISMATCH")) -> n/a | J14: 17000 | K14: also won MENA online; earliest route counts | M14: Ravens Esports
B15: Virtus.pro | C15: 5 | D15: Birmingham | E15: 5 | F15: 8 | G15: =IF($F15="","",IFERROR(LOOKUP(VALUE(LEFT($F15&"",FIND("-",$F15&"-")-1)),$C$50:$C$58,$D$50:$D$58),"")) -> 50 | H15: 50 | I15: =IF($H15="","n/a",IF($G15=$H15,"ok","MISMATCH")) -> ok | J15: 30000 | K15: verified route | M15: Virtus.pro
B16: Team Orchid | C16: 6 | D16: Atlanta | E16: 3 | F16: 18 | G16: =IF($F16="","",IFERROR(LOOKUP(VALUE(LEFT($F16&"",FIND("-",$F16&"-")-1)),$C$50:$C$58,$D$50:$D$58),"")) -> 0 | I16: =IF($H16="","n/a",IF($G16=$H16,"ok","MISMATCH")) -> n/a | J16: 10500 | K16: verified route | M16: Team Orchid
B17: G2 Esports | C17: 7 | D17: Atlanta | E17: 5 | F17: 1 | G17: =IF($F17="","",IFERROR(LOOKUP(VALUE(LEFT($F17&"",FIND("-",$F17&"-")-1)),$C$50:$C$58,$D$50:$D$58),"")) -> 1000 | H17: 1000 | I17: =IF($H17="","n/a",IF($G17=$H17,"ok","MISMATCH")) -> ok | J17: 250000 | K17: verified route | M17: G2 Esports
B18: NOVO Esports | C18: 8 | D18: Atlanta | E18: 6 | F18: 10 | G18: =IF($F18="","",IFERROR(LOOKUP(VALUE(LEFT($F18&"",FIND("-",$F18&"-")-1)),$C$50:$C$58,$D$50:$D$58),"")) -> 0 | I18: =IF($H18="","n/a",IF($G18=$H18,"ok","MISMATCH")) -> n/a | J18: 24000 | K18: verified route | M18: NOVO Esports
B19: JD Gaming | C19: 9 | D19: Atlanta | E19: 7 | F19: 3 | G19: =IF($F19="","",IFERROR(LOOKUP(VALUE(LEFT($F19&"",FIND("-",$F19&"-")-1)),$C$50:$C$58,$D$50:$D$58),"")) -> 500 | H19: 500 | I19: =IF($H19="","n/a",IF($G19=$H19,"ok","MISMATCH")) -> ok | J19: 100000 | K19: verified route | M19: JD Gaming
B20: T1 | C20: 10 | D20: Atlanta | E20: 8 | F20: 2 | G20: =IF($F20="","",IFERROR(LOOKUP(VALUE(LEFT($F20&"",FIND("-",$F20&"-")-1)),$C$50:$C$58,$D$50:$D$58),"")) -> 750 | H20: 750 | I20: =IF($H20="","n/a",IF($G20=$H20,"ok","MISMATCH")) -> ok | J20: 145000 | K20: verified route | M20: T1
B21: Team Vitality | C21: 11 | D21: NA online | E21: 1 | F21: 11 | G21: =IF($F21="","",IFERROR(LOOKUP(VALUE(LEFT($F21&"",FIND("-",$F21&"-")-1)),$C$50:$C$58,$D$50:$D$58),"")) -> 0 | H21: 0 | I21: =IF($H21="","n/a",IF($G21=$H21,"ok","MISMATCH")) -> ok | J21: 21000 | K21: verified route | M21: Team Vitality
B22: For Fun Esports | C22: 12 | D22: NA online | E22: 2 | F22: 24 | G22: =IF($F22="","",IFERROR(LOOKUP(VALUE(LEFT($F22&"",FIND("-",$F22&"-")-1)),$C$50:$C$58,$D$50:$D$58),"")) -> 0 | I22: =IF($H22="","n/a",IF($G22=$H22,"ok","MISMATCH")) -> n/a | J22: 7500 | K22: verified route | M22: For Fun Esports
B23: Gen.G Esports | C23: 13 | D23: NA online | E23: 3 | F23: 12 | G23: =IF($F23="","",IFERROR(LOOKUP(VALUE(LEFT($F23&"",FIND("-",$F23&"-")-1)),$C$50:$C$58,$D$50:$D$58),"")) -> 0 | H23: 0 | I23: =IF($H23="","n/a",IF($G23=$H23,"ok","MISMATCH")) -> ok | J23: 19000 | K23: verified route | M23: Gen.G Esports
B24: GodLike Esports | C24: 14 | D24: NA online | E24: 4 | F24: 25 | G24: =IF($F24="","",IFERROR(LOOKUP(VALUE(LEFT($F24&"",FIND("-",$F24&"-")-1)),$C$50:$C$58,$D$50:$D$58),"")) -> 0 | I24: =IF($H24="","n/a",IF($G24=$H24,"ok","MISMATCH")) -> n/a | J24: 7000 | K24: verified route | M24: GodLike
B25: AG.AL | C25: 15 | D25: NA online | E25: 5 | F25: 14 | G25: =IF($F25="","",IFERROR(LOOKUP(VALUE(LEFT($F25&"",FIND("-",$F25&"-")-1)),$C$50:$C$58,$D$50:$D$58),"")) -> 0 | H25: 0 | I25: =IF($H25="","n/a",IF($G25=$H25,"ok","MISMATCH")) -> ok | J25: 15000 | K25: verified route | M25: AG.AL International
B26: PBJ | C26: 16 | D26: NA online | E26: 6 | F26: 15 | G26: =IF($F26="","",IFERROR(LOOKUP(VALUE(LEFT($F26&"",FIND("-",$F26&"-")-1)),$C$50:$C$58,$D$50:$D$58),"")) -> 0 | I26: =IF($H26="","n/a",IF($G26=$H26,"ok","MISMATCH")) -> n/a | J26: 13000 | K26: INFERRED: NA 6th qualifier had no org tag; PBJ fills that slot in field order | M26: PBJ
B27: Fnatic | C27: 17 | D27: LATAM N | E27: 1 | F27: 29-30 | G27: =IF($F27="","",IFERROR(LOOKUP(VALUE(LEFT($F27&"",FIND("-",$F27&"-")-1)),$C$50:$C$58,$D$50:$D$58),"")) -> 0 | H27: 0 | I27: =IF($H27="","n/a",IF($G27=$H27,"ok","MISMATCH")) -> ok | J27: 5500 | K27: Fnatic entry | M27: Fnatic
B28: FaZe Clan | C28: 18 | D28: LATAM N | E28: 2 | F28: 31-32 | G28: =IF($F28="","",IFERROR(LOOKUP(VALUE(LEFT($F28&"",FIND("-",$F28&"-")-1)),$C$50:$C$58,$D$50:$D$58),"")) -> 0 | H28: 0 | I28: =IF($H28="","n/a",IF($G28=$H28,"ok","MISMATCH")) -> ok | J28: 5000 | K28: INFERRED: LATAM N 2nd was Phoenix Arena; FaZe occupies that slot in the EWC field | M28: FaZe Clan
B29: CT Gaming | C29: 19 | D29: LATAM N | E29: 4 | F29: 29-30 | G29: =IF($F29="","",IFERROR(LOOKUP(VALUE(LEFT($F29&"",FIND("-",$F29&"-")-1)),$C$50:$C$58,$D$50:$D$58),"")) -> 0 | I29: =IF($H29="","n/a",IF($G29=$H29,"ok","MISMATCH")) -> n/a | J29: 5500 | K29: verified route | M29: CT Gaming
B30: First Squad | C30: 20 | D30: LATAM S | E30: 1 | F30: 27-28 | G30: =IF($F30="","",IFERROR(LOOKUP(VALUE(LEFT($F30&"",FIND("-",$F30&"-")-1)),$C$50:$C$58,$D$50:$D$58),"")) -> 0 | I30: =IF($H30="","n/a",IF($G30=$H30,"ok","MISMATCH")) -> n/a | J30: 6000 | K30: verified route | M30: First Squad
B31: New Icons | C31: 21 | D31: LATAM S | E31: 2 | F31: 31-32 | G31: =IF($F31="","",IFERROR(LOOKUP(VALUE(LEFT($F31&"",FIND("-",$F31&"-")-1)),$C$50:$C$58,$D$50:$D$58),"")) -> 0 | I31: =IF($H31="","n/a",IF($G31=$H31,"ok","MISMATCH")) -> n/a | J31: 5000 | K31: verified route | M31: New Icons
B32: Gentle Mates | C32: 22 | D32: EU online | E32: 1 | F32: 5 | G32: =IF($F32="","",IFERROR(LOOKUP(VALUE(LEFT($F32&"",FIND("-",$F32&"-")-1)),$C$50:$C$58,$D$50:$D$58),"")) -> 200 | H32: 200 | I32: =IF($H32="","n/a",IF($G32=$H32,"ok","MISMATCH")) -> ok | J32: 55000 | K32: verified route | M32: Gentle Mates
B33: Ekletyc | C33: 23 | D33: EU online | E33: 2 | F33: 6 | G33: =IF($F33="","",IFERROR(LOOKUP(VALUE(LEFT($F33&"",FIND("-",$F33&"-")-1)),$C$50:$C$58,$D$50:$D$58),"")) -> 150 | I33: =IF($H33="","n/a",IF($G33=$H33,"ok","MISMATCH")) -> n/a | J33: 45000 | K33: verified route | M33: Ekletyc
B34: Ninjas In Pyjamas eStar | C34: 24 | D34: EU online | E34: 3 | F34: 9 | G34: =IF($F34="","",IFERROR(LOOKUP(VALUE(LEFT($F34&"",FIND("-",$F34&"-")-1)),$C$50:$C$58,$D$50:$D$58),"")) -> 0 | I34: =IF($H34="","n/a",IF($G34=$H34,"ok","MISMATCH")) -> n/a | J34: 27000 | K34: listed as Ninjas In Pyjamas in the qualifier | M34: Ninjas in Pyjamas
B35: H1 | C35: 25 | D35: EU online | E35: 4 | F35: 23 | G35: =IF($F35="","",IFERROR(LOOKUP(VALUE(LEFT($F35&"",FIND("-",$F35&"-")-1)),$C$50:$C$58,$D$50:$D$58),"")) -> 0 | I35: =IF($H35="","n/a",IF($G35=$H35,"ok","MISMATCH")) -> n/a | J35: 8000 | K35: INFERRED: EU 4th was Insight Gaming; H1 occupies that slot in the EWC field | M35: H1
B36: Geekay Esports | C36: 26 | D36: EU online | E36: 5 | F36: 17 | G36: =IF($F36="","",IFERROR(LOOKUP(VALUE(LEFT($F36&"",FIND("-",$F36&"-")-1)),$C$50:$C$58,$D$50:$D$58),"")) -> 0 | H36: 0 | I36: =IF($H36="","n/a",IF($G36=$H36,"ok","MISMATCH")) -> ok | J36: 11000 | K36: verified route | M36: Geekay Esports
B37: KGV | C37: 27 | D37: EU online | E37: 6 | F37: 21 | G37: =IF($F37="","",IFERROR(LOOKUP(VALUE(LEFT($F37&"",FIND("-",$F37&"-")-1)),$C$50:$C$58,$D$50:$D$58),"")) -> 0 | I37: =IF($H37="","n/a",IF($G37=$H37,"ok","MISMATCH")) -> n/a | J37: 9000 | K37: INFERRED: EU 6th qualifier had no org tag | M37: KGV
B38: Team Nemesis | C38: 28 | D38: APAC | E38: 1 | F38: 19 | G38: =IF($F38="","",IFERROR(LOOKUP(VALUE(LEFT($F38&"",FIND("-",$F38&"-")-1)),$C$50:$C$58,$D$50:$D$58),"")) -> 0 | H38: 0 | I38: =IF($H38="","n/a",IF($G38=$H38,"ok","MISMATCH")) -> ok | J38: 10000 | K38: verified route | M38: Team Nemesis
B39: Team Heretics | C39: 29 | D39: APAC | E39: 2 | F39: 20 | G39: =IF($F39="","",IFERROR(LOOKUP(VALUE(LEFT($F39&"",FIND("-",$F39&"-")-1)),$C$50:$C$58,$D$50:$D$58),"")) -> 0 | H39: 0 | I39: =IF($H39="","n/a",IF($G39=$H39,"ok","MISMATCH")) -> ok | J39: 9500 | K39: verified route | M39: Team Heretics
B40: Team Stallions | C40: 30 | D40: MENA | E40: 2 | F40: 22 | G40: =IF($F40="","",IFERROR(LOOKUP(VALUE(LEFT($F40&"",FIND("-",$F40&"-")-1)),$C$50:$C$58,$D$50:$D$58),"")) -> 0 | H40: 0 | I40: =IF($H40="","n/a",IF($G40=$H40,"ok","MISMATCH")) -> ok | J40: 8500 | K40: listed as Stallions in the EWC field | M40: Team Stallions
B41: Gamax Esports | C41: 31 | D41: MENA | E41: 3 | F41: 26 | G41: =IF($F41="","",IFERROR(LOOKUP(VALUE(LEFT($F41&"",FIND("-",$F41&"-")-1)),$C$50:$C$58,$D$50:$D$58),"")) -> 0 | I41: =IF($H41="","n/a",IF($G41=$H41,"ok","MISMATCH")) -> n/a | J41: 6500 | K41: verified route | M41: Gamax Esports
B42: The Vicious | C42: 32 | D42: MENA | E42: 4 | F42: 27-28 | G42: =IF($F42="","",IFERROR(LOOKUP(VALUE(LEFT($F42&"",FIND("-",$F42&"-")-1)),$C$50:$C$58,$D$50:$D$58),"")) -> 0 | H42: 0 | I42: =IF($H42="","n/a",IF($G42=$H42,"ok","MISMATCH")) -> ok | J42: 6000 | K42: INFERRED: MENA slot passed down after Ravens qualified via Birmingham | M42: The Vicious
B44: TOTAL POINTS AWARDED | G44: =SUM(G11:G42) -> 3050
B45: 3,050 club points — battle-royale curve. Prize money sums to the full $1,000,000.
B48: 2 · POINT SYSTEM
B49: Place | C49: Club points
C50: 1 | D50: 1000
C51: 2 | D51: 750
C52: 3 | D52: 500
C53: 4 | D53: 300
C54: 5 | D54: 200
C55: 6 | D55: 150
C56: 7 | D56: 100
C57: 8 | D57: 50
C58: 9 | D58: 0 | E58: 9th and below — no award
B61: 3 · SEED — QUALIFICATION ROUTE AND TIMING (METHOD B)
B62: There is no Warzone ranking to seed from, but qualification timing carries information: the strongest rosters tend to qualify first, at the two LAN events, while later online opens fill the remaining slots. The seed order is therefore: invited champion, then DH Birmingham, then DH Atlanta, then the regional online opens in the priority order supplied — North America, LATAM North, LATAM South, Europe, APAC, MENA. Within each route, teams are ordered by their finishing position in that qualifier. SIX SEEDS ARE INFERRED, marked amber. In those cases the qualifier winner and the EWC entrant carry different org names — Birmingham's 3rd place was Los Corillos while Leviatán occupies that slot in the field, the NA 6th qualifier carried no org tag at all, and so on. The slot is matched by position in the field rather than a verified link, so treat those six as assumptions. NOTE ON RAVENS ESPORTS: they qualified twice, winning the MENA online open and placing 4th at Birmingham. The earlier LAN route is used, which is the whole logic of this method. WHAT 2026 SHOWED: the route seed was weak, as a TVI of 75 would predict. Champion G2 came from Atlanta 5th (seed 7) and runner-up T1 from Atlanta 8th (seed 10), so the Atlanta cohort did convert — but Birmingham winners Team Falcons finished 16th, and the invited defending champions Twisted Minds took 4th. Meanwhile Gentle Mates and Ekletyc reached 5th and 6th from the European online open, seeds 22 and 23. For a high-volatility battle royale this is roughly what the model should expect: a real but weak signal, better than method E and far short of a ranking.
B70: Route | C70: Teams | D70: Top-8 finishes | E70: Best result | F70: Avg finish
B71: Invited | C71: =COUNTIF($D$11:$D$42,$B71) -> 1 | D71: =SUMPRODUCT(($D$11:$D$42=$B71)*($G$11:$G$42>0)) -> 1 | E71: =IFERROR(SUMPRODUCT(MAX(($D$11:$D$42=$B71)*$G$11:$G$42)),0) -> 300
B72: Birmingham | C72: =COUNTIF($D$11:$D$42,$B72) -> 4 | D72: =SUMPRODUCT(($D$11:$D$42=$B72)*($G$11:$G$42>0)) -> 2 | E72: =IFERROR(SUMPRODUCT(MAX(($D$11:$D$42=$B72)*$G$11:$G$42)),0) -> 100
B73: Atlanta | C73: =COUNTIF($D$11:$D$42,$B73) -> 5 | D73: =SUMPRODUCT(($D$11:$D$42=$B73)*($G$11:$G$42>0)) -> 3 | E73: =IFERROR(SUMPRODUCT(MAX(($D$11:$D$42=$B73)*$G$11:$G$42)),0) -> 1000
B74: NA online | C74: =COUNTIF($D$11:$D$42,$B74) -> 6 | D74: =SUMPRODUCT(($D$11:$D$42=$B74)*($G$11:$G$42>0)) -> 0 | E74: =IFERROR(SUMPRODUCT(MAX(($D$11:$D$42=$B74)*$G$11:$G$42)),0) -> 0
B75: LATAM N | C75: =COUNTIF($D$11:$D$42,$B75) -> 3 | D75: =SUMPRODUCT(($D$11:$D$42=$B75)*($G$11:$G$42>0)) -> 0 | E75: =IFERROR(SUMPRODUCT(MAX(($D$11:$D$42=$B75)*$G$11:$G$42)),0) -> 0
B76: LATAM S | C76: =COUNTIF($D$11:$D$42,$B76) -> 2 | D76: =SUMPRODUCT(($D$11:$D$42=$B76)*($G$11:$G$42>0)) -> 0 | E76: =IFERROR(SUMPRODUCT(MAX(($D$11:$D$42=$B76)*$G$11:$G$42)),0) -> 0
B77: EU online | C77: =COUNTIF($D$11:$D$42,$B77) -> 6 | D77: =SUMPRODUCT(($D$11:$D$42=$B77)*($G$11:$G$42>0)) -> 2 | E77: =IFERROR(SUMPRODUCT(MAX(($D$11:$D$42=$B77)*$G$11:$G$42)),0) -> 200
B78: APAC | C78: =COUNTIF($D$11:$D$42,$B78) -> 2 | D78: =SUMPRODUCT(($D$11:$D$42=$B78)*($G$11:$G$42>0)) -> 0 | E78: =IFERROR(SUMPRODUCT(MAX(($D$11:$D$42=$B78)*$G$11:$G$42)),0) -> 0
B79: MENA | C79: =COUNTIF($D$11:$D$42,$B79) -> 3 | D79: =SUMPRODUCT(($D$11:$D$42=$B79)*($G$11:$G$42>0)) -> 0 | E79: =IFERROR(SUMPRODUCT(MAX(($D$11:$D$42=$B79)*$G$11:$G$42)),0) -> 0
B81: Use this block to test whether route order predicts anything across future editions — if the LAN routes keep outperforming the late online opens, method B is justified for this title.

Sheet Valorant
B2: VALORANT — EWC 2026
B3: Seeded from Riot's own VALORANT Global Power Rankings — the 'End of Masters London' snapshot, dated 21 June 2026, eleven days before this event. A clean pre-event ranking with numeric power scores.
B5: FORMAT | D5: FIELD SIZE | F5: TVI | H5: SEED METHOD | J5: SEED SOURCE | L5: PLACEMENT GRANULARITY
B6: Groups → playoffs | D6: 16 teams | F6: 50 · Medium | H6: A — publisher power ranking | J6: Riot GPR, End of Masters London (21 Jun 26) | L6: Bands (5-8, 9-12, 13-16)
B8: 1 · FIELD & RESULTS
B9: All 16 teams, seeded by GPR power score. The score is kept alongside the rank because it is a genuine strength measure — the gap from NRG on 1,472 to AG.AL on 1,181 is information a bare ranking would lose.
B10: Club | C10: VCT league | D10: Seed | E10: GPR rank | F10: GPR score | G10: Placement | H10: Points (auto) | I10: Official CC pts | J10: Δ check | K10: Prize (USD) | L10: Notes | N10: Club (canonical)
B11: Paper Rex | C11: VCT Pacific | D11: 1 | E11: 1 | F11: 1605 | G11: 13-16 | H11: =IF($G11="","",IFERROR(LOOKUP(VALUE(LEFT($G11&"",FIND("-",$G11&"-")-1)),$C$34:$C$39,$D$34:$D$39),"")) -> 0 | J11: =IF($I11="","n/a",IF($H11=$I11,"ok","MISMATCH")) -> n/a | K11: 30000 | L11: underperformed seed (1 → 13-16) | N11: Paper Rex
B12: Nongshim RedForce | C12: VCT Pacific | D12: 2 | E12: 3 | F12: 1434 | G12: 3 | H12: =IF($G12="","",IFERROR(LOOKUP(VALUE(LEFT($G12&"",FIND("-",$G12&"-")-1)),$C$34:$C$39,$D$34:$D$39),"")) -> 500 | I12: 500 | J12: =IF($I12="","n/a",IF($H12=$I12,"ok","MISMATCH")) -> ok | K12: 220000 | N12: Nongshim RedForce
B13: NRG | C13: VCT Americas | D13: 3 | E13: 5 | F13: 1403 | G13: 2 | H13: =IF($G13="","",IFERROR(LOOKUP(VALUE(LEFT($G13&"",FIND("-",$G13&"-")-1)),$C$34:$C$39,$D$34:$D$39),"")) -> 750 | I13: 750 | J13: =IF($I13="","n/a",IF($H13=$I13,"ok","MISMATCH")) -> ok | K13: 340000 | N13: NRG
B14: Team Vitality | C14: VCT EMEA | D14: 4 | E14: 7 | F14: 1397 | G14: 5-8 | H14: =IF($G14="","",IFERROR(LOOKUP(VALUE(LEFT($G14&"",FIND("-",$G14&"-")-1)),$C$34:$C$39,$D$34:$D$39),"")) -> 200 | I14: 200 | J14: =IF($I14="","n/a",IF($H14=$I14,"ok","MISMATCH")) -> ok | K14: 90000 | N14: Team Vitality
B15: G2 Esports | C15: VCT Americas | D15: 5 | E15: 8 | F15: 1360 | G15: 9-12 | H15: =IF($G15="","",IFERROR(LOOKUP(VALUE(LEFT($G15&"",FIND("-",$G15&"-")-1)),$C$34:$C$39,$D$34:$D$39),"")) -> 0 | I15: 0 | J15: =IF($I15="","n/a",IF($H15=$I15,"ok","MISMATCH")) -> ok | K15: 55000 | N15: G2 Esports
B16: EDward Gaming | C16: VCT CN | D16: 6 | E16: 10 | F16: 1342 | G16: 9-12 | H16: =IF($G16="","",IFERROR(LOOKUP(VALUE(LEFT($G16&"",FIND("-",$G16&"-")-1)),$C$34:$C$39,$D$34:$D$39),"")) -> 0 | I16: 0 | J16: =IF($I16="","n/a",IF($H16=$I16,"ok","MISMATCH")) -> ok | K16: 55000 | N16: EDward Gaming
B17: 100 Thieves | C17: VCT Americas | D17: 7 | E17: 11 | F17: 1324 | G17: 1 | H17: =IF($G17="","",IFERROR(LOOKUP(VALUE(LEFT($G17&"",FIND("-",$G17&"-")-1)),$C$34:$C$39,$D$34:$D$39),"")) -> 1000 | I17: 1000 | J17: =IF($I17="","n/a",IF($H17=$I17,"ok","MISMATCH")) -> ok | K17: 600000 | L17: overperformed seed (7 → 1) | N17: 100 Thieves
B18: Global Esports | C18: VCT Pacific | D18: 8 | E18: 12 | F18: 1318 | G18: 13-16 | H18: =IF($G18="","",IFERROR(LOOKUP(VALUE(LEFT($G18&"",FIND("-",$G18&"-")-1)),$C$34:$C$39,$D$34:$D$39),"")) -> 0 | J18: =IF($I18="","n/a",IF($H18=$I18,"ok","MISMATCH")) -> n/a | K18: 30000 | N18: Global Esports
B19: XLG Esports | C19: VCT CN | D19: 9 | E19: 16 | F19: 1301 | G19: 13-16 | H19: =IF($G19="","",IFERROR(LOOKUP(VALUE(LEFT($G19&"",FIND("-",$G19&"-")-1)),$C$34:$C$39,$D$34:$D$39),"")) -> 0 | J19: =IF($I19="","n/a",IF($H19=$I19,"ok","MISMATCH")) -> n/a | K19: 30000 | N19: XLG Esports
B20: Team Heretics | C20: VCT EMEA | D20: 10 | E20: 17 | F20: 1296 | G20: 5-8 | H20: =IF($G20="","",IFERROR(LOOKUP(VALUE(LEFT($G20&"",FIND("-",$G20&"-")-1)),$C$34:$C$39,$D$34:$D$39),"")) -> 200 | I20: 200 | J20: =IF($I20="","n/a",IF($H20=$I20,"ok","MISMATCH")) -> ok | K20: 90000 | N20: Team Heretics
B21: Rex Regum Qeon | C21: VCT Pacific | D21: 11 | E21: 17 | F21: 1296 | G21: 13-16 | H21: =IF($G21="","",IFERROR(LOOKUP(VALUE(LEFT($G21&"",FIND("-",$G21&"-")-1)),$C$34:$C$39,$D$34:$D$39),"")) -> 0 | I21: 0 | J21: =IF($I21="","n/a",IF($H21=$I21,"ok","MISMATCH")) -> ok | K21: 30000 | N21: Rex Regum Qeon
B22: MIBR.LOS | C22: VCT Americas | D22: 12 | E22: 19 | F22: 1291 | G22: 5-8 | H22: =IF($G22="","",IFERROR(LOOKUP(VALUE(LEFT($G22&"",FIND("-",$G22&"-")-1)),$C$34:$C$39,$D$34:$D$39),"")) -> 200 | I22: 200 | J22: =IF($I22="","n/a",IF($H22=$I22,"ok","MISMATCH")) -> ok | K22: 90000 | L22: overperformed seed (12 → 5-8) | N22: MIBR.LOS
B23: BBL Esports | C23: VCT EMEA | D23: 13 | E23: 23 | F23: 1241 | G23: 4 | H23: =IF($G23="","",IFERROR(LOOKUP(VALUE(LEFT($G23&"",FIND("-",$G23&"-")-1)),$C$34:$C$39,$D$34:$D$39),"")) -> 300 | I23: 300 | J23: =IF($I23="","n/a",IF($H23=$I23,"ok","MISMATCH")) -> ok | K23: 140000 | L23: overperformed seed (13 → 4) | N23: BBL Esports
B24: Gentle Mates | C24: VCT EMEA | D24: 14 | E24: 29 | F24: 1220 | G24: 5-8 | H24: =IF($G24="","",IFERROR(LOOKUP(VALUE(LEFT($G24&"",FIND("-",$G24&"-")-1)),$C$34:$C$39,$D$34:$D$39),"")) -> 200 | I24: 200 | J24: =IF($I24="","n/a",IF($H24=$I24,"ok","MISMATCH")) -> ok | K24: 90000 | L24: overperformed seed (14 → 5-8) | N24: Gentle Mates
B25: AG.AL International | C25: VCT CN | D25: 15 | E25: 31 | F25: 1215 | G25: 9-12 | H25: =IF($G25="","",IFERROR(LOOKUP(VALUE(LEFT($G25&"",FIND("-",$G25&"-")-1)),$C$34:$C$39,$D$34:$D$39),"")) -> 0 | I25: 0 | J25: =IF($I25="","n/a",IF($H25=$I25,"ok","MISMATCH")) -> ok | K25: 55000 | L25: overperformed seed (15 → 9-12) | N25: AG.AL International
B26: Karmine Corp | C26: VCT EMEA | D26: 16 | E26: 41 | F26: 1126 | G26: 9-12 | H26: =IF($G26="","",IFERROR(LOOKUP(VALUE(LEFT($G26&"",FIND("-",$G26&"-")-1)),$C$34:$C$39,$D$34:$D$39),"")) -> 0 | I26: 0 | J26: =IF($I26="","n/a",IF($H26=$I26,"ok","MISMATCH")) -> ok | K26: 55000 | L26: overperformed seed (16 → 9-12) | N26: Karmine Corp
B28: TOTAL POINTS AWARDED | H28: =SUM(H11:H26) -> 3350
B29: 3,350 club points — standard playoff curve. Prize money sums to the full $2,000,000.
B32: 2 · POINT SYSTEM
B33: From place | C33: Club points | D33: Band
C34: 1 | D34: 1000 | E34: 1st
C35: 2 | D35: 750 | E35: 2nd
C36: 3 | D36: 500 | E36: 3rd
C37: 4 | D37: 300 | E37: 4th
C38: 5 | D38: 200 | E38: 5th-8th
C39: 9 | D39: 0 | E39: 9th-16th
B42: 3 · SEED SOURCE — RIOT GPR, AND ITS TIMING PROBLEM
B43: This is the cleanest seed source in the workbook. Riot maintains the GPR themselves: a model with numeric power scores covering 48 teams across all four VCT leagues, so cross-region comparison is built into the number rather than assumed. That is exactly what the Rainbow Six and Dota sources lack. AND THE TIMING IS RIGHT. Riot publishes event-pinned snapshots, so the 'End of Masters London' table dated 21 June 2026 sits eleven days before this event began on 2 July. No result leakage, no stale season. Method A, not a proxy. WHAT 2026 SHOWED: the seed underperformed, and unusually it failed at the TOP rather than the middle. GPR #1 Paper Rex, on 1,605 points and 200 clear of second, finished 13th-16th — the largest single miss in the workbook. Global Esports (seed 8) also went out in 13th-16th. Meanwhile champion 100 Thieves came from seed 7, BBL Esports reached 4th from seed 13, Gentle Mates made the top eight from seed 14, and Karmine Corp entered last on 1,126 points and still finished 9th-12th. That inverts the pattern seen in chess, Trackmania, Tekken and R6, where the elite converted and the middle scattered. Here the elite was the problem. Two readings, unresolvable from one event: either Valorant genuinely punishes favourites more than the TVI of 50 allows, or a strong GPR score built on VCT league form does not transfer to a short offline bracket. WORTH NOTING: GPR #2 Leviatán, #4 T1, #6 Kiwoom DRX and #9 Fnatic did not attend. This was not the world's strongest sixteen, which caps how much any seed could have explained.
B52: GPR rank | C52: Team | D52: Score | E52: League | F52: At EWC?
B53: 1 | C53: Paper Rex | D53: 1605 | E53: VCT Pacific | F53: Yes
B54: 2 | C54: Leviatán Esports | D54: 1544 | E54: VCT Americas | F54: no
B55: 3 | C55: NONGSHIM REDFORCE | D55: 1434 | E55: VCT Pacific | F55: Yes
B56: 4 | C56: T1 | D56: 1423 | E56: VCT Pacific | F56: no
B57: 5 | C57: NRG | D57: 1403 | E57: VCT Americas | F57: Yes
B58: 6 | C58: Kiwoom DRX | D58: 1401 | E58: VCT Pacific | F58: no
B59: 7 | C59: Team Vitality | D59: 1397 | E59: VCT EMEA | F59: Yes
B60: 8 | C60: G2 Esports | D60: 1360 | E60: VCT Americas | F60: Yes
B61: 9 | C61: FNATIC | D61: 1355 | E61: VCT EMEA | F61: no
B62: 10 | C62: EDWARD Gaming | D62: 1342 | E62: VCT CN | F62: Yes
B63: 11 | C63: 100 Thieves | D63: 1324 | E63: VCT Americas | F63: Yes
B64: 12 | C64: GLOBAL ESPORTS | D64: 1318 | E64: VCT Pacific | F64: Yes
... B76: 24 | C76: GIANTX | D76: 1236 | E76: VCT EMEA | F76: no

Sheet MLBB (MSC)
B2: MLBB Mid Season Cup — EWC 2026
B3: The men's MLBB event at EWC. Cohort seeding applied by rule from the qualifying league: MPL Indonesia and MPL Philippines = High, other SEA leagues = Medium, everything else = Low.
B5: FORMAT | D5: FIELD SIZE | F5: TVI | H5: SEED METHOD | J5: SEED SOURCE | L5: PLACEMENT GRANULARITY
B6: Wildcard → double-elim groups → single-elim | D6: 25 teams | F6: 60 · Medium | H6: D — cohort by league | J6: Qualifying league (MPL ID/PH = High) | L6: Bands (5-8, 9-12, 13-16, then pairs)
B8: 1 · FIELD & RESULTS
B9: All 25 teams. League of origin comes from the official qualification table. Where a club fields two teams, the canonical column maps the entry to the parent club — only the better finisher earns club points, so reconciliation takes a MAX over the canonical name.
B10: Entry | C10: Club (canonical) | D10: Qualifying league | E10: Cohort | F10: Placement | G10: Points (auto) | H10: Official CC pts | I10: Δ check | J10: Prize (USD) | K10: Notes | M10: Club (canonical)
B11: Team Spirit | C11: Team Spirit | D11: MCC (EECA) | E11: Low | F11: 1 | G11: =IF($F11="","",IFERROR(LOOKUP(VALUE(LEFT($F11&"",FIND("-",$F11&"-")-1)),$C$44:$C$49,$D$44:$D$49),"")) -> 1000 | H11: 1000 | I11: =IF($H11="","n/a",IF($G11=$H11,"ok","MISMATCH")) -> ok | J11: 1000000 | K11: first EECA club to win an MLBB major | M11: Team Spirit
B12: Yangon Galacticos | C12: Yangon Galacticos | D12: MSL Myanmar | E12: Medium | F12: 2 | G12: =IF($F12="","",IFERROR(LOOKUP(VALUE(LEFT($F12&"",FIND("-",$F12&"-")-1)),$C$44:$C$49,$D$44:$D$49),"")) -> 750 | H12: 750 | I12: =IF($H12="","n/a",IF($G12=$H12,"ok","MISMATCH")) -> ok | J12: 500000 | M12: Yangon Galacticos
B13: ONIC | C13: ONIC | D13: MPL Indonesia | E13: High | F13: 3 | G13: =IF($F13="","",IFERROR(LOOKUP(VALUE(LEFT($F13&"",FIND("-",$F13&"-")-1)),$C$44:$C$49,$D$44:$D$49),"")) -> 500 | H13: 500 | I13: =IF($H13="","n/a",IF($G13=$H13,"ok","MISMATCH")) -> ok | J13: 250000 | M13: ONIC
B14: Team Falcons PH | C14: Team Falcons | D14: MPL Philippines | E14: High | F14: 4 | G14: =IF($F14="","",IFERROR(LOOKUP(VALUE(LEFT($F14&"",FIND("-",$F14&"-")-1)),$C$44:$C$49,$D$44:$D$49),"")) -> 300 | H14: 300 | I14: =IF($H14="","n/a",IF($G14=$H14,"ok","MISMATCH")) -> ok | J14: 150000 | K14: second Team Falcons entry — only the better finisher scores | M14: Team Falcons
B15: Team Vamos | C15: Team Vamos | D15: MPL Malaysia | E15: Medium | F15: 5-8 | G15: =IF($F15="","",IFERROR(LOOKUP(VALUE(LEFT($F15&"",FIND("-",$F15&"-")-1)),$C$44:$C$49,$D$44:$D$49),"")) -> 200 | H15: 200 | I15: =IF($H15="","n/a",IF($G15=$H15,"ok","MISMATCH")) -> ok | J15: 100000 | M15: Team Vamos
B16: Aurora Gaming | C16: Aurora Gaming | D16: MTC (Turkey) | E16: Low | F16: 5-8 | G16: =IF($F16="","",IFERROR(LOOKUP(VALUE(LEFT($F16&"",FIND("-",$F16&"-")-1)),$C$44:$C$49,$D$44:$D$49),"")) -> 200 | H16: 200 | I16: =IF($H16="","n/a",IF($G16=$H16,"ok","MISMATCH")) -> ok | J16: 100000 | M16: Aurora Gaming
B17: Team Vitality | C17: Team Vitality | D17: MPL Indonesia | E17: High | F17: 5-8 | G17: =IF($F17="","",IFERROR(LOOKUP(VALUE(LEFT($F17&"",FIND("-",$F17&"-")-1)),$C$44:$C$49,$D$44:$D$49),"")) -> 200 | H17: 200 | I17: =IF($H17="","n/a",IF($G17=$H17,"ok","MISMATCH")) -> ok | J17: 100000 | K17: competes as Bigetron by Vitality | M17: Team Vitality
B18: PRO Esports | C18: PRO Esports | D18: MPL Cambodia | E18: Medium | F18: 5-8 | G18: =IF($F18="","",IFERROR(LOOKUP(VALUE(LEFT($F18&"",FIND("-",$F18&"-")-1)),$C$44:$C$49,$D$44:$D$49),"")) -> 200 | H18: 200 | I18: =IF($H18="","n/a",IF($G18=$H18,"ok","MISMATCH")) -> ok | J18: 100000 | M18: PRO Esports
B19: Guangzhou Gaming | C19: Guangzhou Gaming | D19: MCT East Asia | E19: Low | F19: 9-12 | G19: =IF($F19="","",IFERROR(LOOKUP(VALUE(LEFT($F19&"",FIND("-",$F19&"-")-1)),$C$44:$C$49,$D$44:$D$49),"")) -> 0 | I19: =IF($H19="","n/a",IF($G19=$H19,"ok","MISMATCH")) -> n/a | J19: 65000 | M19: Guangzhou Gaming
B20: Team Falcons | C20: Team Falcons | D20: MPL MENA | E20: Low | F20: 9-12 | G20: =IF($F20="","",IFERROR(LOOKUP(VALUE(LEFT($F20&"",FIND("-",$F20&"-")-1)),$C$44:$C$49,$D$44:$D$49),"")) -> 0 | I20: =IF($H20="","n/a",IF($G20=$H20,"ok","MISMATCH")) -> n/a | J20: 65000 | M20: Team Falcons
B21: Selangor Red Giants | C21: Selangor Red Giants | D21: MPL Malaysia | E21: Medium | F21: 9-12 | G21: =IF($F21="","",IFERROR(LOOKUP(VALUE(LEFT($F21&"",FIND("-",$F21&"-")-1)),$C$44:$C$49,$D$44:$D$49),"")) -> 0 | I21: =IF($H21="","n/a",IF($G21=$H21,"ok","MISMATCH")) -> n/a | J21: 65000 | M21: Selangor Red Giants
B22: Entity7 | C22: Entity7 | D22: MCT Americas | E22: Low | F22: 9-12 | G22: =IF($F22="","",IFERROR(LOOKUP(VALUE(LEFT($F22&"",FIND("-",$F22&"-")-1)),$C$44:$C$49,$D$44:$D$49),"")) -> 0 | I22: =IF($H22="","n/a",IF($G22=$H22,"ok","MISMATCH")) -> n/a | J22: 65000 | M22: Entity7
B23: True Rippers | C23: True Rippers | D23: ML Masters Series | E23: Low | F23: 13-16 | G23: =IF($F23="","",IFERROR(LOOKUP(VALUE(LEFT($F23&"",FIND("-",$F23&"-")-1)),$C$44:$C$49,$D$44:$D$49),"")) -> 0 | I23: =IF($H23="","n/a",IF($G23=$H23,"ok","MISMATCH")) -> n/a | J23: 45000 | M23: True Rippers
B24: IGNITE Gaming | C24: IGNITE Gaming | D24: MPL Singapore | E24: Medium | F24: 13-16 | G24: =IF($F24="","",IFERROR(LOOKUP(VALUE(LEFT($F24&"",FIND("-",$F24&"-")-1)),$C$44:$C$49,$D$44:$D$49),"")) -> 0 | I24: =IF($H24="","n/a",IF($G24=$H24,"ok","MISMATCH")) -> n/a | J24: 45000 | M24: IGNITE Gaming
B25: Geekay Esports | C25: Geekay Esports | D25: MPL MENA | E25: Low | F25: 13-16 | G25: =IF($F25="","",IFERROR(LOOKUP(VALUE(LEFT($F25&"",FIND("-",$F25&"-")-1)),$C$44:$C$49,$D$44:$D$49),"")) -> 0 | H25: 0 | I25: =IF($H25="","n/a",IF($G25=$H25,"ok","MISMATCH")) -> ok | J25: 45000 | M25: Geekay Esports
B26: Team Liquid PH | C26: Team Liquid | D26: MPL Philippines | E26: High | F26: 13-16 | G26: =IF($F26="","",IFERROR(LOOKUP(VALUE(LEFT($F26&"",FIND("-",$F26&"-")-1)),$C$44:$C$49,$D$44:$D$49),"")) -> 0 | H26: 0 | I26: =IF($H26="","n/a",IF($G26=$H26,"ok","MISMATCH")) -> ok | J26: 45000 | K26: second Team Liquid entry — only the better finisher scores | M26: Team Liquid
B27: The Huns Esports | C27: The Huns Esports | D27: MCT East Asia | E27: Low | F27: 17 | G27: =IF($F27="","",IFERROR(LOOKUP(VALUE(LEFT($F27&"",FIND("-",$F27&"-")-1)),$C$44:$C$49,$D$44:$D$49),"")) -> 0 | I27: =IF($H27="","n/a",IF($G27=$H27,"ok","MISMATCH")) -> n/a | J27: 35000 | M27: The Huns Esports
B28: FUT Esports | C28: FUT Esports | D28: MTC (Turkey) | E28: Low | F28: 18-19 | G28: =IF($F28="","",IFERROR(LOOKUP(VALUE(LEFT($F28&"",FIND("-",$F28&"-")-1)),$C$44:$C$49,$D$44:$D$49),"")) -> 0 | H28: 0 | I28: =IF($H28="","n/a",IF($G28=$H28,"ok","MISMATCH")) -> ok | J28: 31500 | M28: FUT Esports
B29: Alpha7 Esports | C29: Alpha7 Esports | D29: MCT Americas | E29: Low | F29: 18-19 | G29: =IF($F29="","",IFERROR(LOOKUP(VALUE(LEFT($F29&"",FIND("-",$F29&"-")-1)),$C$44:$C$49,$D$44:$D$49),"")) -> 0 | H29: 0 | I29: =IF($H29="","n/a",IF($G29=$H29,"ok","MISMATCH")) -> ok | J29: 31500 | M29: Alpha7 Esports
B30: King of Gamers Club | C30: King of Gamers Club | D30: MSL Thailand | E30: Medium | F30: 20-21 | G30: =IF($F30="","",IFERROR(LOOKUP(VALUE(LEFT($F30&"",FIND("-",$F30&"-")-1)),$C$44:$C$49,$D$44:$D$49),"")) -> 0 | I30: =IF($H30="","n/a",IF($G30=$H30,"ok","MISMATCH")) -> n/a | J30: 29000 | M30: King of Gamers Club
B31: Niightmare Esports | C31: Niightmare Esports | D31: MCCM | E31: Low | F31: 20-21 | G31: =IF($F31="","",IFERROR(LOOKUP(VALUE(LEFT($F31&"",FIND("-",$F31&"-")-1)),$C$44:$C$49,$D$44:$D$49),"")) -> 0 | I31: =IF($H31="","n/a",IF($G31=$H31,"ok","MISMATCH")) -> n/a | J31: 29000 | M31: Niightmare Esports
B32: Sunset Ravens | C32: Sunset Ravens | D32: MCT East Asia | E32: Low | F32: 22-23 | G32: =IF($F32="","",IFERROR(LOOKUP(VALUE(LEFT($F32&"",FIND("-",$F32&"-")-1)),$C$44:$C$49,$D$44:$D$49),"")) -> 0 | I32: =IF($H32="","n/a",IF($G32=$H32,"ok","MISMATCH")) -> n/a | J32: 27000 | M32: Sunset Ravens
B33: The MongolZ | C33: The MongolZ | D33: MCT East Asia | E33: Low | F33: 22-23 | G33: =IF($F33="","",IFERROR(LOOKUP(VALUE(LEFT($F33&"",FIND("-",$F33&"-")-1)),$C$44:$C$49,$D$44:$D$49),"")) -> 0 | I33: =IF($H33="","n/a",IF($G33=$H33,"ok","MISMATCH")) -> n/a | J33: 27000 | M33: The MongolZ
B34: VSG | C34: VSG | D34: MEC | E34: Low | F34: 24-25 | G34: =IF($F34="","",IFERROR(LOOKUP(VALUE(LEFT($F34&"",FIND("-",$F34&"-")-1)),$C$44:$C$49,$D$44:$D$49),"")) -> 0 | I34: =IF($H34="","n/a",IF($G34=$H34,"ok","MISMATCH")) -> n/a | J34: 25000 | M34: VSG
B35: Verso Time | C35: Verso Time | D35: MCC (EECA) | E35: Low | F35: 24-25 | G35: =IF($F35="","",IFERROR(LOOKUP(VALUE(LEFT($F35&"",FIND("-",$F35&"-")-1)),$C$44:$C$49,$D$44:$D$49),"")) -> 0 | I35: =IF($H35="","n/a",IF($G35=$H35,"ok","MISMATCH")) -> n/a | J35: 25000 | M35: Verso Time
B37: TOTAL POINTS AWARDED | G37: =SUM(G11:G35) -> 3350
B38: 3,350 club points — standard playoff curve. Prize money sums to $3,000,000 of the $3,025,000 pool; the balance is an MVP-style award. Note this is the richest single title in the workbook.
B42: 2 · POINT SYSTEM
B43: From place | C43: Club points | D43: Band
C44: 1 | D44: 1000 | E44: 1st
C45: 2 | D45: 750 | E45: 2nd
C46: 3 | D46: 500 | E46: 3rd
C47: 4 | D47: 300 | E47: 4th
C48: 5 | D48: 200 | E48: 5th-8th
C49: 9 | D49: 0 | E49: 9th-25th
B52: 3 · COHORT RULE AND HOW IT PERFORMED
B53: THE RULE: High = MPL Indonesia and MPL Philippines. Medium = the other Southeast Asian leagues (Malaysia, Singapore, Cambodia, Myanmar, Thailand). Low = everything else — EECA, Turkey, MENA, Americas, East Asia, India. Applied from the qualifying league recorded on the official qualification table, so it derives from sourced data rather than inference about club origin. IT SEPARATED WELL. High converted three of four entries into top-eight finishes (75%), Medium three of six (50%), Low two of fifteen (13%), against a baseline of 32%. That is the cleanest cohort separation in the workbook and supports treating MPL ID and PH as the strongest leagues. BUT THE WINNER CAME FROM LOW. Team Spirit qualified through MCC, the EECA circuit, and won the whole thing — the first EECA club to take an MLBB major. Yangon Galacticos took second from Myanmar, a Medium league. So the rule ranked the FIELD well while missing the PODIUM entirely: neither finalist came from a High cohort league, and the best High finish was ONIC in 3rd. This is the same tension seen elsewhere — a seed that predicts who makes the top eight is not automatically a seed that predicts who wins. With a TVI of 60 the model should already expect upsets of this size; worth rechecking after the next edition rather than adjusting either input now.
B61: Cohort | C61: Teams (auto) | D61: Top-8 finishes | E61: Top-8 rate | F61: Best result | G61: Band from | H61: Band to
B62: High | C62: =COUNTIF($E$11:$E$35,$B62) -> 4 | D62: =SUMPRODUCT(($E$11:$E$35=$B62)*($G$11:$G$35>0)) -> 3 | E62: =IF(C62=0,"",D62/C62) -> 0.75 | F62: =IFERROR(SUMPRODUCT(MAX(($E$11:$E$35=$B62)*$G$11:$G$35)),0) -> 500 | G62: =1 -> 1 | H62: =G62+C62-1 -> 4
B63: Medium | C63: =COUNTIF($E$11:$E$35,$B63) -> 6 | D63: =SUMPRODUCT(($E$11:$E$35=$B63)*($G$11:$G$35>0)) -> 3 | E63: =IF(C63=0,"",D63/C63) -> 0.5 | F63: =IFERROR(SUMPRODUCT(MAX(($E$11:$E$35=$B63)*$G$11:$G$35)),0) -> 750 | G63: =H62+1 -> 5 | H63: =G63+C63-1 -> 10
B64: Low | C64: =COUNTIF($E$11:$E$35,$B64) -> 15 | D64: =SUMPRODUCT(($E$11:$E$35=$B64)*($G$11:$G$35>0)) -> 2 | E64: =IF(C64=0,"",D64/C64) -> 0.13333333 | F64: =IFERROR(SUMPRODUCT(MAX(($E$11:$E$35=$B64)*$G$11:$G$35)),0) -> 1000 | G64: =H63+1 -> 11 | H64: =G64+C64-1 -> 25
B66: Baseline top-8 rate is 8/25 = 32%. Bands re-tile automatically if you reassign a cohort.

Sheet Apex Legends
B2: Apex Legends — EWC 2026
B3: Run as the ALGS 2026 Split 1 Playoffs. Cohorts applied by rule from Split 1 Pro League regional finishing position.
B5: FORMAT | D5: FIELD SIZE | F5: TVI | H5: SEED METHOD | J5: SEED SOURCE | L5: PLACEMENT GRANULARITY
B6: Groups → Survivor → Finals | D6: 40 trios | F6: 82 · High | H6: D — cohort by Pro League | J6: ALGS 2026 Split 1 Pro League | L6: Exact 1-40
B8: 1 · FIELD & RESULTS
B9: All 40 trios. Region and Pro League placement come from the four Split 1 regional standings pages, so the cohort derives from sourced data. ZEDI ESPORTS' 300 points are voided — squad signed past the Team Deadline.
B10: Club | C10: Region | D10: PL place | E10: Cohort | F10: Placement | G10: Points (auto) | H10: CC eligible? | I10: Eligible pts | J10: Official CC pts | K10: Δ check | L10: Prize (USD) | M10: Notes | O10: Club (canonical)
B11: UNLIMIT | C11: APAC North | D11: 3 | E11: High | F11: 1 | G11: =IF($F11="","",IFERROR(LOOKUP(VALUE($F11),$C$56:$C$64,$D$56:$D$64),"")) -> 1000 | H11: Yes | I11: =IF($H11="VOID",0,$G11) -> 1000 | J11: 1000 | K11: =IF($J11="","n/a",IF($I11=$J11,"ok","MISMATCH")) -> ok | L11: 600000 | O11: UNLIMIT
B12: Team Vision | C12: Americas | D12: 3 | E12: High | F12: 2 | G12: =IF($F12="","",IFERROR(LOOKUP(VALUE($F12),$C$56:$C$64,$D$56:$D$64),"")) -> 750 | H12: Yes | I12: =IF($H12="VOID",0,$G12) -> 750 | J12: 750 | K12: =IF($J12="","n/a",IF($I12=$J12,"ok","MISMATCH")) -> ok | L12: 300000 | O12: Team Vision
B13: Sentinels | C13: Americas | D13: 7 | E13: Medium | F13: 3 | G13: =IF($F13="","",IFERROR(LOOKUP(VALUE($F13),$C$56:$C$64,$D$56:$D$64),"")) -> 500 | H13: Yes | I13: =IF($H13="VOID",0,$G13) -> 500 | J13: 500 | K13: =IF($J13="","n/a",IF($I13=$J13,"ok","MISMATCH")) -> ok | L13: 200000 | O13: Sentinels
B14: ZEDI ESPORTS | C14: Americas | D14: 11 | E14: Medium | F14: 4 | G14: =IF($F14="","",IFERROR(LOOKUP(VALUE($F14),$C$56:$C$64,$D$56:$D$64),"")) -> 300 | H14: VOID | I14: =IF($H14="VOID",0,$G14) -> 0 | K14: =IF($J14="","n/a",IF($I14=$J14,"ok","MISMATCH")) -> n/a | L14: 150000 | M14: VOIDED — squad signed past the Team Deadline | O14: ZEDI ESPORTS
B15: ZETA DIVISION | C15: APAC North | D15: 1 | E15: High | F15: 5 | G15: =IF($F15="","",IFERROR(LOOKUP(VALUE($F15),$C$56:$C$64,$D$56:$D$64),"")) -> 200 | H15: Yes | I15: =IF($H15="VOID",0,$G15) -> 200 | J15: 200 | K15: =IF($J15="","n/a",IF($I15=$J15,"ok","MISMATCH")) -> ok | L15: 125000 | O15: ZETA DIVISION
B16: All Gamers Global | C16: Americas | D16: 8 | E16: Medium | F16: 6 | G16: =IF($F16="","",IFERROR(LOOKUP(VALUE($F16),$C$56:$C$64,$D$56:$D$64),"")) -> 150 | H16: Yes | I16: =IF($H16="VOID",0,$G16) -> 150 | J16: 150 | K16: =IF($J16="","n/a",IF($I16=$J16,"ok","MISMATCH")) -> ok | L16: 100000 | O16: AG.AL International
B17: Wolves Esports | C17: APAC South | D17: 1 | E17: High | F17: 7 | G17: =IF($F17="","",IFERROR(LOOKUP(VALUE($F17),$C$56:$C$64,$D$56:$D$64),"")) -> 100 | H17: Yes | I17: =IF($H17="VOID",0,$G17) -> 100 | J17: 100 | K17: =IF($J17="","n/a",IF($I17=$J17,"ok","MISMATCH")) -> ok | L17: 80000 | O17: Wolves Esports
B18: Team Falcons | C18: Americas | D18: 4 | E18: High | F18: 8 | G18: =IF($F18="","",IFERROR(LOOKUP(VALUE($F18),$C$56:$C$64,$D$56:$D$64),"")) -> 50 | H18: Yes | I18: =IF($H18="VOID",0,$G18) -> 50 | J18: 50 | K18: =IF($J18="","n/a",IF($I18=$J18,"ok","MISMATCH")) -> ok | L18: 60000 | O18: Team Falcons
B19: Team Liquid | C19: Americas | D19: 6 | E19: Medium | F19: 9 | G19: =IF($F19="","",IFERROR(LOOKUP(VALUE($F19),$C$56:$C$64,$D$56:$D$64),"")) -> 0 | H19: Yes | I19: =IF($H19="VOID",0,$G19) -> 0 | J19: 0 | K19: =IF($J19="","n/a",IF($I19=$J19,"ok","MISMATCH")) -> ok | L19: 50000 | O19: Team Liquid
B20: Rex Regum Qeon | C20: APAC South | D20: 6 | E20: Medium | F20: 10 | G20: =IF($F20="","",IFERROR(LOOKUP(VALUE($F20),$C$56:$C$64,$D$56:$D$64),"")) -> 0 | H20: Yes | I20: =IF($H20="VOID",0,$G20) -> 0 | J20: 0 | K20: =IF($J20="","n/a",IF($I20=$J20,"ok","MISMATCH")) -> ok | L20: 40000 | O20: Rex Regum Qeon
B21: REJECT | C21: APAC North | D21: 2 | E21: High | F21: 11 | G21: =IF($F21="","",IFERROR(LOOKUP(VALUE($F21),$C$56:$C$64,$D$56:$D$64),"")) -> 0 | H21: Yes | I21: =IF($H21="VOID",0,$G21) -> 0 | J21: 0 | K21: =IF($J21="","n/a",IF($I21=$J21,"ok","MISMATCH")) -> ok | L21: 30000 | O21: REJECT
B22: Alliance | C22: EMEA | D22: 4 | E22: High | F22: 12 | G22: =IF($F22="","",IFERROR(LOOKUP(VALUE($F22),$C$56:$C$64,$D$56:$D$64),"")) -> 0 | H22: Yes | I22: =IF($H22="VOID",0,$G22) -> 0 | K22: =IF($J22="","n/a",IF($I22=$J22,"ok","MISMATCH")) -> n/a | L22: 27000 | O22: Alliance
B23: Elite Esports Europe | C23: EMEA | D23: 5 | E23: High | F23: 13 | G23: =IF($F23="","",IFERROR(LOOKUP(VALUE($F23),$C$56:$C$64,$D$56:$D$64),"")) -> 0 | H23: Yes | I23: =IF($H23="VOID",0,$G23) -> 0 | K23: =IF($J23="","n/a",IF($I23=$J23,"ok","MISMATCH")) -> n/a | L23: 24000 | O23: Elite Esports Europe
B24: Team Nemesis | C24: Americas | D24: 13 | E24: Low | F24: 14 | G24: =IF($F24="","",IFERROR(LOOKUP(VALUE($F24),$C$56:$C$64,$D$56:$D$64),"")) -> 0 | H24: Yes | I24: =IF($H24="VOID",0,$G24) -> 0 | J24: 0 | K24: =IF($J24="","n/a",IF($I24=$J24,"ok","MISMATCH")) -> ok | L24: 22000 | O24: Team Nemesis
B25: Ninjas in Pyjamas | C25: Americas | D25: 1 | E25: High | F25: 15 | G25: =IF($F25="","",IFERROR(LOOKUP(VALUE($F25),$C$56:$C$64,$D$56:$D$64),"")) -> 0 | H25: Yes | I25: =IF($H25="VOID",0,$G25) -> 0 | J25: 0 | K25: =IF($J25="","n/a",IF($I25=$J25,"ok","MISMATCH")) -> ok | L25: 20000 | O25: Ninjas in Pyjamas
B26: S8UL Esports | C26: APAC South | D26: 2 | E26: High | F26: 16 | G26: =IF($F26="","",IFERROR(LOOKUP(VALUE($F26),$C$56:$C$64,$D$56:$D$64),"")) -> 0 | H26: Yes | I26: =IF($H26="VOID",0,$G26) -> 0 | J26: 0 | K26: =IF($J26="","n/a",IF($I26=$J26,"ok","MISMATCH")) -> ok | L26: 18000 | O26: S8UL Esports
B27: Geekay Esports | C27: Americas | D27: 9 | E27: Medium | F27: 17 | G27: =IF($F27="","",IFERROR(LOOKUP(VALUE($F27),$C$56:$C$64,$D$56:$D$64),"")) -> 0 | H27: Yes | I27: =IF($H27="VOID",0,$G27) -> 0 | J27: 0 | K27: =IF($J27="","n/a",IF($I27=$J27,"ok","MISMATCH")) -> ok | L27: 16000 | O27: Geekay Esports
B28: For Fun Esports | C28: EMEA | D28: 3 | E28: High | F28: 18 | G28: =IF($F28="","",IFERROR(LOOKUP(VALUE($F28),$C$56:$C$64,$D$56:$D$64),"")) -> 0 | H28: Yes | I28: =IF($H28="VOID",0,$G28) -> 0 | K28: =IF($J28="","n/a",IF($I28=$J28,"ok","MISMATCH")) -> n/a | L28: 14000 | O28: For Fun Esports
B29: Gaimin Gladiators | C29: EMEA | D29: 6 | E29: Medium | F29: 19 | G29: =IF($F29="","",IFERROR(LOOKUP(VALUE($F29),$C$56:$C$64,$D$56:$D$64),"")) -> 0 | H29: Yes | I29: =IF($H29="VOID",0,$G29) -> 0 | K29: =IF($J29="","n/a",IF($I29=$J29,"ok","MISMATCH")) -> n/a | L29: 12000 | O29: Gaimin Gladiators
B30: ENTER FORCE.36 | C30: APAC North | D30: 4 | E30: High | F30: 20 | G30: =IF($F30="","",IFERROR(LOOKUP(VALUE($F30),$C$56:$C$64,$D$56:$D$64),"")) -> 0 | H30: Yes | I30: =IF($H30="VOID",0,$G30) -> 0 | K30: =IF($J30="","n/a",IF($I30=$J30,"ok","MISMATCH")) -> n/a | L30: 10000 | O30: ENTER FORCE.36
B31: ZiPLine Mafia | C31: EMEA | D31: 10 | E31: Low | F31: 21 | G31: =IF($F31="","",IFERROR(LOOKUP(VALUE($F31),$C$56:$C$64,$D$56:$D$64),"")) -> 0 | H31: Yes | I31: =IF($H31="VOID",0,$G31) -> 0 | K31: =IF($J31="","n/a",IF($I31=$J31,"ok","MISMATCH")) -> n/a | L31: 9000 | O31: ZiPLine Mafia
B32: DINOS | C32: Americas | D32: 10 | E32: Medium | F32: 22 | G32: =IF($F32="","",IFERROR(LOOKUP(VALUE($F32),$C$56:$C$64,$D$56:$D$64),"")) -> 0 | H32: Yes | I32: =IF($H32="VOID",0,$G32) -> 0 | K32: =IF($J32="","n/a",IF($I32=$J32,"ok","MISMATCH")) -> n/a | L32: 8250 | O32: DINOS
B33: JD Gaming | C33: Americas | D33: 2 | E33: High | F33: 23 | G33: =IF($F33="","",IFERROR(LOOKUP(VALUE($F33),$C$56:$C$64,$D$56:$D$64),"")) -> 0 | H33: Yes | I33: =IF($H33="VOID",0,$G33) -> 0 | J33: 0 | K33: =IF($J33="","n/a",IF($I33=$J33,"ok","MISMATCH")) -> ok | L33: 7500 | O33: JD Gaming
B34: Shopify Rebellion | C34: Americas | D34: 5 | E34: High | F34: 24 | G34: =IF($F34="","",IFERROR(LOOKUP(VALUE($F34),$C$56:$C$64,$D$56:$D$64),"")) -> 0 | H34: Yes | I34: =IF($H34="VOID",0,$G34) -> 0 | J34: 0 | K34: =IF($J34="","n/a",IF($I34=$J34,"ok","MISMATCH")) -> ok | L34: 7000 | O34: Shopify Rebellion
